Workbook
Name DETENIDO: Hoja1!$Y:$Y
Name CONTRAVENTOR: Hoja1!$X:$X
Name TIPIFICACION: Hoja1!$K:$K

Sheet Hoja1
A1: FECHA | B1: HORA | C1: FRANJA HORARIA | D1: JEFE DE SERVICIO | E1: OFICIAL | F1: GRUPO | G1: OPERADOR | H1: GAP | I1: SAE | J1: UBICACIÓN | K1: TIPIFICACIÓN | L1: SUBTIPIFICACION | M1: TIPO EVENTO | N1: CAMARA | O1: BARRIO | P1: INICIO | Q1: FIN | R1: PC | S1: SAME | T1: BOMBEROS | U1: OTROS | V1: HORARIO | W1: RESEÑA | X1: CONTRAVENTORES | Y1: DETENIDOS | Z1: PERS. TRASLADADA | AA1: COMUNA | AB1: OBSERVACIONES | AC1: ORIGEN | AD1: SISEP/ANILLO | AE1: COMENTARIO | AF1: TIPO DE CIERRE | AG1: ERRORES DE CIERRE | AH1: OTROS ERRORES | AI1: OTRAS IMPUTACIONES | AJ1: ACLARACIONES | AK1: GAP | AL1: LP/DNI | AM1: imp | AN1: corr
A2: 45992 | B2: =IF(AND(VALUE(P2)>=VALUE("06:00"),VALUE(P2)<=VALUE("17:59")),"06 A 18","18 A 06") -> 18 A 06 | C2: =IF(AND(VALUE(P2)>=VALUE("00:00"),VALUE(P2)<=VALUE("01:59")),"00:00 a 02:00",IF(AND(VALUE(P2)>=VALUE("02:00"),VALUE(P2)<=VALUE("03:59")),"02:00 a 04:00",IF(AND(VALUE(P2)>=VALUE("04:00"),VALUE(P2)<=VALUE("05:59")),"04:00 a 06:00",IF(AND(VALUE(P2)>=VALUE("06:00"),VALUE(P2)<=VALUE("07:59")),"06:00 a 08:00",IF(AND(VALUE(P2)>=VALUE("08:00"),VALUE(P2)<=VALUE("09:59")),"08:00 a 10:00",IF(AND(VALUE(P2)>=VALUE("10:00"),VALUE(P2)<=VALUE("11:59")),"10:00 a 12:00",IF(AND(VALUE(P2)>=VALUE("12:00"),VALUE(P2)<=VALUE("13:59")),"12:00 a 14:00",IF(AND(VALUE(P2)>=VALUE("14:00"),VALUE(P2)<=VALUE("15:59")),"14:00 a 16:00",IF(AND(VALUE(P2)>=VALUE("16:00"),VALUE(P2)<=VALUE("17:59")),"16:00 a 18:00",IF(AND(VALUE(P2)>=VALUE("18:00"),VALUE(P2)<=VALUE("19:59")),"18:00 a 20:00",IF(AND(VALUE(P2)>=VALUE("20:00"),VALUE(P2)<=VALUE("21:59")),"20:00 a 22:00",IF(AND(VALUE(P2)>=VALUE("22:00"),VALUE(P2)<=VALUE("23:59")),"22:00 a 00:00","no corresponde")))))))))))) -> 00:00 a 02:00 | D2: ARGUELLO | E2: QUINTANA, GILDA | F2: 3 | G2: VILLANUEVA, CELESTE | H2: 919892 | I2: 46736933 | J2: CHACARITA | K2: COLABORACION | L2: ROBO/HURTO | N2: PALERMO O203 | O2: Palermo | P2: 0.014583333 | Q2: 0.035416667 | R2: 0.014583333 | S2: - | T2: - | U2: - | V2: - | W2: SE TOMA CONOCIMIENTO POR MEDIO DE LA CARTA SAE N° 46736933 DENUNCIANTE REFIERE QUE LE HABRIAN SUSTRAIDO LA BICICLETA. SIENDO LAS 00:21 HS. SE OBSERVA POR LA CAMARA PALERMOO203 EMPLAZADA EN MEDRANO 1038 Y CORDOBA DONDE SE VISUALIZA AL PERSONAL POLICIAL ENTREVISTANDO A UNA FEMENINA Y A UN MASCULINO. 00:51 HS. SE RETIRA EL MOVIL POLICIAL DANDO ASI POR FINALIZADO EL EVENTO. POSTERIORMENTE SE TOMA CONOCIMIENTO POR MEDIO DE LA AMPLIACION DE LA CARTA SAE QUE MOVIL 914 INFORMA QUE SE REALIZA CONSULTA CON LA FISCALIA NACIONAL CRIMINAL Y CORRECCIONAL N°29 A CARGO DEL DR. LUCIO HERRERA SECRETARIA UNICA A CARGO DE LA DRA. GONZALEZ DISPONE ACTUACIONES POR HURTO. | X2: 0 | Y2: 0 | Z2: 0 | AA2: 14B | AB2: U | AC2: CARTA | AF2: CARTA FINALIZADA | AL2: =VLOOKUP(G2,Hoja2!P:Q,2,0) -> 45324330 | AM2: =IF(OR(Y2>0,X2>0),"IMPUTADO","NADA") -> NADA | AN2: =IF(AND(AM2="IMPUTADO",ISBLANK(M2)),"FALTO","NO") -> NO
A3: 45992 | B3: =IF(AND(VALUE(P3)>=VALUE("06:00"),VALUE(P3)<=VALUE("17:59")),"06 A 18","18 A 06") -> 18 A 06 | C3: =IF(AND(VALUE(P3)>=VALUE("00:00"),VALUE(P3)<=VALUE("01:59")),"00:00 a 02:00",IF(AND(VALUE(P3)>=VALUE("02:00"),VALUE(P3)<=VALUE("03:59")),"02:00 a 04:00",IF(AND(VALUE(P3)>=VALUE("04:00"),VALUE(P3)<=VALUE("05:59")),"04:00 a 06:00",IF(AND(VALUE(P3)>=VALUE("06:00"),VALUE(P3)<=VALUE("07:59")),"06:00 a 08:00",IF(AND(VALUE(P3)>=VALUE("08:00"),VALUE(P3)<=VALUE("09:59")),"08:00 a 10:00",IF(AND(VALUE(P3)>=VALUE("10:00"),VALUE(P3)<=VALUE("11:59")),"10:00 a 12:00",IF(AND(VALUE(P3)>=VALUE("12:00"),VALUE(P3)<=VALUE("13:59")),"12:00 a 14:00",IF(AND(VALUE(P3)>=VALUE("14:00"),VALUE(P3)<=VALUE("15:59")),"14:00 a 16:00",IF(AND(VALUE(P3)>=VALUE("16:00"),VALUE(P3)<=VALUE("17:59")),"16:00 a 18:00",IF(AND(VALUE(P3)>=VALUE("18:00"),VALUE(P3)<=VALUE("19:59")),"18:00 a 20:00",IF(AND(VALUE(P3)>=VALUE("20:00"),VALUE(P3)<=VALUE("21:59")),"20:00 a 22:00",IF(AND(VALUE(P3)>=VALUE("22:00"),VALUE(P3)<=VALUE("23:59")),"22:00 a 00:00","no corresponde")))))))))))) -> 00:00 a 02:00 | D3: ARGUELLO | E3: QUINTANA, GILDA | F3: 3 | G3: LOBOS, LUCRECIA | H3: 919856 | I3: 46736945 | J3: CHACARITA | K3: PERSONA CAIDA | N3: BALVANERA28 | O3: Balvanera | P3: 0.010416667 | Q3: 0.020833333 | R3: 0.025694444 | S3: - | T3: - | U3: - | V3: - | W3: SE TOMA CONOCIMIENTO MEDIANTE CARTA SAE SOBRE DENUNCIANTE QUIEN REFIERE QUE MASCULINO TAXISTA ESTARIA APARENTEMENTE EBRIO DENTRO DEL VEHICULO ESTACIONADO EN EL LUGAR. SE VISUALIZA VEHICULO DE ALQUILER EN EL LUGAR. ARRIBA PERSONAL POLICIAL DANDO CON EL RODADO EN MENCION. SE INFORMA SE TRATA DE MASCULINO DORMITANDO EN SU VEHICULO PARTICULAR.- | X3: 0 | Y3: 0 | Z3: 0 | AA3: 3A | AB3: U | AC3: CARTA | AD3: SISEP | AF3: CARTA FINALIZADA | AL3: =VLOOKUP(G3,Hoja2!P:Q,2,0) -> 28898771 | AM3: =IF(OR(Y3>0,X3>0),"IMPUTADO","NADA") -> NADA | AN3: =IF(AND(AM3="IMPUTADO",ISBLANK(M3)),"FALTO","NO") -> NO
A4: 45992 | B4: =IF(AND(VALUE(P4)>=VALUE("06:00"),VALUE(P4)<=VALUE("17:59")),"06 A 18","18 A 06") -> 18 A 06 | C4: =IF(AND(VALUE(P4)>=VALUE("00:00"),VALUE(P4)<=VALUE("01:59")),"00:00 a 02:00",IF(AND(VALUE(P4)>=VALUE("02:00"),VALUE(P4)<=VALUE("03:59")),"02:00 a 04:00",IF(AND(VALUE(P4)>=VALUE("04:00"),VALUE(P4)<=VALUE("05:59")),"04:00 a 06:00",IF(AND(VALUE(P4)>=VALUE("06:00"),VALUE(P4)<=VALUE("07:59")),"06:00 a 08:00",IF(AND(VALUE(P4)>=VALUE("08:00"),VALUE(P4)<=VALUE("09:59")),"08:00 a 10:00",IF(AND(VALUE(P4)>=VALUE("10:00"),VALUE(P4)<=VALUE("11:59")),"10:00 a 12:00",IF(AND(VALUE(P4)>=VALUE("12:00"),VALUE(P4)<=VALUE("13:59")),"12:00 a 14:00",IF(AND(VALUE(P4)>=VALUE("14:00"),VALUE(P4)<=VALUE("15:59")),"14:00 a 16:00",IF(AND(VALUE(P4)>=VALUE("16:00"),VALUE(P4)<=VALUE("17:59")),"16:00 a 18:00",IF(AND(VALUE(P4)>=VALUE("18:00"),VALUE(P4)<=VALUE("19:59")),"18:00 a 20:00",IF(AND(VALUE(P4)>=VALUE("20:00"),VALUE(P4)<=VALUE("21:59")),"20:00 a 22:00",IF(AND(VALUE(P4)>=VALUE("22:00"),VALUE(P4)<=VALUE("23:59")),"22:00 a 00:00","no corresponde")))))))))))) -> 00:00 a 02:00 | D4: ARGUELLO | E4: QUINTANA, GILDA | F4: 3 | G4: RIGONI, VALENTINA | H4: 919879 | I4: 46737131 | J4: CHACARITA | K4: PERSONA CAIDA | N4: FLORESTA16CAM02 | O4: Floresta | P4: 0.034722222 | Q4: 0.059722222 | R4: 0.034722222 | S4: 0.048611111 | T4: - | U4: - | V4: - | W4: SE TOMA CONOCIMIENTO MEDIANTE CARTA SAE N°46737131 QUE DENUNCIANTE REFIERE QUE UNA MUJER SE CAYÓ DE LA MOTO. ESTA LASTIMADA Y SANGRANDO DE LA BOCA. SIENDO LAS 00:50HS. SE TOMA CÁMARA FLORESTA16CAM02 EMPLAZADA EN RIVADAVIA 7902 Y AZUL DONDE SE VISUALIZA A UNA PERSONA TENDIDA EN EL MEDIO DE LA CINTA ASFÁLTICA SIENDO ASISTIDA POR TRANSEÚNTES. SE PROCEDE A REALIZAR LÍNEA DE TIEMPO SOBRE LA MISMA CÁMARA DONDE SIENDO LAS 00:47HS. SE VISUALIZA A UN MOTOVEHICULO CIRCULANDO POR CALLE RIVADAVIA SENTIDO AZUL DONDE ESTE PIERDE EL CONTROL DEL MOTOVEHICULO Y CAE SOBRE CINTA ASFÁLTICA. 01:03HS. ARRIBA PERSONAL POLICIAL AL LUGAR. 01:10HS. ARRIBA SAME. 01:21HS. SE RETIRA SAME CON TRASLADO. 01:26HS. SE RETIRA PERSONAL POLICIAL DANDO ASÍ COMO FINALIZADO ESTE EVENTO. POSTERIORMENTE SE AMPLÍA MEDIANTE CARTA SAE QUE SECTOR 1 INFORMA ARRIBO SAME 404 DEL HOSPITAL PIÑEIRO A CARGO DE DRA. DE LA GARCÍA MATRICULA N° 198166 QUIEN ASISTE Y DERIVA CON DIAGNOSTICO POLITRAUMATISMO A MISMO NOSOCOMIO. | X4: 0 | Y4: 0 | Z4: 1 | AA4: 10C | AB4: U | AC4: CARTA | AD4: SISEP | AE4: 1 TRASLADO SAME | AF4: CARTA FINALIZADA | AL4: =VLOOKUP(G4,Hoja2!P:Q,2,0) -> 45756657 | AM4: =IF(OR(Y4>0,X4>0),"IMPUTADO","NADA") -> NADA | AN4: =IF(AND(AM4="IMPUTADO",ISBLANK(M4)),"FALTO","NO") -> NO
A5: 45992 | B5: =IF(AND(VALUE(P5)>=VALUE("06:00"),VALUE(P5)<=VALUE("17:59")),"06 A 18","18 A 06") -> 18 A 06 | C5: =IF(AND(VALUE(P5)>=VALUE("00:00"),VALUE(P5)<=VALUE("01:59")),"00:00 a 02:00",IF(AND(VALUE(P5)>=VALUE("02:00"),VALUE(P5)<=VALUE("03:59")),"02:00 a 04:00",IF(AND(VALUE(P5)>=VALUE("04:00"),VALUE(P5)<=VALUE("05:59")),"04:00 a 06:00",IF(AND(VALUE(P5)>=VALUE("06:00"),VALUE(P5)<=VALUE("07:59")),"06:00 a 08:00",IF(AND(VALUE(P5)>=VALUE("08:00"),VALUE(P5)<=VALUE("09:59")),"08:00 a 10:00",IF(AND(VALUE(P5)>=VALUE("10:00"),VALUE(P5)<=VALUE("11:59")),"10:00 a 12:00",IF(AND(VALUE(P5)>=VALUE("12:00"),VALUE(P5)<=VALUE("13:59")),"12:00 a 14:00",IF(AND(VALUE(P5)>=VALUE("14:00"),VALUE(P5)<=VALUE("15:59")),"14:00 a 16:00",IF(AND(VALUE(P5)>=VALUE("16:00"),VALUE(P5)<=VALUE("17:59")),"16:00 a 18:00",IF(AND(VALUE(P5)>=VALUE("18:00"),VALUE(P5)<=VALUE("19:59")),"18:00 a 20:00",IF(AND(VALUE(P5)>=VALUE("20:00"),VALUE(P5)<=VALUE("21:59")),"20:00 a 22:00",IF(AND(VALUE(P5)>=VALUE("22:00"),VALUE(P5)<=VALUE("23:59")),"22:00 a 00:00","no corresponde")))))))))))) -> 00:00 a 02:00 | D5: ARGUELLO | E5: QUINTANA, GILDA | F5: 3 | G5: ALONSO, JORGE ANTONIO | H5: 919860 | I5: 46737148 | J5: CHACARITA | K5: ROBO/HURTO | M5: ROBO/HURTO | N5: FLORES27 | O5: Flores | P5: 0.033333333 | Q5: 0.11111111 | R5: 0.039583333 | S5: - | T5: - | U5: - | V5: - | W5: SE VISUALIZA UN MASCULINO TRANSPORTANDO UNA BATERIA EN INTERIOR DE COLECTIVO LINEA 76 INTERNO 1302 SENTIDO A SAN PEDRITO. ARRIBA PERSONAL POLICIAL INTERCEPTANDO EL COELCTIVO EN CUESTION. SE VERIFICA LINEA DE TIEMPO OBSERVANDO A DOS MACULINOS LEVANTAR EL CAPOT DE UN RODADO Y SUSTRAER LA BATERIA PARA LUEGO ASCENDER A LA UNIDAD DE COLECTIVO. SE INFORMA SE HALLA EL VEHICULO VIOLENTADO CON FALTANTE DE BATERIA. SE LABRAN ACTUASCIONES POR ROBO. DETENCION DE AMBOS MASCULINOS.-- | X5: 0 | Y5: 2 | Z5: 0 | AA5: 7C | AB5: U | AC5: MONITOREO | AD5: SISEP | AE5: 2 DETENIDOS.- | AF5: FINALIZA CON IMPUTADO/S | AL5: =VLOOKUP(G5,Hoja2!P:Q,2,0) -> 23671702 | AM5: =IF(OR(Y5>0,X5>0),"IMPUTADO","NADA") -> IMPUTADO | AN5: =IF(AND(AM5="IMPUTADO",ISBLANK(M5)),"FALTO","NO") -> NO
A6: 45992 | B6: =IF(AND(VALUE(P6)>=VALUE("06:00"),VALUE(P6)<=VALUE("17:59")),"06 A 18","18 A 06") -> 18 A 06 | C6: =IF(AND(VALUE(P6)>=VALUE("00:00"),VALUE(P6)<=VALUE("01:59")),"00:00 a 02:00",IF(AND(VALUE(P6)>=VALUE("02:00"),VALUE(P6)<=VALUE("03:59")),"02:00 a 04:00",IF(AND(VALUE(P6)>=VALUE("04:00"),VALUE(P6)<=VALUE("05:59")),"04:00 a 06:00",IF(AND(VALUE(P6)>=VALUE("06:00"),VALUE(P6)<=VALUE("07:59")),"06:00 a 08:00",IF(AND(VALUE(P6)>=VALUE("08:00"),VALUE(P6)<=VALUE("09:59")),"08:00 a 10:00",IF(AND(VALUE(P6)>=VALUE("10:00"),VALUE(P6)<=VALUE("11:59")),"10:00 a 12:00",IF(AND(VALUE(P6)>=VALUE("12:00"),VALUE(P6)<=VALUE("13:59")),"12:00 a 14:00",IF(AND(VALUE(P6)>=VALUE("14:00"),VALUE(P6)<=VALUE("15:59")),"14:00 a 16:00",IF(AND(VALUE(P6)>=VALUE("16:00"),VALUE(P6)<=VALUE("17:59")),"16:00 a 18:00",IF(AND(VALUE(P6)>=VALUE("18:00"),VALUE(P6)<=VALUE("19:59")),"18:00 a 20:00",IF(AND(VALUE(P6)>=VALUE("20:00"),VALUE(P6)<=VALUE("21:59")),"20:00 a 22:00",IF(AND(VALUE(P6)>=VALUE("22:00"),VALUE(P6)<=VALUE("23:59")),"22:00 a 00:00","no corresponde")))))))))))) -> 00:00 a 02:00 | D6: ARGUELLO | E6: QUINTANA, GILDA | F6: 3 | G6: RIOS MESA, MALCOM MIGUEL | H6: 919876 | I6: 46737165 | J6: CHACARITA | K6: COLABORACION | L6: SUICIDIO/TTVA. SUICIDIO | N6: PALERMO O136 | O6: Palermo | P6: 0.041666667 | Q6: 0.18611111 | R6: 0.041666667 | S6: 0.05 | T6: - | U6: - | V6: - | W6: SE TOMA CONOCIMIENTO MEDIANTE CARTA SAE SOBRE DENUNCIANTE QUIEN REFIERE QUE ESCUCHA UN FEMENINO EN DEMANDA DE AUXILIO. SE VISUALIZA PERSONAL POLICIAL. ARRIBA SAME QUIEN ASISTE EN EL LUGAR Y CONSTATA OBITO. SE INFORMA FEMENINO REFIERE QUE EL MASCULINO HABRIA CONSUMIDO COCAINA Y ASCIENDE AL DORMITORIO, EL MISMOCOMIENZSA A DEMORAR DONDE LA FEMENINO SUBE AL MISMO Y ESTE SE TIRA DEL BARANDAL CON UNA SABANA. CONSTATAN OBITO HORAS 01:27 EN POSICION CUBITO DORSAL. SE LABRAN ACTS POR AVERIGUACION CAUSALES DE MUERTE.- | X6: 0 | Y6: 0 | Z6: 0 | AA6: 14B | AB6: U | AC6: CARTA | AE6: 1 OBITO | AF6: CARTA FINALIZADA | AL6: =VLOOKUP(G6,Hoja2!P:Q,2,0) -> 27382983 | AM6: =IF(OR(Y6>0,X6>0),"IMPUTADO","NADA") -> NADA | AN6: =IF(AND(AM6="IMPUTADO",ISBLANK(M6)),"FALTO","NO") -> NO
A7: 45992 | B7: =IF(AND(VALUE(P7)>=VALUE("06:00"),VALUE(P7)<=VALUE("17:59")),"06 A 18","18 A 06") -> 18 A 06 | C7: =IF(AND(VALUE(P7)>=VALUE("00:00"),VALUE(P7)<=VALUE("01:59")),"00:00 a 02:00",IF(AND(VALUE(P7)>=VALUE("02:00"),VALUE(P7)<=VALUE("03:59")),"02:00 a 04:00",IF(AND(VALUE(P7)>=VALUE("04:00"),VALUE(P7)<=VALUE("05:59")),"04:00 a 06:00",IF(AND(VALUE(P7)>=VALUE("06:00"),VALUE(P7)<=VALUE("07:59")),"06:00 a 08:00",IF(AND(VALUE(P7)>=VALUE("08:00"),VALUE(P7)<=VALUE("09:59")),"08:00 a 10:00",IF(AND(VALUE(P7)>=VALUE("10:00"),VALUE(P7)<=VALUE("11:59")),"10:00 a 12:00",IF(AND(VALUE(P7)>=VALUE("12:00"),VALUE(P7)<=VALUE("13:59")),"12:00 a 14:00",IF(AND(VALUE(P7)>=VALUE("14:00"),VALUE(P7)<=VALUE("15:59")),"14:00 a 16:00",IF(AND(VALUE(P7)>=VALUE("16:00"),VALUE(P7)<=VALUE("17:59")),"16:00 a 18:00",IF(AND(VALUE(P7)>=VALUE("18:00"),VALUE(P7)<=VALUE("19:59")),"18:00 a 20:00",IF(AND(VALUE(P7)>=VALUE("20:00"),VALUE(P7)<=VALUE("21:59")),"20:00 a 22:00",IF(AND(VALUE(P7)>=VALUE("22:00"),VALUE(P7)<=VALUE("23:59")),"22:00 a 00:00","no corresponde")))))))))))) -> 00:00 a 02:00 | D7: ARGUELLO | E7: QUINTANA, GILDA | F7: 3 | G7: RODRIGUEZ BAEZ, MAXIMA | H7: 919857 | I7: 46737219 | J7: CHACARITA | K7: PERSONA CAIDA | N7: AGRONOMIA 01 CAM2 | O7: Agronomia | P7: 0.045833333 | Q7: 0.070138889 | R7: 0.048611111 | S7: 0.055555556 | T7: - | U7: - | V7: - | W7: SE TOMA CONOCIMIENTO MEDIANTE CARTA SAE SOBRE DENUNCIANTE QUIENREFIERE QUE HABRIA UN FEMENINO CAIDO DE LA MOTO ESTARIA GOLPEADA EN EL HOMBRO. SE VISUALIZA MASCULINO CAIDOEN LA VIA PUBLICA. SE VERIFICA LIENA DE TIEM POOBSERVANDO FEMENINO CAER POR MALA MANIOBRA POR INCLEMENCIA CLIMATICA. ARRIBA PERSONAL POLICIAL Y SAME QUIEN ASISTE Y DERIVA CON DIAGN TRAUMATISMO DDEHOMBRO DERECHO. SE LABRA CONSTANCIA EN PARTE.- | X7: 0 | Y7: 0 | Z7: 1 | AA7: 15C | AB7: U | AC7: CARTA | AD7: SISEP | AE7: 1 TRASLADO SAME | AF7: CARTA FINALIZADA | AL7: =VLOOKUP(G7,Hoja2!P:Q,2,0) -> 44544554 | AM7: =IF(OR(Y7>0,X7>0),"IMPUTADO","NADA") -> NADA | AN7: =IF(AND(AM7="IMPUTADO",ISBLANK(M7)),"FALTO","NO") -> NO
A8: 45992 | B8: =IF(AND(VALUE(P8)>=VALUE("06:00"),VALUE(P8)<=VALUE("17:59")),"06 A 18","18 A 06") -> 18 A 06 | C8: =IF(AND(VALUE(P8)>=VALUE("00:00"),VALUE(P8)<=VALUE("01:59")),"00:00 a 02:00",IF(AND(VALUE(P8)>=VALUE("02:00"),VALUE(P8)<=VALUE("03:59")),"02:00 a 04:00",IF(AND(VALUE(P8)>=VALUE("04:00"),VALUE(P8)<=VALUE("05:59")),"04:00 a 06:00",IF(AND(VALUE(P8)>=VALUE("06:00"),VALUE(P8)<=VALUE("07:59")),"06:00 a 08:00",IF(AND(VALUE(P8)>=VALUE("08:00"),VALUE(P8)<=VALUE("09:59")),"08:00 a 10:00",IF(AND(VALUE(P8)>=VALUE("10:00"),VALUE(P8)<=VALUE("11:59")),"10:00 a 12:00",IF(AND(VALUE(P8)>=VALUE("12:00"),VALUE(P8)<=VALUE("13:59")),"12:00 a 14:00",IF(AND(VALUE(P8)>=VALUE("14:00"),VALUE(P8)<=VALUE("15:59")),"14:00 a 16:00",IF(AND(VALUE(P8)>=VALUE("16:00"),VALUE(P8)<=VALUE("17:59")),"16:00 a 18:00",IF(AND(VALUE(P8)>=VALUE("18:00"),VALUE(P8)<=VALUE("19:59")),"18:00 a 20:00",IF(AND(VALUE(P8)>=VALUE("20:00"),VALUE(P8)<=VALUE("21:59")),"20:00 a 22:00",IF(AND(VALUE(P8)>=VALUE("22:00"),VALUE(P8)<=VALUE("23:59")),"22:00 a 00:00","no corresponde")))))))))))) -> 00:00 a 02:00 | D8: ARGUELLO | E8: COLO, NADIA | F8: 3 | G8: PONCE, VANESA PAOLA | H8: 919887 | I8: 46737291 | J8: PUERTO MADERO | K8: INCIDENCIA EN VIA PUBLICA | N8: BARRACAS82 | O8: Barracas | P8: 0.051388889 | Q8: 0.059027778 | R8: 0.054861111 | S8: - | T8: - | U8: - | V8: - | W8: SE VISUALIZA POR CAMARA BARRACAS 82 UNA INCIDENCIA ENTRE DOS MASCULINOS LOS CUALES MINUTOS POSTERIORES SE RETIRAN EN DISTINTAS DIRECCIONES. ARRIBA PERSONAL POLCIAL SIN DAR CON LOS MISMOS. | X8: 0 | Y8: 0 | Z8: 0 | AA8: 4D | AB8: U | AC8: MONITOREO | AF8: CARTA FINALIZADA | AL8: =VLOOKUP(G8,Hoja2!P:Q,2,0) -> 30642469 | AM8: =IF(OR(Y8>0,X8>0),"IMPUTADO","NADA") -> NADA | AN8: =IF(AND(AM8="IMPUTADO",ISBLANK(M8)),"FALTO","NO") -> NO
A9: 45992 | B9: =IF(AND(VALUE(P9)>=VALUE("06:00"),VALUE(P9)<=VALUE("17:59")),"06 A 18","18 A 06") -> 18 A 06 | C9: =IF(AND(VALUE(P9)>=VALUE("00:00"),VALUE(P9)<=VALUE("01:59")),"00:00 a 02:00",IF(AND(VALUE(P9)>=VALUE("02:00"),VALUE(P9)<=VALUE("03:59")),"02:00 a 04:00",IF(AND(VALUE(P9)>=VALUE("04:00"),VALUE(P9)<=VALUE("05:59")),"04:00 a 06:00",IF(AND(VALUE(P9)>=VALUE("06:00"),VALUE(P9)<=VALUE("07:59")),"06:00 a 08:00",IF(AND(VALUE(P9)>=VALUE("08:00"),VALUE(P9)<=VALUE("09:59")),"08:00 a 10:00",IF(AND(VALUE(P9)>=VALUE("10:00"),VALUE(P9)<=VALUE("11:59")),"10:00 a 12:00",IF(AND(VALUE(P9)>=VALUE("12:00"),VALUE(P9)<=VALUE("13:59")),"12:00 a 14:00",IF(AND(VALUE(P9)>=VALUE("14:00"),VALUE(P9)<=VALUE("15:59")),"14:00 a 16:00",IF(AND(VALUE(P9)>=VALUE("16:00"),VALUE(P9)<=VALUE("17:59")),"16:00 a 18:00",IF(AND(VALUE(P9)>=VALUE("18:00"),VALUE(P9)<=VALUE("19:59")),"18:00 a 20:00",IF(AND(VALUE(P9)>=VALUE("20:00"),VALUE(P9)<=VALUE("21:59")),"20:00 a 22:00",IF(AND(VALUE(P9)>=VALUE("22:00"),VALUE(P9)<=VALUE("23:59")),"22:00 a 00:00","no corresponde")))))))))))) -> 00:00 a 02:00 | D9: ARGUELLO | E9: QUINTANA, GILDA | F9: 3 | G9: SOSA, DÉBORA | H9: 919846 | I9: 46737350 | J9: CHACARITA | K9: INCIDENCIA EN VIA PUBLICA | N9: FLORES O137 | O9: Flores | P9: 0.059027778 | Q9: 0.068055556 | R9: 0.061805556 | S9: - | T9: - | U9: - | V9: - | W9: SE VISUALIZA UNA INCIDENCIA EN EL LUGAR.A RRIBA PERSONAL POLICIAL DANDO CON LAS PARTE. SE INFORMA SE TRATO DE INCIDENCIA SOLUCIONADA SIN NOVEDAD.- | X9: 0 | Y9: 0 | Z9: 0 | AA9: 7A | AB9: U | AC9: MONITOREO | AD9: SISEP | AF9: CARTA FINALIZADA | AL9: =VLOOKUP(G9,Hoja2!P:Q,2,0) -> 38862287 | AM9: =IF(OR(Y9>0,X9>0),"IMPUTADO","NADA") -> NADA | AN9: =IF(AND(AM9="IMPUTADO",ISBLANK(M9)),"FALTO","NO") -> NO
A10: 45992 | B10: =IF(AND(VALUE(P10)>=VALUE("06:00"),VALUE(P10)<=VALUE("17:59")),"06 A 18","18 A 06") -> 18 A 06 | C10: =IF(AND(VALUE(P10)>=VALUE("00:00"),VALUE(P10)<=VALUE("01:59")),"00:00 a 02:00",IF(AND(VALUE(P10)>=VALUE("02:00"),VALUE(P10)<=VALUE("03:59")),"02:00 a 04:00",IF(AND(VALUE(P10)>=VALUE("04:00"),VALUE(P10)<=VALUE("05:59")),"04:00 a 06:00",IF(AND(VALUE(P10)>=VALUE("06:00"),VALUE(P10)<=VALUE("07:59")),"06:00 a 08:00",IF(AND(VALUE(P10)>=VALUE("08:00"),VALUE(P10)<=VALUE("09:59")),"08:00 a 10:00",IF(AND(VALUE(P10)>=VALUE("10:00"),VALUE(P10)<=VALUE("11:59")),"10:00 a 12:00",IF(AND(VALUE(P10)>=VALUE("12:00"),VALUE(P10)<=VALUE("13:59")),"12:00 a 14:00",IF(AND(VALUE(P10)>=VALUE("14:00"),VALUE(P10)<=VALUE("15:59")),"14:00 a 16:00",IF(AND(VALUE(P10)>=VALUE("16:00"),VALUE(P10)<=VALUE("17:59")),"16:00 a 18:00",IF(AND(VALUE(P10)>=VALUE("18:00"),VALUE(P10)<=VALUE("19:59")),"18:00 a 20:00",IF(AND(VALUE(P10)>=VALUE("20:00"),VALUE(P10)<=VALUE("21:59")),"20:00 a 22:00",IF(AND(VALUE(P10)>=VALUE("22:00"),VALUE(P10)<=VALUE("23:59")),"22:00 a 00:00","no corresponde")))))))))))) -> 00:00 a 02:00 | D10: ARGUELLO | E10: CARABAJAL, GRACIELA | F10: 3 | G10: INFANTE, JONATHAN ISMAEL | H10: 919871 | I10: 46737371 | J10: CHACARITA | K10: APARENTE COMERCIALIZACION ESTUPEFACIENTES | M10: LEY 23.737 | N10: CONSTITUCION32 | O10: Constitucion | P10: 0.063194444 | Q10: 0.078472222 | R10: 0.068055556 | S10: - | T10: - | U10: - | V10: - | W10: SE VISUALIZA POR CAMARA CONSTITUCION32 FEMENINO EN APARNETE VENTA DE ESTUPEFACIENTES,SE DA AVISO A COMANDO GENERANDO CARTA SAE N°46737371,ARRIBO DE PERSONAL POLICIAL. SE TOMA CONOCIMIENTO MEDIANTE CARTA SAE: MOVIL AMPLIA QUE SE REALIZO CONSULTA POR ANTE LA UFLA ESTE A/C DR DEBRASSI, DISPUSO ACTUACIONES POR AVERIGUACION COMERCIALIZACION DE ESTUPEFACIENTES. NOTIFICACION DEL FEMENINO. | X10: 0 | Y10: 1 | Z10: 1 | AA10: 1C | AB10: U | AC10: MONITOREO | AE10: 1 IMPUTADO | AF10: FINALIZA CON IMPUTADO/S | AL10: =VLOOKUP(G10,Hoja2!P:Q,2,0) -> 37358594 | AM10: =IF(OR(Y10>0,X10>0),"IMPUTADO","NADA") -> IMPUTADO | AN10: =IF(AND(AM10="IMPUTADO",ISBLANK(M10)),"FALTO","NO") -> NO
A11: 45992 | B11: =IF(AND(VALUE(P11)>=VALUE("06:00"),VALUE(P11)<=VALUE("17:59")),"06 A 18","18 A 06") -> 18 A 06 | C11: =IF(AND(VALUE(P11)>=VALUE("00:00"),VALUE(P11)<=VALUE("01:59")),"00:00 a 02:00",IF(AND(VALUE(P11)>=VALUE("02:00"),VALUE(P11)<=VALUE("03:59")),"02:00 a 04:00",IF(AND(VALUE(P11)>=VALUE("04:00"),VALUE(P11)<=VALUE("05:59")),"04:00 a 06:00",IF(AND(VALUE(P11)>=VALUE("06:00"),VALUE(P11)<=VALUE("07:59")),"06:00 a 08:00",IF(AND(VALUE(P11)>=VALUE("08:00"),VALUE(P11)<=VALUE("09:59")),"08:00 a 10:00",IF(AND(VALUE(P11)>=VALUE("10:00"),VALUE(P11)<=VALUE("11:59")),"10:00 a 12:00",IF(AND(VALUE(P11)>=VALUE("12:00"),VALUE(P11)<=VALUE("13:59")),"12:00 a 14:00",IF(AND(VALUE(P11)>=VALUE("14:00"),VALUE(P11)<=VALUE("15:59")),"14:00 a 16:00",IF(AND(VALUE(P11)>=VALUE("16:00"),VALUE(P11)<=VALUE("17:59")),"16:00 a 18:00",IF(AND(VALUE(P11)>=VALUE("18:00"),VALUE(P11)<=VALUE("19:59")),"18:00 a 20:00",IF(AND(VALUE(P11)>=VALUE("20:00"),VALUE(P11)<=VALUE("21:59")),"20:00 a 22:00",IF(AND(VALUE(P11)>=VALUE("22:00"),VALUE(P11)<=VALUE("23:59")),"22:00 a 00:00","no corresponde")))))))))))) -> 00:00 a 02:00 | D11: ARGUELLO | E11: QUINTANA, GILDA | F11: 3 | G11: SUAREZ, SABRINA | H11: 919868 | I11: 46737459 | J11: CHACARITA | K11: COLABORACION | L11: IDENT. DE PERSONAS | N11: VILLA DEVOTO39 | O11: Villa Devoto | P11: 0.079861111 | Q11: 0.090277778 | R11: 0.08125 | S11: - | T11: - | U11: - | V11: - | W11: SE TOMA CONOCIMIENTO MEDIANTE CARTA SAE SOBRE LLAMANTE APARENTEMENTE EN DEMANDA DE AUXILIO, PERSONAL 911 ESCUCHA DISCUSION NO RESPONDEN AL OPERADOR. SE VISUALIZA UN FEMENNO Y CUATRO MASCULINOS. ARRIBA PERSONAL POLICIAL. PERSONAL INFORMA SE PROCEDE A IDENTIFICAR A LOS MASCULINOS PASADOS DE COPAS CON RESULTADO NEGATIVO SIN ELEMENTOS CONSTITUTIVO DE DELITO PANORAMA NORMAL.- | X11: 0 | Y11: 0 | Z11: 0 | AA11: 11B | AB11: U | AC11: CARTA | AD11: SISEP | AF11: CARTA FINALIZADA | AL11: =VLOOKUP(G11,Hoja2!P:Q,2,0) -> 29382472 | AM11: =IF(OR(Y11>0,X11>0),"IMPUTADO","NADA") -> NADA | AN11: =IF(AND(AM11="IMPUTADO",ISBLANK(M11)),"FALTO","NO") -> NO
A12: 45992 | B12: =IF(AND(VALUE(P12)>=VALUE("06:00"),VALUE(P12)<=VALUE("17:59")),"06 A 18","18 A 06") -> 18 A 06 | C12: =IF(AND(VALUE(P12)>=VALUE("00:00"),VALUE(P12)<=VALUE("01:59")),"00:00 a 02:00",IF(AND(VALUE(P12)>=VALUE("02:00"),VALUE(P12)<=VALUE("03:59")),"02:00 a 04:00",IF(AND(VALUE(P12)>=VALUE("04:00"),VALUE(P12)<=VALUE("05:59")),"04:00 a 06:00",IF(AND(VALUE(P12)>=VALUE("06:00"),VALUE(P12)<=VALUE("07:59")),"06:00 a 08:00",IF(AND(VALUE(P12)>=VALUE("08:00"),VALUE(P12)<=VALUE("09:59")),"08:00 a 10:00",IF(AND(VALUE(P12)>=VALUE("10:00"),VALUE(P12)<=VALUE("11:59")),"10:00 a 12:00",IF(AND(VALUE(P12)>=VALUE("12:00"),VALUE(P12)<=VALUE("13:59")),"12:00 a 14:00",IF(AND(VALUE(P12)>=VALUE("14:00"),VALUE(P12)<=VALUE("15:59")),"14:00 a 16:00",IF(AND(VALUE(P12)>=VALUE("16:00"),VALUE(P12)<=VALUE("17:59")),"16:00 a 18:00",IF(AND(VALUE(P12)>=VALUE("18:00"),VALUE(P12)<=VALUE("19:59")),"18:00 a 20:00",IF(AND(VALUE(P12)>=VALUE("20:00"),VALUE(P12)<=VALUE("21:59")),"20:00 a 22:00",IF(AND(VALUE(P12)>=VALUE("22:00"),VALUE(P12)<=VALUE("23:59")),"22:00 a 00:00","no corresponde")))))))))))) -> 02:00 a 04:00 | D12: ARGUELLO | E12: COLO, NADIA | F12: 3 | G12: BENITEZ PEREIRA, PATRICIA | I12: 46737485 | J12: PUERTO MADERO | K12: ROBO/HURTO | M12: ROBO/HURTO | N12: RECOLETAO109 | O12: Recoleta | P12: 0.083333333 | Q12: 0.10972222 | R12: 0.086805556 | S12: - | T12: - | U12: - | V12: - | W12: SE TOMA CONOCIMIENTO MEDIANTE CARTA SAE QUE UN MASCULINO ESTABA SUSTRAYENDO COBRE. SE VISUALIZO RETIRARSE DEL MISMO Y AL GIRAR SOBRE CALLE BUSTAMANTE PERSONAL POLICIAL DA CON EL MISMO. SE LABRAN ACTUACIONES POR ROBO PROCEDIENDO A LA DETENCION DEL MASCULINO. SE SECUESTRA PICAPORTE SUSTRAIDO, UN CUCHILLO, DESTORNILLADOR Y UN PEDAZO DE MADERA.- | X12: 0 | Y12: 1 | Z12: 1 | AA12: 2A | AB12: U | AC12: CARTA | AD12: SISEP | AE12: 1 DETENIDO | AF12: FINALIZA CON IMPUTADO/S | AL12: =VLOOKUP(G12,Hoja2!P:Q,2,0) -> 39339538 | AM12: =IF(OR(Y12>0,X12>0),"IMPUTADO","NADA") -> IMPUTADO | AN12: =IF(AND(AM12="IMPUTADO",ISBLANK(M12)),"FALTO","NO") -> NO
A13: 45992 | B13: =IF(AND(VALUE(P13)>=VALUE("06:00"),VALUE(P13)<=VALUE("17:59")),"06 A 18","18 A 06") -> 18 A 06 | C13: =IF(AND(VALUE(P13)>=VALUE("00:00"),VALUE(P13)<=VALUE("01:59")),"00:00 a 02:00",IF(AND(VALUE(P13)>=VALUE("02:00"),VALUE(P13)<=VALUE("03:59")),"02:00 a 04:00",IF(AND(VALUE(P13)>=VALUE("04:00"),VALUE(P13)<=VALUE("05:59")),"04:00 a 06:00",IF(AND(VALUE(P13)>=VALUE("06:00"),VALUE(P13)<=VALUE("07:59")),"06:00 a 08:00",IF(AND(VALUE(P13)>=VALUE("08:00"),VALUE(P13)<=VALUE("09:59")),"08:00 a 10:00",IF(AND(VALUE(P13)>=VALUE("10:00"),VALUE(P13)<=VALUE("11:59")),"10:00 a 12:00",IF(AND(VALUE(P13)>=VALUE("12:00"),VALUE(P13)<=VALUE("13:59")),"12:00 a 14:00",IF(AND(VALUE(P13)>=VALUE("14:00"),VALUE(P13)<=VALUE("15:59")),"14:00 a 16:00",IF(AND(VALUE(P13)>=VALUE("16:00"),VALUE(P13)<=VALUE("17:59")),"16:00 a 18:00",IF(AND(VALUE(P13)>=VALUE("18:00"),VALUE(P13)<=VALUE("19:59")),"18:00 a 20:00",IF(AND(VALUE(P13)>=VALUE("20:00"),VALUE(P13)<=VALUE("21:59")),"20:00 a 22:00",IF(AND(VALUE(P13)>=VALUE("22:00"),VALUE(P13)<=VALUE("23:59")),"22:00 a 00:00","no corresponde")))))))))))) -> 02:00 a 04:00 | D13: ARGUELLO | E13: ALCARAZ, ARIEL | F13: 3 | G13: LOBOS, LUCRECIA | H13: 919866 | I13: 46737489 | J13: CHACARITA | K13: INCIDENCIA EN VIA PUBLICA | M13: LESIONES | N13: BALVANERA21 | O13: Balvanera | P13: 0.084027778 | Q13: 0.10069444 | R13: 0.0875 | S13: - | T13: - | U13: - | V13: - | W13: SE TOMA CONOCIMIENTO MEDIANTE CARTA SAE SOBRE DENUNCIANTE QUIEN REFIERE QUE HABRIA UN MASCULINO GOLPEANDO A UN FEMENINO EN LA VIA PUBLICA. HABRIA OTRO MASCULINO INTENTANDO DEFENDER AL FEMENINO DE LAS AGRESIONES. SE VISUALIZA DOS MASCULINOS EN INCIDENCIA. ARRIBA PERSONAL POLICIAL. SE INFORMA NEGATIVO IVOLENCIA DE GENERO SE TRATO DE UNA INCIDENCIA. AMBAS PARTES ILESAS. SE TOMA CONOCIMIENTO QUE SE LABRAN ACTUACIONES POR LESIONES 89 AGRAVADA POR ARTICULO 92. AVALA DETENCION DEL FEMENINO.- | X13: 0 | Y13: 1 | Z13: 0 | AA13: 3B | AB13: U | AC13: CARTA | AD13: SISEP | AE13: 1 DETENIDO | AF13: FINALIZA CON IMPUTADO/S | AL13: =VLOOKUP(G13,Hoja2!P:Q,2,0) -> 28898771 | AM13: =IF(OR(Y13>0,X13>0),"IMPUTADO","NADA") -> IMPUTADO | AN13: =IF(AND(AM13="IMPUTADO",ISBLANK(M13)),"FALTO","NO") -> NO
A14: 45992 | B14: =IF(AND(VALUE(P14)>=VALUE("06:00"),VALUE(P14)<=VALUE("17:59")),"06 A 18","18 A 06") -> 18 A 06 | C14: =IF(AND(VALUE(P14)>=VALUE("00:00"),VALUE(P14)<=VALUE("01:59")),"00:00 a 02:00",IF(AND(VALUE(P14)>=VALUE("02:00"),VALUE(P14)<=VALUE("03:59")),"02:00 a 04:00",IF(AND(VALUE(P14)>=VALUE("04:00"),VALUE(P14)<=VALUE("05:59")),"04:00 a 06:00",IF(AND(VALUE(P14)>=VALUE("06:00"),VALUE(P14)<=VALUE("07:59")),"06:00 a 08:00",IF(AND(VALUE(P14)>=VALUE("08:00"),VALUE(P14)<=VALUE("09:59")),"08:00 a 10:00",IF(AND(VALUE(P14)>=VALUE("10:00"),VALUE(P14)<=VALUE("11:59")),"10:00 a 12:00",IF(AND(VALUE(P14)>=VALUE("12:00"),VALUE(P14)<=VALUE("13:59")),"12:00 a 14:00",IF(AND(VALUE(P14)>=VALUE("14:00"),VALUE(P14)<=VALUE("15:59")),"14:00 a 16:00",IF(AND(VALUE(P14)>=VALUE("16:00"),VALUE(P14)<=VALUE("17:59")),"16:00 a 18:00",IF(AND(VALUE(P14)>=VALUE("18:00"),VALUE(P14)<=VALUE("19:59")),"18:00 a 20:00",IF(AND(VALUE(P14)>=VALUE("20:00"),VALUE(P14)<=VALUE("21:59")),"20:00 a 22:00",IF(AND(VALUE(P14)>=VALUE("22:00"),VALUE(P14)<=VALUE("23:59")),"22:00 a 00:00","no corresponde")))))))))))) -> 02:00 a 04:00 | D14: ARGUELLO | E14: ALCARAZ, ARIEL | F14: 3 | G14: SUAREZ, SABRINA | H14: 919865 | I14: 46737542 | J14: CHACARITA | K14: INCIDENCIA EN VIA PUBLICA | N14: VILLA LURO24 / 05 CAM02 | O14: Villa Luro | P14: 0.092361111 | Q14: 0.10902778 | R14: 0.098611111 | S14: - | T14: - | U14: - | V14: - | W14: SE TOMA CONOCIMIENTO MEDIANTE CARTA SAE SOBRE DENUNCIANTE QUIEN REFIER EQUE HABRIA ESCUCHADO CUATRO DETONACIONES Y GRITOS DE UNA PERSONA, REFIERE QUE HABRIA MATADO A ALGUIEN, WESCUCHA GRITOS DE VARIAS PERSONAS. SEVISUALIZA TRES MASCULINOS DE SIMILARES CARACTERISTICAS A LAS APORTADAS EN CARTA. LOS MISMOS EN BICICLETA. ARRIBA PERSONAL POLICIAL DANDO CON LOS MISMOS. VERIFICADA LINEA DE TIEMPO OBSERVANDO A ESTOS DESCARTANDO ALGUN TIPO DE ELEMENTO EN UN CONTENEDOR DE RESIDUOS. SE INFORMA SE PROCEDE A IDENTIFICAR A TRES MASCULINOS CON RESULTADO NEGATIVO . NEGATIVO ELEMENTO CONSTITUTIVO DE DELITO. SE RETIRAN SIN NOVEDAD PANORAMA NORMAL.- | X14: 0 | Y14: 0 | Z14: 0 | AA14: 10C | AB14: U | AC14: CARTA | AF14: CARTA FINALIZADA | AL14: =VLOOKUP(G14,Hoja2!P:Q,2,0) -> 29382472 | AM14: =IF(OR(Y14>0,X14>0),"IMPUTADO","NADA") -> NADA | AN14: =IF(AND(AM14="IMPUTADO",ISBLANK(M14)),"FALTO","NO") -> NO
A15: 45992 | B15: =IF(AND(VALUE(P15)>=VALUE("06:00"),VALUE(P15)<=VALUE("17:59")),"06 A 18","18 A 06") -> 18 A 06 | C15: =IF(AND(VALUE(P15)>=VALUE("00:00"),VALUE(P15)<=VALUE("01:59")),"00:00 a 02:00",IF(AND(VALUE(P15)>=VALUE("02:00"),VALUE(P15)<=VALUE("03:59")),"02:00 a 04:00",IF(AND(VALUE(P15)>=VALUE("04:00"),VALUE(P15)<=VALUE("05:59")),"04:00 a 06:00",IF(AND(VALUE(P15)>=VALUE("06:00"),VALUE(P15)<=VALUE("07:59")),"06:00 a 08:00",IF(AND(VALUE(P15)>=VALUE("08:00"),VALUE(P15)<=VALUE("09:59")),"08:00 a 10:00",IF(AND(VALUE(P15)>=VALUE("10:00"),VALUE(P15)<=VALUE("11:59")),"10:00 a 12:00",IF(AND(VALUE(P15)>=VALUE("12:00"),VALUE(P15)<=VALUE("13:59")),"12:00 a 14:00",IF(AND(VALUE(P15)>=VALUE("14:00"),VALUE(P15)<=VALUE("15:59")),"14:00 a 16:00",IF(AND(VALUE(P15)>=VALUE("16:00"),VALUE(P15)<=VALUE("17:59")),"16:00 a 18:00",IF(AND(VALUE(P15)>=VALUE("18:00"),VALUE(P15)<=VALUE("19:59")),"18:00 a 20:00",IF(AND(VALUE(P15)>=VALUE("20:00"),VALUE(P15)<=VALUE("21:59")),"20:00 a 22:00",IF(AND(VALUE(P15)>=VALUE("22:00"),VALUE(P15)<=VALUE("23:59")),"22:00 a 00:00","no corresponde")))))))))))) -> 02:00 a 04:00 | D15: ARGUELLO | E15: QUINTANA, GILDA | F15: 3 | G15: LOBOS, LUCRECIA | H15: 919858 | I15: 46737617 | J15: CHACARITA | K15: IDENTIFICACION DE PERSONAS | N15: BALVANERA35 | O15: Balvanera | P15: 0.10833333 | Q15: 0.11319444 | R15: 0.10972222 | S15: - | T15: - | U15: - | V15: - | W15: SE VISUALIZA UN MASCULINO TENDIDO EN LA ACERA APARENTEMENTE EN ESTADO DE EBRIEDAD EXHIBIENDO PARTES INTIMAS. ARRIBA PERSONAL POLICIAL. SE INFORMA SE TRATA DE MASCULINOS EN SITUACION VULNERABLE LOS CUALES SE RETIRAN DE FORMA AMABLE. SIN NOVEDAD.- | X15: 0 | Y15: 0 | Z15: 0 | AA15: 3A | AB15: U | AC15: MONITOREO | AF15: CARTA FINALIZADA | AL15: =VLOOKUP(G15,Hoja2!P:Q,2,0) -> 28898771 | AM15: =IF(OR(Y15>0,X15>0),"IMPUTADO","NADA") -> NADA | AN15: =IF(AND(AM15="IMPUTADO",ISBLANK(M15)),"FALTO","NO") -> NO
A16: 45992 | B16: =IF(AND(VALUE(P16)>=VALUE("06:00"),VALUE(P16)<=VALUE("17:59")),"06 A 18","18 A 06") -> 18 A 06 | C16: =IF(AND(VALUE(P16)>=VALUE("00:00"),VALUE(P16)<=VALUE("01:59")),"00:00 a 02:00",IF(AND(VALUE(P16)>=VALUE("02:00"),VALUE(P16)<=VALUE("03:59")),"02:00 a 04:00",IF(AND(VALUE(P16)>=VALUE("04:00"),VALUE(P16)<=VALUE("05:59")),"04:00 a 06:00",IF(AND(VALUE(P16)>=VALUE("06:00"),VALUE(P16)<=VALUE("07:59")),"06:00 a 08:00",IF(AND(VALUE(P16)>=VALUE("08:00"),VALUE(P16)<=VALUE("09:59")),"08:00 a 10:00",IF(AND(VALUE(P16)>=VALUE("10:00"),VALUE(P16)<=VALUE("11:59")),"10:00 a 12:00",IF(AND(VALUE(P16)>=VALUE("12:00"),VALUE(P16)<=VALUE("13:59")),"12:00 a 14:00",IF(AND(VALUE(P16)>=VALUE("14:00"),VALUE(P16)<=VALUE("15:59")),"14:00 a 16:00",IF(AND(VALUE(P16)>=VALUE("16:00"),VALUE(P16)<=VALUE("17:59")),"16:00 a 18:00",IF(AND(VALUE(P16)>=VALUE("18:00"),VALUE(P16)<=VALUE("19:59")),"18:00 a 20:00",IF(AND(VALUE(P16)>=VALUE("20:00"),VALUE(P16)<=VALUE("21:59")),"20:00 a 22:00",IF(AND(VALUE(P16)>=VALUE("22:00"),VALUE(P16)<=VALUE("23:59")),"22:00 a 00:00","no corresponde")))))))))))) -> 02:00 a 04:00 | D16: ARGUELLO | E16: QUINTANA, GILDA | F16: 3 | G16: CACERES, MATIAS NAHUEL | H16: 919853 | I16: 46737683 | J16: CHACARITA | K16: ROBO/HURTO | M16: ROBO/HURTO | N16: PALERMO O151 | O16: Palermo | P16: 0.125 | Q16: 0.16666667 | R16: 0.12708333 | S16: - | T16: - | U16: - | V16: - | W16: SE TOMA CONOCIMIENTO MEDIANTE CARTA SAE SOBRE DENUNCIANTE QUIEN REFIERE QUE HABRIA UN MASCULINO ELCUAL ROMPIO EL VIDRIODE U NVEHICULO TOYOUA ESTACIONADO EN LA VIA PUBLICA. SE VISUALIZ MASCULINO DE SIMILARES CARACTERISTICAS EN EL LUGAR. SEGUIDAMENTE SE VERIFICALINEA DE TIEMPO OBSERVANDO AL AMSCULINO APROXIMARSE AL VEHICULO E INTRODUCIR PARTE DEL TORSO PARA LUEGO RETIRARSE SIN LOGRAR OBSERVAR SI SUSTRAE ALGUN TIPO DE ELEMENTO. ARRIBA PERSONAL POLICIAL. SE INFORMA SE HALOLA VEHICULO CON PARABRISASA TRASERO VIOLENTADO.Posteriormente se toma conocimiento mediante la ampliación de la carta SAE Fiscalía n°29 a cargo del Dr. Herrera secretaria única a cargo de la Dra. Tedezco actuaciones en flagrancia con tentativa de robo | X16: 0 | Y16: 1 | Z16: 0 | AA16: 14A | AB16: U | AC16: CARTA | AD16: SISEP | AE16: 1 DETENIDO | AF16: FINALIZA CON IMPUTADO/S | AL16: =VLOOKUP(G16,Hoja2!P:Q,2,0) -> 42930433 | AM16: =IF(OR(Y16>0,X16>0),"IMPUTADO","NADA") -> IMPUTADO | AN16: =IF(AND(AM16="IMPUTADO",ISBLANK(M16)),"FALTO","NO") -> NO
A17: 45992 | B17: =IF(AND(VALUE(P17)>=VALUE("06:00"),VALUE(P17)<=VALUE("17:59")),"06 A 18","18 A 06") -> 18 A 06 | C17: =IF(AND(VALUE(P17)>=VALUE("00:00"),VALUE(P17)<=VALUE("01:59")),"00:00 a 02:00",IF(AND(VALUE(P17)>=VALUE("02:00"),VALUE(P17)<=VALUE("03:59")),"02:00 a 04:00",IF(AND(VALUE(P17)>=VALUE("04:00"),VALUE(P17)<=VALUE("05:59")),"04:00 a 06:00",IF(AND(VALUE(P17)>=VALUE("06:00"),VALUE(P17)<=VALUE("07:59")),"06:00 a 08:00",IF(AND(VALUE(P17)>=VALUE("08:00"),VALUE(P17)<=VALUE("09:59")),"08:00 a 10:00",IF(AND(VALUE(P17)>=VALUE("10:00"),VALUE(P17)<=VALUE("11:59")),"10:00 a 12:00",IF(AND(VALUE(P17)>=VALUE("12:00"),VALUE(P17)<=VALUE("13:59")),"12:00 a 14:00",IF(AND(VALUE(P17)>=VALUE("14:00"),VALUE(P17)<=VALUE("15:59")),"14:00 a 16:00",IF(AND(VALUE(P17)>=VALUE("16:00"),VALUE(P17)<=VALUE("17:59")),"16:00 a 18:00",IF(AND(VALUE(P17)>=VALUE("18:00"),VALUE(P17)<=VALUE("19:59")),"18:00 a 20:00",IF(AND(VALUE(P17)>=VALUE("20:00"),VALUE(P17)<=VALUE("21:59")),"20:00 a 22:00",IF(AND(VALUE(P17)>=VALUE("22:00"),VALUE(P17)<=VALUE("23:59")),"22:00 a 00:00","no corresponde")))))))))))) -> 02:00 a 04:00 | D17: ARGUELLO | E17: QUINTANA, GILDA | F17: 3 | G17: CUELLAR, CAMILA | H17: 919842 | I17: 46737728 | J17: CHACARITA | K17: COLABORACION | L17: IDENT. VEHICULAR | N17: PARQUE CHACABUCO71 | O17: Parque Chacabuco | P17: 0.13402778 | Q17: 0.13819444 | R17: 0.13402778 | S17: - | T17: - | U17: - | V17: - | W17: SE TOMA CONOCIMIENTO MEDIANTE CARTA SAE SOBRE DENUNCIANTE QUIEN REFIERE QUE HABRIA UN AUTOMOVIL ESTACIONADO EN SITUACION EXTRAÑA HABRIAN CINCO PERSONAS EN EL VEHICULO. ESTARIAN ALCOHOLIZADOS. SE VISUALIZA SARRIBO DE PERSONAL POLICIAL. SE INFORMA SE TRATO DE VEHICULO CON PROBLEMAS MECANICOS. SE ENCUENTRA AGUARDANDO GRUA.- | X17: 0 | Y17: 0 | Z17: 0 | AA17: 7B | AB17: U | AC17: CARTA | AF17: CARTA FINALIZADA | AL17: =VLOOKUP(G17,Hoja2!P:Q,2,0) -> 46280094 | AM17: =IF(OR(Y17>0,X17>0),"IMPUTADO","NADA") -> NADA | AN17: =IF(AND(AM17="IMPUTADO",ISBLANK(M17)),"FALTO","NO") -> NO
A18: 45992 | B18: =IF(AND(VALUE(P18)>=VALUE("06:00"),VALUE(P18)<=VALUE("17:59")),"06 A 18","18 A 06") -> 18 A 06 | C18: =IF(AND(VALUE(P18)>=VALUE("00:00"),VALUE(P18)<=VALUE("01:59")),"00:00 a 02:00",IF(AND(VALUE(P18)>=VALUE("02:00"),VALUE(P18)<=VALUE("03:59")),"02:00 a 04:00",IF(AND(VALUE(P18)>=VALUE("04:00"),VALUE(P18)<=VALUE("05:59")),"04:00 a 06:00",IF(AND(VALUE(P18)>=VALUE("06:00"),VALUE(P18)<=VALUE("07:59")),"06:00 a 08:00",IF(AND(VALUE(P18)>=VALUE("08:00"),VALUE(P18)<=VALUE("09:59")),"08:00 a 10:00",IF(AND(VALUE(P18)>=VALUE("10:00"),VALUE(P18)<=VALUE("11:59")),"10:00 a 12:00",IF(AND(VALUE(P18)>=VALUE("12:00"),VALUE(P18)<=VALUE("13:59")),"12:00 a 14:00",IF(AND(VALUE(P18)>=VALUE("14:00"),VALUE(P18)<=VALUE("15:59")),"14:00 a 16:00",IF(AND(VALUE(P18)>=VALUE("16:00"),VALUE(P18)<=VALUE("17:59")),"16:00 a 18:00",IF(AND(VALUE(P18)>=VALUE("18:00"),VALUE(P18)<=VALUE("19:59")),"18:00 a 20:00",IF(AND(VALUE(P18)>=VALUE("20:00"),VALUE(P18)<=VALUE("21:59")),"20:00 a 22:00",IF(AND(VALUE(P18)>=VALUE("22:00"),VALUE(P18)<=VALUE("23:59")),"22:00 a 00:00","no corresponde")))))))))))) -> 02:00 a 04:00 | D18: ARGUELLO | E18: QUINTANA, GILDA | F18: 3 | G18: GONZALEZ, ARACELI | H18: 919891 | I18: 46737754 | J18: CHACARITA | K18: IDENTIFICACION DE PERSONAS | N18: BALVANERA 44 | O18: Balvanera | P18: 0.13402778 | Q18: 0.14166667 | R18: 0.13819444 | S18: - | T18: - | U18: - | V18: - | W18: SE TOMA CONOCIMIENTO MEDIANTE CARTA SAE SOBRE DENUNCIANTE QUIEN REFIERE QUE HABRIA UNA PERSONA QUE SE ENCUENTRA TOCANDO EL TIMBRE DEL DEPARTAMENTO. SE VISUALIZA FEMENINO Y MASCULINO EN CERCANIAS DE INGRESO DE EDIFICIO. ARRIBA PERSONAL POLICIAL. SE INFORMA SE IDENTIFICA SIN NOVEDAD. PANORAMA NORMAL.- | X18: 0 | Y18: 0 | Z18: 0 | AA18: 3C | AB18: U | AC18: CARTA | AD18: SISEP | AF18: CARTA FINALIZADA | AL18: =VLOOKUP(G18,Hoja2!P:Q,2,0) -> 94914642 | AM18: =IF(OR(Y18>0,X18>0),"IMPUTADO","NADA") -> NADA | AN18: =IF(AND(AM18="IMPUTADO",ISBLANK(M18)),"FALTO","NO") -> NO
A19: 45992 | B19: =IF(AND(VALUE(P19)>=VALUE("06:00"),VALUE(P19)<=VALUE("17:59")),"06 A 18","18 A 06") -> 18 A 06 | C19: =IF(AND(VALUE(P19)>=VALUE("00:00"),VALUE(P19)<=VALUE("01:59")),"00:00 a 02:00",IF(AND(VALUE(P19)>=VALUE("02:00"),VALUE(P19)<=VALUE("03:59")),"02:00 a 04:00",IF(AND(VALUE(P19)>=VALUE("04:00"),VALUE(P19)<=VALUE("05:59")),"04:00 a 06:00",IF(AND(VALUE(P19)>=VALUE("06:00"),VALUE(P19)<=VALUE("07:59")),"06:00 a 08:00",IF(AND(VALUE(P19)>=VALUE("08:00"),VALUE(P19)<=VALUE("09:59")),"08:00 a 10:00",IF(AND(VALUE(P19)>=VALUE("10:00"),VALUE(P19)<=VALUE("11:59")),"10:00 a 12:00",IF(AND(VALUE(P19)>=VALUE("12:00"),VALUE(P19)<=VALUE("13:59")),"12:00 a 14:00",IF(AND(VALUE(P19)>=VALUE("14:00"),VALUE(P19)<=VALUE("15:59")),"14:00 a 16:00",IF(AND(VALUE(P19)>=VALUE("16:00"),VALUE(P19)<=VALUE("17:59")),"16:00 a 18:00",IF(AND(VALUE(P19)>=VALUE("18:00"),VALUE(P19)<=VALUE("19:59")),"18:00 a 20:00",IF(AND(VALUE(P19)>=VALUE("20:00"),VALUE(P19)<=VALUE("21:59")),"20:00 a 22:00",IF(AND(VALUE(P19)>=VALUE("22:00"),VALUE(P19)<=VALUE("23:59")),"22:00 a 00:00","no corresponde")))))))))))) -> 02:00 a 04:00 | D19: ARGUELLO | E19: QUINTANA, GILDA | F19: 3 | G19: FEDELLE, SANDRA ANALIA | H19: 919844 | I19: 46737810 | J19: CHACARITA | K19: IDENTIFICACION DE PERSONAS | N19: VILLA CRESPO10 | O19: Villa Crespo | P19: 0.15069444 | Q19: 0.15763889 | R19: 0.15277778 | S19: - | T19: - | U19: - | V19: - | W19: SE TOMA CONOCIMIENTO MEDIANTE CARTA SAE SOBRE DENUNCIANTE QUIEN REFIERE QUE HABRIA UN AUTO ESTACIONADO EN CONTRAMANO. SE VISUALIZAVEHICULO APORTADO REALIZANDO MANIOBRAS PELIGROSAS SOBRE AV. CORRIENTES. ARRIBA PERSONAL POLICIAL REFIERE SIN NOVEDAD. MASCULINO SE HABIA EQUIVOCADO DE SENTIDO.- | X19: 0 | Y19: 0 | Z19: 0 | AA19: 15B | AB19: U | AC19: CARTA | AD19: SISEP | AF19: CARTA FINALIZADA | AL19: =VLOOKUP(G19,Hoja2!P:Q,2,0) -> 34210219 | AM19: =IF(OR(Y19>0,X19>0),"IMPUTADO","NADA") -> NADA | AN19: =IF(AND(AM19="IMPUTADO",ISBLANK(M19)),"FALTO","NO") -> NO
A20: 45992 | B20: =IF(AND(VALUE(P20)>=VALUE("06:00"),VALUE(P20)<=VALUE("17:59")),"06 A 18","18 A 06") -> 18 A 06 | C20: =IF(AND(VALUE(P20)>=VALUE("00:00"),VALUE(P20)<=VALUE("01:59")),"00:00 a 02:00",IF(AND(VALUE(P20)>=VALUE("02:00"),VALUE(P20)<=VALUE("03:59")),"02:00 a 04:00",IF(AND(VALUE(P20)>=VALUE("04:00"),VALUE(P20)<=VALUE("05:59")),"04:00 a 06:00",IF(AND(VALUE(P20)>=VALUE("06:00"),VALUE(P20)<=VALUE("07:59")),"06:00 a 08:00",IF(AND(VALUE(P20)>=VALUE("08:00"),VALUE(P20)<=VALUE("09:59")),"08:00 a 10:00",IF(AND(VALUE(P20)>=VALUE("10:00"),VALUE(P20)<=VALUE("11:59")),"10:00 a 12:00",IF(AND(VALUE(P20)>=VALUE("12:00"),VALUE(P20)<=VALUE("13:59")),"12:00 a 14:00",IF(AND(VALUE(P20)>=VALUE("14:00"),VALUE(P20)<=VALUE("15:59")),"14:00 a 16:00",IF(AND(VALUE(P20)>=VALUE("16:00"),VALUE(P20)<=VALUE("17:59")),"16:00 a 18:00",IF(AND(VALUE(P20)>=VALUE("18:00"),VALUE(P20)<=VALUE("19:59")),"18:00 a 20:00",IF(AND(VALUE(P20)>=VALUE("20:00"),VALUE(P20)<=VALUE("21:59")),"20:00 a 22:00",IF(AND(VALUE(P20)>=VALUE("22:00"),VALUE(P20)<=VALUE("23:59")),"22:00 a 00:00","no corresponde")))))))))))) -> 02:00 a 04:00 | D20: ARGUELLO | E20: QUINTANA, GILDA | F20: 3 | G20: CACERES, MATIAS NAHUEL | H20: 919864 | I20: 46737880 | J20: CHACARITA | K20: COLABORACION | L20: INCIDENCIA | N20: PALERMO90 | O20: Palermo | P20: 0.16388889 | Q20: 0.17152778 | R20: 0.16527778 | S20: - | T20: - | U20: - | V20: - | W20: SE VISUALIZA PERSONAL POLICIAL INGRESANDO A ESTACION DE FERROCARRIL, ESTACION PALERMO, SE VISUALIZA INCIDENCIA ENTRE DOS PERSONAS EN AL VIA PUBLICA..HT INF QUE SE TRATO INCIDENCIA ENTRE MASCULINOS, LOS MISMOS SE RETIRAN SIN APORTAR DATOS.- | X20: 0 | Y20: 0 | Z20: 0 | AA20: 14B | AB20: U | AC20: MONITOREO | AD20: SISEP | AF20: CARTA FINALIZADA | AL20: =VLOOKUP(G20,Hoja2!P:Q,2,0) -> 42930433 | AM20: =IF(OR(Y20>0,X20>0),"IMPUTADO","NADA") -> NADA | AN20: =IF(AND(AM20="IMPUTADO",ISBLANK(M20)),"FALTO","NO") -> NO
A21: 45992 | B21: =IF(AND(VALUE(P21)>=VALUE("06:00"),VALUE(P21)<=VALUE("17:59")),"06 A 18","18 A 06") -> 18 A 06 | C21: =IF(AND(VALUE(P21)>=VALUE("00:00"),VALUE(P21)<=VALUE("01:59")),"00:00 a 02:00",IF(AND(VALUE(P21)>=VALUE("02:00"),VALUE(P21)<=VALUE("03:59")),"02:00 a 04:00",IF(AND(VALUE(P21)>=VALUE("04:00"),VALUE(P21)<=VALUE("05:59")),"04:00 a 06:00",IF(AND(VALUE(P21)>=VALUE("06:00"),VALUE(P21)<=VALUE("07:59")),"06:00 a 08:00",IF(AND(VALUE(P21)>=VALUE("08:00"),VALUE(P21)<=VALUE("09:59")),"08:00 a 10:00",IF(AND(VALUE(P21)>=VALUE("10:00"),VALUE(P21)<=VALUE("11:59")),"10:00 a 12:00",IF(AND(VALUE(P21)>=VALUE("12:00"),VALUE(P21)<=VALUE("13:59")),"12:00 a 14:00",IF(AND(VALUE(P21)>=VALUE("14:00"),VALUE(P21)<=VALUE("15:59")),"14:00 a 16:00",IF(AND(VALUE(P21)>=VALUE("16:00"),VALUE(P21)<=VALUE("17:59")),"16:00 a 18:00",IF(AND(VALUE(P21)>=VALUE("18:00"),VALUE(P21)<=VALUE("19:59")),"18:00 a 20:00",IF(AND(VALUE(P21)>=VALUE("20:00"),VALUE(P21)<=VALUE("21:59")),"20:00 a 22:00",IF(AND(VALUE(P21)>=VALUE("22:00"),VALUE(P21)<=VALUE("23:59")),"22:00 a 00:00","no corresponde")))))))))))) -> 04:00 a 06:00 | D21: ARGUELLO | E21: CORTES SEBASTIAN | F21: 3 | G21: FERREYRA, SONIA CRISTINA | H21: 919889 | I21: 46737944 | J21: VILLA LUGANO | K21: IDENTIFICACION DE PERSONAS | N21: NUEVA POMPEYA 72 | O21: Nueva Pompeya | P21: 0.17569444 | Q21: 0.18888889 | R21: 0.17847222 | W21: SE VISUALIZA POR CAMARA NUEVA POMPEYA 72 UN MASCULINO JUNTO A UN FEMENINO AMBOS DE MANERA EXTRAÑA AL LADO DE UN MOTOVEHICULO OBSERVANDO PARA LA ESQUINA DE MOM SE DA AVISO A COMANDO GENERAN CARTA SAE MASCULINO DE ROPAS OSCURAS Y CASCO NEGRO FEMNINO DE CAMPERA NEGRA PANTALON DE JEANS AZUL CASCO NEGRO Y BLANCO CON DETALLES ROSAS Y UNA BOLSA BLANCA EN LA MANO SE VISUALIZA EL ARRIBO DE PERSONAL 904 INF SE IDENTIFICO A LAS PERSONAS Y EL MOTOVEHICULO LOS CUALES CORRESPONDEN Y NO POSEEN IMPEDIMENTOS,PNA NORMAL | X21: 0 | Y21: 0 | Z21: 0 | AA21: 4A | AB21: U | AC21: MONITOREO | AF21: CARTA FINALIZADA | AL21: =VLOOKUP(G21,Hoja2!P:Q,2,0) -> 30461376 | AM21: =IF(OR(Y21>0,X21>0),"IMPUTADO","NADA") -> NADA | AN21: =IF(AND(AM21="IMPUTADO",ISBLANK(M21)),"FALTO","NO") -> NO
A22: 45992 | B22: =IF(AND(VALUE(P22)>=VALUE("06:00"),VALUE(P22)<=VALUE("17:59")),"06 A 18","18 A 06") -> 18 A 06 | C22: =IF(AND(VALUE(P22)>=VALUE("00:00"),VALUE(P22)<=VALUE("01:59")),"00:00 a 02:00",IF(AND(VALUE(P22)>=VALUE("02:00"),VALUE(P22)<=VALUE("03:59")),"02:00 a 04:00",IF(AND(VALUE(P22)>=VALUE("04:00"),VALUE(P22)<=VALUE("05:59")),"04:00 a 06:00",IF(AND(VALUE(P22)>=VALUE("06:00"),VALUE(P22)<=VALUE("07:59")),"06:00 a 08:00",IF(AND(VALUE(P22)>=VALUE("08:00"),VALUE(P22)<=VALUE("09:59")),"08:00 a 10:00",IF(AND(VALUE(P22)>=VALUE("10:00"),VALUE(P22)<=VALUE("11:59")),"10:00 a 12:00",IF(AND(VALUE(P22)>=VALUE("12:00"),VALUE(P22)<=VALUE("13:59")),"12:00 a 14:00",IF(AND(VALUE(P22)>=VALUE("14:00"),VALUE(P22)<=VALUE("15:59")),"14:00 a 16:00",IF(AND(VALUE(P22)>=VALUE("16:00"),VALUE(P22)<=VALUE("17:59")),"16:00 a 18:00",IF(AND(VALUE(P22)>=VALUE("18:00"),VALUE(P22)<=VALUE("19:59")),"18:00 a 20:00",IF(AND(VALUE(P22)>=VALUE("20:00"),VALUE(P22)<=VALUE("21:59")),"20:00 a 22:00",IF(AND(VALUE(P22)>=VALUE("22:00"),VALUE(P22)<=VALUE("23:59")),"22:00 a 00:00","no corresponde")))))))))))) -> 04:00 a 06:00 | D22: ARGUELLO | E22: ALCARAZ, ARIEL | F22: 3 | G22: SCHIRRIPA, ESTEBAN | H22: 919886 | I22: 46737973 | J22: CHACARITA | K22: ROBO/HURTO | M22: ROBO/HURTO | N22: ALMAGRO O175 | O22: Almagro | P22: 0.18819444 | Q22: 0.19027778 | R22: 0.18819444 | S22: - | T22: - | U22: - | V22: - | W22: SE TOMA CONOCIMIENTO MEDIANTE CARTA SAE OSBRE DENUNCIANTE QUIEN REFIERE QUE HABRIA UN MASCULINO ROBANDO A UNN AUTOMOVIL. SE ROBO DOS CAJAS Y UNA MOCHILA DEL INTERIOR DE LA MISMA Y LUEGO SE DA A LA FUGA. SE VISUALIZA MASCULINO PORTANDO UAN CAJA COLOR MARRON Y UNA MOCHILA DESPLAZANDOSE DANDOSE A LA FUGA. ARRIBA PERSONAL POLICIAL DANDO CON EL MISMO. PERSONAL INFORMA EL MASCULINO POSEE UN ESTEREO DEL VEHICULO Y DOS CAJAS DE CARTON. ACTUACIONES TTVA ROBO | X22: 0 | Y22: 1 | Z22: 0 | AA22: 5A | AB22: U | AC22: CARTA | AD22: SISEP | AE22: 1 DETENIDO.- | AF22: FINALIZA CON IMPUTADO/S | AL22: =VLOOKUP(G22,Hoja2!P:Q,2,0) -> 22310347 | AM22: =IF(OR(Y22>0,X22>0),"IMPUTADO","NADA") -> IMPUTADO | AN22: =IF(AND(AM22="IMPUTADO",ISBLANK(M22)),"FALTO","NO") -> NO
A23: 45992 | B23: =IF(AND(VALUE(P23)>=VALUE("06:00"),VALUE(P23)<=VALUE("17:59")),"06 A 18","18 A 06") -> 18 A 06 | C23: =IF(AND(VALUE(P23)>=VALUE("00:00"),VALUE(P23)<=VALUE("01:59")),"00:00 a 02:00",IF(AND(VALUE(P23)>=VALUE("02:00"),VALUE(P23)<=VALUE("03:59")),"02:00 a 04:00",IF(AND(VALUE(P23)>=VALUE("04:00"),VALUE(P23)<=VALUE("05:59")),"04:00 a 06:00",IF(AND(VALUE(P23)>=VALUE("06:00"),VALUE(P23)<=VALUE("07:59")),"06:00 a 08:00",IF(AND(VALUE(P23)>=VALUE("08:00"),VALUE(P23)<=VALUE("09:59")),"08:00 a 10:00",IF(AND(VALUE(P23)>=VALUE("10:00"),VALUE(P23)<=VALUE("11:59")),"10:00 a 12:00",IF(AND(VALUE(P23)>=VALUE("12:00"),VALUE(P23)<=VALUE("13:59")),"12:00 a 14:00",IF(AND(VALUE(P23)>=VALUE("14:00"),VALUE(P23)<=VALUE("15:59")),"14:00 a 16:00",IF(AND(VALUE(P23)>=VALUE("16:00"),VALUE(P23)<=VALUE("17:59")),"16:00 a 18:00",IF(AND(VALUE(P23)>=VALUE("18:00"),VALUE(P23)<=VALUE("19:59")),"18:00 a 20:00",IF(AND(VALUE(P23)>=VALUE("20:00"),VALUE(P23)<=VALUE("21:59")),"20:00 a 22:00",IF(AND(VALUE(P23)>=VALUE("22:00"),VALUE(P23)<=VALUE("23:59")),"22:00 a 00:00","no corresponde")))))))))))) -> 00:00 a 02:00 | D23: ARGUELLO | E23: CARABAJAL, GRACIELA | F23: 3 | G23: REINAGA, MARTIN | I23: 46737983 | J23: PUERTO MADERO | K23: ROBO/HURTO | N23: SAN NICOLAS 38 | O23: San Nicolas | P23: 0.065972222 | Q23: 0.11111111 | R23: 0.075 | S23: - | T23: - | U23: - | V23: - | W23: SE TOMA CONOCIMIENTO MEDIANTE CARTA SAE QUE UN MASCULINO SUSTRAJO ELEMENTOS DE UNA OBRA EN CONSTRUCCION. PERSONAL POLICIAL DA CON EL MASCULINO QUE SE RETIRA NO HABIENDO TOMADO TEMPERAMENTO PARA EL . | X23: 0 | Y23: 0 | Z23: 0 | AA23: 1D | AB23: U | AC23: CARTA | AF23: CARTA FINALIZADA | AL23: =VLOOKUP(G23,Hoja2!P:Q,2,0) -> 43819657 | AM23: =IF(OR(Y23>0,X23>0),"IMPUTADO","NADA") -> NADA | AN23: =IF(AND(AM23="IMPUTADO",ISBLANK(M23)),"FALTO","NO") -> NO
A24: 45992 | B24: =IF(AND(VALUE(P24)>=VALUE("06:00"),VALUE(P24)<=VALUE("17:59")),"06 A 18","18 A 06") -> 18 A 06 | C24: =IF(AND(VALUE(P24)>=VALUE("00:00"),VALUE(P24)<=VALUE("01:59")),"00:00 a 02:00",IF(AND(VALUE(P24)>=VALUE("02:00"),VALUE(P24)<=VALUE("03:59")),"02:00 a 04:00",IF(AND(VALUE(P24)>=VALUE("04:00"),VALUE(P24)<=VALUE("05:59")),"04:00 a 06:00",IF(AND(VALUE(P24)>=VALUE("06:00"),VALUE(P24)<=VALUE("07:59")),"06:00 a 08:00",IF(AND(VALUE(P24)>=VALUE("08:00"),VALUE(P24)<=VALUE("09:59")),"08:00 a 10:00",IF(AND(VALUE(P24)>=VALUE("10:00"),VALUE(P24)<=VALUE("11:59")),"10:00 a 12:00",IF(AND(VALUE(P24)>=VALUE("12:00"),VALUE(P24)<=VALUE("13:59")),"12:00 a 14:00",IF(AND(VALUE(P24)>=VALUE("14:00"),VALUE(P24)<=VALUE("15:59")),"14:00 a 16:00",IF(AND(VALUE(P24)>=VALUE("16:00"),VALUE(P24)<=VALUE("17:59")),"16:00 a 18:00",IF(AND(VALUE(P24)>=VALUE("18:00"),VALUE(P24)<=VALUE("19:59")),"18:00 a 20:00",IF(AND(VALUE(P24)>=VALUE("20:00"),VALUE(P24)<=VALUE("21:59")),"20:00 a 22:00",IF(AND(VALUE(P24)>=VALUE("22:00"),VALUE(P24)<=VALUE("23:59")),"22:00 a 00:00","no corresponde")))))))))))) -> 04:00 a 06:00 | D24: ARGUELLO | E24: ALCARAZ, ARIEL | F24: 3 | G24: MEZA, ROMINA | H24: 919852 | I24: 46737990 | J24: CHACARITA | K24: INCIDENCIA EN VIA PUBLICA | N24: BALVANERA65 | O24: Balvanera | P24: 0.1875 | Q24: 0.21458333 | R24: 0.19305556 | S24: - | T24: - | U24: - | V24: - | W24: SE TOMA CONOCIMIENTO MEDIANTE CARTA SAE SOBRE DENUNCIANTE QUIEN REFIERE QUE HABRIA UNA PERSONA INCONSCIENTE LUEGO DE UNA PELEA. SE VISUALIZA PERSONAL IDENTIFICANDO A MASCULINO Y DOS FEMENINOS. SE INFORMA SE TRATO DE INCIDENCIA SOLUCIONADA SIN NOVEDAD.- | X24: 0 | Y24: 0 | Z24: 0 | AA24: 3C | AB24: U | AC24: CARTA | AD24: SISEP | AF24: CARTA FINALIZADA | AL24: =VLOOKUP(G24,Hoja2!P:Q,2,0) -> 39712754 | AM24: =IF(OR(Y24>0,X24>0),"IMPUTADO","NADA") -> NADA | AN24: =IF(AND(AM24="IMPUTADO",ISBLANK(M24)),"FALTO","NO") -> NO
A25: 45992 | B25: =IF(AND(VALUE(P25)>=VALUE("06:00"),VALUE(P25)<=VALUE("17:59")),"06 A 18","18 A 06") -> 18 A 06 | C25: =IF(AND(VALUE(P25)>=VALUE("00:00"),VALUE(P25)<=VALUE("01:59")),"00:00 a 02:00",IF(AND(VALUE(P25)>=VALUE("02:00"),VALUE(P25)<=VALUE("03:59")),"02:00 a 04:00",IF(AND(VALUE(P25)>=VALUE("04:00"),VALUE(P25)<=VALUE("05:59")),"04:00 a 06:00",IF(AND(VALUE(P25)>=VALUE("06:00"),VALUE(P25)<=VALUE("07:59")),"06:00 a 08:00",IF(AND(VALUE(P25)>=VALUE("08:00"),VALUE(P25)<=VALUE("09:59")),"08:00 a 10:00",IF(AND(VALUE(P25)>=VALUE("10:00"),VALUE(P25)<=VALUE("11:59")),"10:00 a 12:00",IF(AND(VALUE(P25)>=VALUE("12:00"),VALUE(P25)<=VALUE("13:59")),"12:00 a 14:00",IF(AND(VALUE(P25)>=VALUE("14:00"),VALUE(P25)<=VALUE("15:59")),"14:00 a 16:00",IF(AND(VALUE(P25)>=VALUE("16:00"),VALUE(P25)<=VALUE("17:59")),"16:00 a 18:00",IF(AND(VALUE(P25)>=VALUE("18:00"),VALUE(P25)<=VALUE("19:59")),"18:00 a 20:00",IF(AND(VALUE(P25)>=VALUE("20:00"),VALUE(P25)<=VALUE("21:59")),"20:00 a 22:00",IF(AND(VALUE(P25)>=VALUE("22:00"),VALUE(P25)<=VALUE("23:59")),"22:00 a 00:00","no corresponde")))))))))))) -> 04:00 a 06:00 | D25: ARGUELLO | E25: COLO, NADIA | F25: 3 | G25: REINAGA, MARTIN | H25: 918447 | I25: 46738015 | J25: PUERTO MADERO | K25: IDENTIFICACION DE PERSONAS | N25: RECOLETA96 | O25: Recoleta | P25: 0.19652778 | Q25: 0.23958333 | R25: 0.19930556 | S25: - | T25: - | U25: - | V25: - | W25: SE TOMA CONOCIMIENTO MEDIANTE CARTA SAE POR CUATRO MASCULINOS QUE HABRIAN INGRESADO A UN DEPARTAMENTO MIENTRAS EL DUEÑO DORMIA. LOS CAUSANTES ATARON AL DUEÑO CON PRECINTOS Y SE LLEVARON PERTENENCIAS. SE VERIFICO EL EDIFICIO NO SE LOGRO DAR CON LOS CAUSANTES. | X25: 0 | Y25: 0 | Z25: 0 | AA25: 2A | AB25: U | AC25: CARTA | AF25: CARTA FINALIZADA | AL25: =VLOOKUP(G25,Hoja2!P:Q,2,0) -> 43819657 | AM25: =IF(OR(Y25>0,X25>0),"IMPUTADO","NADA") -> NADA | AN25: =IF(AND(AM25="IMPUTADO",ISBLANK(M25)),"FALTO","NO") -> NO
A26: 45992 | B26: =IF(AND(VALUE(P26)>=VALUE("06:00"),VALUE(P26)<=VALUE("17:59")),"06 A 18","18 A 06") -> 18 A 06 | C26: =IF(AND(VALUE(P26)>=VALUE("00:00"),VALUE(P26)<=VALUE("01:59")),"00:00 a 02:00",IF(AND(VALUE(P26)>=VALUE("02:00"),VALUE(P26)<=VALUE("03:59")),"02:00 a 04:00",IF(AND(VALUE(P26)>=VALUE("04:00"),VALUE(P26)<=VALUE("05:59")),"04:00 a 06:00",IF(AND(VALUE(P26)>=VALUE("06:00"),VALUE(P26)<=VALUE("07:59")),"06:00 a 08:00",IF(AND(VALUE(P26)>=VALUE("08:00"),VALUE(P26)<=VALUE("09:59")),"08:00 a 10:00",IF(AND(VALUE(P26)>=VALUE("10:00"),VALUE(P26)<=VALUE("11:59")),"10:00 a 12:00",IF(AND(VALUE(P26)>=VALUE("12:00"),VALUE(P26)<=VALUE("13:59")),"12:00 a 14:00",IF(AND(VALUE(P26)>=VALUE("14:00"),VALUE(P26)<=VALUE("15:59")),"14:00 a 16:00",IF(AND(VALUE(P26)>=VALUE("16:00"),VALUE(P26)<=VALUE("17:59")),"16:00 a 18:00",IF(AND(VALUE(P26)>=VALUE("18:00"),VALUE(P26)<=VALUE("19:59")),"18:00 a 20:00",IF(AND(VALUE(P26)>=VALUE("20:00"),VALUE(P26)<=VALUE("21:59")),"20:00 a 22:00",IF(AND(VALUE(P26)>=VALUE("22:00"),VALUE(P26)<=VALUE("23:59")),"22:00 a 00:00","no corresponde")))))))))))) -> 04:00 a 06:00 | D26: ARGUELLO | E26: QUINTANA, GILDA | F26: 3 | G26: MONTIEL, JUAN | I26: 46738098 | J26: CHACARITA | K26: COLABORACION | L26: CHOQUE | M26: LESIONES | N26: ALMAGRO05 | O26: Almagro | P26: 0.2 | W26: SE TOMA CONOCIMIENTO MEDIANTE CARTA SAE SOBREDENUNCIANTE QUIEN REFIERE QUE ATROPELLARON A UN OFICIAL DE POLICIA LDE LA CIUDAD. SEVISUALIZA PERSONAL ASISTIENDO A UNA PERSONA TENDIDA SOBRE LA CINTA ASFALTICA. ARRIBA SAME. | X26: 0 | Y26: 1 | Z26: 0 | AA26: 5A | AB26: U | AC26: CARTA | AF26: COLABORACION CON IMPUTADO/S | AL26: =VLOOKUP(G26,Hoja2!P:Q,2,0) -> 46252382 | AM26: =IF(OR(Y26>0,X26>0),"IMPUTADO","NADA") -> IMPUTADO | AN26: =IF(AND(AM26="IMPUTADO",ISBLANK(M26)),"FALTO","NO") -> NO
A27: 45992 | B27: =IF(AND(VALUE(P27)>=VALUE("06:00"),VALUE(P27)<=VALUE("17:59")),"06 A 18","18 A 06") -> 06 A 18 | C27: =IF(AND(VALUE(P27)>=VALUE("00:00"),VALUE(P27)<=VALUE("01:59")),"00:00 a 02:00",IF(AND(VALUE(P27)>=VALUE("02:00"),VALUE(P27)<=VALUE("03:59")),"02:00 a 04:00",IF(AND(VALUE(P27)>=VALUE("04:00"),VALUE(P27)<=VALUE("05:59")),"04:00 a 06:00",IF(AND(VALUE(P27)>=VALUE("06:00"),VALUE(P27)<=VALUE("07:59")),"06:00 a 08:00",IF(AND(VALUE(P27)>=VALUE("08:00"),VALUE(P27)<=VALUE("09:59")),"08:00 a 10:00",IF(AND(VALUE(P27)>=VALUE("10:00"),VALUE(P27)<=VALUE("11:59")),"10:00 a 12:00",IF(AND(VALUE(P27)>=VALUE("12:00"),VALUE(P27)<=VALUE("13:59")),"12:00 a 14:00",IF(AND(VALUE(P27)>=VALUE("14:00"),VALUE(P27)<=VALUE("15:59")),"14:00 a 16:00",IF(AND(VALUE(P27)>=VALUE("16:00"),VALUE(P27)<=VALUE("17:59")),"16:00 a 18:00",IF(AND(VALUE(P27)>=VALUE("18:00"),VALUE(P27)<=VALUE("19:59")),"18:00 a 20:00",IF(AND(VALUE(P27)>=VALUE("20:00"),VALUE(P27)<=VALUE("21:59")),"20:00 a 22:00",IF(AND(VALUE(P27)>=VALUE("22:00"),VALUE(P27)<=VALUE("23:59")),"22:00 a 00:00","no corresponde")))))))))))) -> 06:00 a 08:00 | D27: MARTINEZ. R | E27: MEZA, GASTON | F27: 1 | G27: ROJAS MELANIE | H27: 918234 | I27: 46738272 | J27: CMU 9 DE JULIO | K27: INCIDENCIA EN VIA PUBLICA | M27: PEDIDO DE CAPTURA | N27: CONSTITUCION 23 | O27: Constitucion | P27: 0.26388889 | Q27: 0.28333333 | R27: 0.26875 | V27: - | W27: SE VISUALIZA POR CAMARA CONSTITUCION 23 UNA INCIDENCIA EN EL LUGAR. SE AVISO A COMANDO. ARRIBA PERSONAL POLICIAL. 901C INF SE REALIZO CONSULTA CON EL JUZGADO NCC NRO 58 AC DR GRUÑAR SECRETARIA NRO 64 AC DR JUAN ZIELLI QUIEN DISPUSO DETENCION DE LA FEMENINO QUIEN POSEIA UN PEDIDO VIGENTE, TRASLADO A CV1C.- | X27: 0 | Y27: 1 | Z27: 0 | AA27: 1C | AB27: U | AC27: MONITOREO | AE27: 1 DETENIDO | AF27: FINALIZA CON IMPUTADO/S | AL27: =VLOOKUP(G27,Hoja2!P:Q,2,0) -> 40097155 | AM27: =IF(OR(Y27>0,X27>0),"IMPUTADO","NADA") -> IMPUTADO | AN27: =IF(AND(AM27="IMPUTADO",ISBLANK(M27)),"FALTO","NO") -> NO
A28: 45992 | B28: =IF(AND(VALUE(P28)>=VALUE("06:00"),VALUE(P28)<=VALUE("17:59")),"06 A 18","18 A 06") -> 06 A 18 | C28: =IF(AND(VALUE(P28)>=VALUE("00:00"),VALUE(P28)<=VALUE("01:59")),"00:00 a 02:00",IF(AND(VALUE(P28)>=VALUE("02:00"),VALUE(P28)<=VALUE("03:59")),"02:00 a 04:00",IF(AND(VALUE(P28)>=VALUE("04:00"),VALUE(P28)<=VALUE("05:59")),"04:00 a 06:00",IF(AND(VALUE(P28)>=VALUE("06:00"),VALUE(P28)<=VALUE("07:59")),"06:00 a 08:00",IF(AND(VALUE(P28)>=VALUE("08:00"),VALUE(P28)<=VALUE("09:59")),"08:00 a 10:00",IF(AND(VALUE(P28)>=VALUE("10:00"),VALUE(P28)<=VALUE("11:59")),"10:00 a 12:00",IF(AND(VALUE(P28)>=VALUE("12:00"),VALUE(P28)<=VALUE("13:59")),"12:00 a 14:00",IF(AND(VALUE(P28)>=VALUE("14:00"),VALUE(P28)<=VALUE("15:59")),"14:00 a 16:00",IF(AND(VALUE(P28)>=VALUE("16:00"),VALUE(P28)<=VALUE("17:59")),"16:00 a 18:00",IF(AND(VALUE(P28)>=VALUE("18:00"),VALUE(P28)<=VALUE("19:59")),"18:00 a 20:00",IF(AND(VALUE(P28)>=VALUE("20:00"),VALUE(P28)<=VALUE("21:59")),"20:00 a 22:00",IF(AND(VALUE(P28)>=VALUE("22:00"),VALUE(P28)<=VALUE("23:59")),"22:00 a 00:00","no corresponde")))))))))))) -> 06:00 a 08:00 | D28: MARTINEZ. R | E28: MEZA, GASTON | F28: 1 | G28: KRAKOVSKY, FLORENCIA | H28: 918510 | I28: 46738334 | J28: CMU 9 DE JULIO | K28: COLABORACION | L28: CHOQUE | N28: SAN NICOLAS 03 | O28: San Nicolas | P28: 0.28125 | Q28: 0.30208333 | R28: 0.28125 | V28: - | W28: SE TOMA CONOCIMIENTO MEDIANTE CARTA SAE HT V/P SOLCITA SAME PARA MASCULINO ATROPELLADO . SE POSEE CAMARA SAN NICOLAS 03 SE VISUALIZA A UN MASCULINO TENDIDO EN EL SUELO SIENDO ASISTIDO POR PERSONALN POLICIAL. SE AMPLIA LINEA DE TIEMPO POR CAMARA SAN NICOLAS 03 CAM 02_ SIENDO LAS 06:32 HS SE VISUALIZA A UN MASCULINO CRUZAR POR EL MEDION LA AVENIDA CON LOS VEHICULOS CIRCULANDO FUERA DE LA SENDA PEATONAL EN FORMA IMPRUDENTE MOMENTO EN EL CUAL ES ENVESTIDO POR UN VEHICULO PARTICULAR COLOR OSCURO. SE AMPLIA M 601 INF ENTREVISTA AL MASC EN SIT DE CALLE DAMNIFICADO QUIEN REF SE ENCONTRABA CRUZANDO LA CALLE DE MANERA IMPRUDENTE Y MASC LE HABRAI PISADO EL PIE EL MISMO AL ARRIBO DEL MOVIL SE HABRIA RETIRADO Y PARA CON LA PARTE DAMNIFICADDA QUIEN REF NO INSTA A LA ACCION PENAL ES ASISTIDA POR PERSONAL MEDICO MEDIANTE TELEMEDICINA A SU VEZ SE NEGO A LA ASISTENCIA EL MISMO SE RETIRA POR SUS PROPIOS MEDIOS EN BUENAS CONDICIONES, A SU VEZ SE EVACUA CONSULTA A LA UFLA ESTE A LA VOZ DEL DR DEBRACHI QUIEN INDICA SE DEJE CONSTANCIA EN EL PARTE | X28: 0 | Y28: 0 | Z28: 0 | AA28: 1D | AB28: U | AC28: CARTA | AF28: CARTA FINALIZADA | AL28: =VLOOKUP(G28,Hoja2!P:Q,2,0) -> 41290026 | AM28: =IF(OR(Y28>0,X28>0),"IMPUTADO","NADA") -> NADA | AN28: =IF(AND(AM28="IMPUTADO",ISBLANK(M28)),"FALTO","NO") -> NO
A29: 45992 | B29: =IF(AND(VALUE(P29)>=VALUE("06:00"),VALUE(P29)<=VALUE("17:59")),"06 A 18","18 A 06") -> 06 A 18 | C29: =IF(AND(VALUE(P29)>=VALUE("00:00"),VALUE(P29)<=VALUE("01:59")),"00:00 a 02:00",IF(AND(VALUE(P29)>=VALUE("02:00"),VALUE(P29)<=VALUE("03:59")),"02:00 a 04:00",IF(AND(VALUE(P29)>=VALUE("04:00"),VALUE(P29)<=VALUE("05:59")),"04:00 a 06:00",IF(AND(VALUE(P29)>=VALUE("06:00"),VALUE(P29)<=VALUE("07:59")),"06:00 a 08:00",IF(AND(VALUE(P29)>=VALUE("08:00"),VALUE(P29)<=VALUE("09:59")),"08:00 a 10:00",IF(AND(VALUE(P29)>=VALUE("10:00"),VALUE(P29)<=VALUE("11:59")),"10:00 a 12:00",IF(AND(VALUE(P29)>=VALUE("12:00"),VALUE(P29)<=VALUE("13:59")),"12:00 a 14:00",IF(AND(VALUE(P29)>=VALUE("14:00"),VALUE(P29)<=VALUE("15:59")),"14:00 a 16:00",IF(AND(VALUE(P29)>=VALUE("16:00"),VALUE(P29)<=VALUE("17:59")),"16:00 a 18:00",IF(AND(VALUE(P29)>=VALUE("18:00"),VALUE(P29)<=VALUE("19:59")),"18:00 a 20:00",IF(AND(VALUE(P29)>=VALUE("20:00"),VALUE(P29)<=VALUE("21:59")),"20:00 a 22:00",IF(AND(VALUE(P29)>=VALUE("22:00"),VALUE(P29)<=VALUE("23:59")),"22:00 a 00:00","no corresponde")))))))))))) -> 06:00 a 08:00 | D29: MARTINEZ. R | E29: ARREGUI, FERNANDO | F29: 1 | G29: CARRIZO RODRIGO | H29: 918285 | I29: 46738371 | J29: CHACARITA | K29: COLABORACION | L29: INCIDENCIA | N29: CABALLITO 04 | O29: Caballito | P29: 0.29861111 | Q29: 0.30972222 | R29: 0.29861111 | S29: - | T29: - | U29: - | V29: - | W29: SE TOMA CONOCIMIENTO MEDIANTE CARTA SAE FEMENINO REFIERE INCIDENCIA CON UN MASCULINO. AGUARDA JANA NAHIR. 4º A..- CMU INF, SE POSEE CAMARA CABALLITO11 SE VISUALIZA PERSONAL POLICIAL EN EL LUGAR.- 606 INF SE ENTRVISTA CON LA SEÑORA QUIEN LE BRIDA EL ACCESO - DA CON LA PROPIETARIA DEL 4A - RECORREN EL EDIFICIO PANAMA NORMAL NEGATIVO PERSONAS EXTRAÑAS | X29: 0 | Y29: 0 | Z29: 0 | AA29: 6A | AB29: U | AC29: CARTA | AF29: CARTA FINALIZADA | AL29: =VLOOKUP(G29,Hoja2!P:Q,2,0) -> 43444086 | AM29: =IF(OR(Y29>0,X29>0),"IMPUTADO","NADA") -> NADA | AN29: =IF(AND(AM29="IMPUTADO",ISBLANK(M29)),"FALTO","NO") -> NO
A30: 45992 | B30: =IF(AND(VALUE(P30)>=VALUE("06:00"),VALUE(P30)<=VALUE("17:59")),"06 A 18","18 A 06") -> 06 A 18 | C30: =IF(AND(VALUE(P30)>=VALUE("00:00"),VALUE(P30)<=VALUE("01:59")),"00:00 a 02:00",IF(AND(VALUE(P30)>=VALUE("02:00"),VALUE(P30)<=VALUE("03:59")),"02:00 a 04:00",IF(AND(VALUE(P30)>=VALUE("04:00"),VALUE(P30)<=VALUE("05:59")),"04:00 a 06:00",IF(AND(VALUE(P30)>=VALUE("06:00"),VALUE(P30)<=VALUE("07:59")),"06:00 a 08:00",IF(AND(VALUE(P30)>=VALUE("08:00"),VALUE(P30)<=VALUE("09:59")),"08:00 a 10:00",IF(AND(VALUE(P30)>=VALUE("10:00"),VALUE(P30)<=VALUE("11:59")),"10:00 a 12:00",IF(AND(VALUE(P30)>=VALUE("12:00"),VALUE(P30)<=VALUE("13:59")),"12:00 a 14:00",IF(AND(VALUE(P30)>=VALUE("14:00"),VALUE(P30)<=VALUE("15:59")),"14:00 a 16:00",IF(AND(VALUE(P30)>=VALUE("16:00"),VALUE(P30)<=VALUE("17:59")),"16:00 a 18:00",IF(AND(VALUE(P30)>=VALUE("18:00"),VALUE(P30)<=VALUE("19:59")),"18:00 a 20:00",IF(AND(VALUE(P30)>=VALUE("20:00"),VALUE(P30)<=VALUE("21:59")),"20:00 a 22:00",IF(AND(VALUE(P30)>=VALUE("22:00"),VALUE(P30)<=VALUE("23:59")),"22:00 a 00:00","no corresponde")))))))))))) -> 06:00 a 08:00 | D30: MARTINEZ. R | E30: ARREGUI, FERNANDO | F30: 1 | G30: CARDOZO, ROMINA | H30: 918164 | I30: 46738521 | J30: CHACARITA | K30: COLABORACION | L30: CHOQUE | M30: LESIONES | N30: SAAVEDRA 18 CAM02 | O30: Saavedra | P30: 0.32013889 | Q30: 0.38680556 | R30: 0.32013889 | S30: 0.32430556 | T30: - | U30: - | V30: - | W30: SE TOMA CONOCIMIENTO MEDIANTE CARTA SAE HT SOLICITA MOV POR UN CHOQUE,EL VEHICULO SE QUEDO SIN FRENOS Y CHOCO CONTRA EL METROBUS.- CMU INFORMA QUE SE POSEE CAMARA SAAVEDRA 18 AL MOMENTO SE VISUALIZA A PERSONAL POLICIAL Y A UNA CAMIONETA BLANCA TIPO PARNET ENCIMADA AL METROBUS.- CMU INFORMA QUE SE VISUALIZA EL ARRIBO DE PERSONAL DE SAME.- 613B IND QUE SE HIZO CONSULTA CON LA UFLA NORTE AC DRGALVAIRE SEC UNICA DR DIAZ ACT POR AV DE ILICITO,SE TOMO CONTACTO PARA SOLICITAR LA GRUA,SE SECUESTRA LA CUBIERTA QUE PROVOCA EL ACCIDENTE,ESTA UNIDAD TRALADABA A 3 PERSONAS DE DISCAPACIDAD AL COLECIO SITO EN COLEGIALES,AL MISMO LE REVENTO LA RUEDA DELANTERA DE LADO IZQUIERA QUE PRODUCE LA PERDIDA DE CONTROL DEL VEHICULO ,TODOS ILESOS,LA MADRE DE LA MENOR VALENTIA ARRIBO,CON RESPECTO A LAS OTRAS PERSONAS LOS FAMILIARES ESTAN DESPLAZAMIENTO.-613B IND QUE LAS PERSONAS INVOLUCRADAS SON MAYORES DE EDAD,ARRIBO LA MADRE DE ECHAZU VALENTINA QUIEN APORTO LOS DATOS,RESPECTO A LOS OTROS PERSONAS INVOLUCRADAS ARRIBO LA 2DA UNIDAD DE TRASLADO APORTANDO LOS DATOS DE TODAS LAS PERSONAS INVOLUCRADAS.-613B IND QUE LA SRA MALENA SE RETIRA DEL LUGAR CON SU MADRE,LA SRA VALENTIA Y ARIEL FUERON TRASLADADAS POR LA 2DA UNIDAD DE TRASLADO AL COLEGIO,ESTO LO DISP EL MAGISTRADO QUE EL MISMO DISPUSO QUE DE SER NECESARIO FUERAN TRASLADOS POR UNIDADES DE TRASLADO DISPONIBLES O LOS FAMILIARES,NO SE TIENE NOMBRE DEL COLEGIO,ARRIBO GRUA PARA RETIRAR EL VEHICULO,CONTINUA CORTADA PARROISIEN Y CABILDO HASTA LA REMOCION DEL VEHICULO.- | X30: 0 | Y30: 1 | Z30: 0 | AA30: 13B | AB30: U | AC30: CARTA | AF30: COLABORACION CON IMPUTADO/S | AL30: =VLOOKUP(G30,Hoja2!P:Q,2,0) -> 32445282 | AM30: =IF(OR(Y30>0,X30>0),"IMPUTADO","NADA") -> IMPUTADO | AN30: =IF(AND(AM30="IMPUTADO",ISBLANK(M30)),"FALTO","NO") -> NO
A31: 45992 | B31: =IF(AND(VALUE(P31)>=VALUE("06:00"),VALUE(P31)<=VALUE("17:59")),"06 A 18","18 A 06") -> 06 A 18 | C31: =IF(AND(VALUE(P31)>=VALUE("00:00"),VALUE(P31)<=VALUE("01:59")),"00:00 a 02:00",IF(AND(VALUE(P31)>=VALUE("02:00"),VALUE(P31)<=VALUE("03:59")),"02:00 a 04:00",IF(AND(VALUE(P31)>=VALUE("04:00"),VALUE(P31)<=VALUE("05:59")),"04:00 a 06:00",IF(AND(VALUE(P31)>=VALUE("06:00"),VALUE(P31)<=VALUE("07:59")),"06:00 a 08:00",IF(AND(VALUE(P31)>=VALUE("08:00"),VALUE(P31)<=VALUE("09:59")),"08:00 a 10:00",IF(AND(VALUE(P31)>=VALUE("10:00"),VALUE(P31)<=VALUE("11:59")),"10:00 a 12:00",IF(AND(VALUE(P31)>=VALUE("12:00"),VALUE(P31)<=VALUE("13:59")),"12:00 a 14:00",IF(AND(VALUE(P31)>=VALUE("14:00"),VALUE(P31)<=VALUE("15:59")),"14:00 a 16:00",IF(AND(VALUE(P31)>=VALUE("16:00"),VALUE(P31)<=VALUE("17:59")),"16:00 a 18:00",IF(AND(VALUE(P31)>=VALUE("18:00"),VALUE(P31)<=VALUE("19:59")),"18:00 a 20:00",IF(AND(VALUE(P31)>=VALUE("20:00"),VALUE(P31)<=VALUE("21:59")),"20:00 a 22:00",IF(AND(VALUE(P31)>=VALUE("22:00"),VALUE(P31)<=VALUE("23:59")),"22:00 a 00:00","no corresponde")))))))))))) -> 06:00 a 08:00 | D31: MARTINEZ. R | E31: GAUNA, MICAELA | F31: 1 | G31: CARRERA, DEBORA ALEJANDRA | H31: 926370 | I31: 46738522 | J31: PUERTO MADERO | K31: PERSONA DESCOMPUESTA | N31: PUERTO MADERO49 | O31: Puerto Madero | P31: 0.30277778 | Q31: 0.34305556 | R31: 0.31875 | V31: - | W31: SE VISUALIZA POR CAMARA PUERTO MADERO49 PERSONA CAIDA DE SU PROPIA ALTURA, 901E DEJA S/E SAME DEBIDO A QUE LA FEMENINA SE NIEGA A LA ASISTENCIA.- | X31: 0 | Y31: 0 | Z31: 0 | AA31: 1E | AB31: U | AC31: MONITOREO | AF31: CARTA FINALIZADA | AL31: =VLOOKUP(G31,Hoja2!P:Q,2,0) -> 36552867 | AM31: =IF(OR(Y31>0,X31>0),"IMPUTADO","NADA") -> NADA | AN31: =IF(AND(AM31="IMPUTADO",ISBLANK(M31)),"FALTO","NO") -> NO
A32: 45992 | B32: =IF(AND(VALUE(P32)>=VALUE("06:00"),VALUE(P32)<=VALUE("17:59")),"06 A 18","18 A 06") -> 06 A 18 | C32: =IF(AND(VALUE(P32)>=VALUE("00:00"),VALUE(P32)<=VALUE("01:59")),"00:00 a 02:00",IF(AND(VALUE(P32)>=VALUE("02:00"),VALUE(P32)<=VALUE("03:59")),"02:00 a 04:00",IF(AND(VALUE(P32)>=VALUE("04:00"),VALUE(P32)<=VALUE("05:59")),"04:00 a 06:00",IF(AND(VALUE(P32)>=VALUE("06:00"),VALUE(P32)<=VALUE("07:59")),"06:00 a 08:00",IF(AND(VALUE(P32)>=VALUE("08:00"),VALUE(P32)<=VALUE("09:59")),"08:00 a 10:00",IF(AND(VALUE(P32)>=VALUE("10:00"),VALUE(P32)<=VALUE("11:59")),"10:00 a 12:00",IF(AND(VALUE(P32)>=VALUE("12:00"),VALUE(P32)<=VALUE("13:59")),"12:00 a 14:00",IF(AND(VALUE(P32)>=VALUE("14:00"),VALUE(P32)<=VALUE("15:59")),"14:00 a 16:00",IF(AND(VALUE(P32)>=VALUE("16:00"),VALUE(P32)<=VALUE("17:59")),"16:00 a 18:00",IF(AND(VALUE(P32)>=VALUE("18:00"),VALUE(P32)<=VALUE("19:59")),"18:00 a 20:00",IF(AND(VALUE(P32)>=VALUE("20:00"),VALUE(P32)<=VALUE("21:59")),"20:00 a 22:00",IF(AND(VALUE(P32)>=VALUE("22:00"),VALUE(P32)<=VALUE("23:59")),"22:00 a 00:00","no corresponde")))))))))))) -> 06:00 a 08:00 | D32: MARTINEZ. R | E32: PEREZ, RAMON | F32: 1 | G32: RIBEIRO GUADALUPE | H32: 918295 | I32: 46738562 | J32: CHACARITA | K32: IDENTIFICACION DE PERSONAS | N32: CABALLITO 11 | O32: Caballito | P32: 0.325 | Q32: 0.34027778 | R32: 0.32638889 | S32: - | T32: - | U32: - | V32: - | W32: SE TOMA CONOCIMIENTO MEDIANTE CARTA SAE SE MANTIENE AL DENUNCIANTE EN LINEA A LOS FINES DE APORTAR MAYORES DATOS DEL HECHO. NO ASOCIAR ESTA CARTA HASTA FINALIZAR LA COMUNICACION CON EL LLAMANTE.- CMU AMPLIA AL MOMENTRO NO SE LOGRA VISUALIZAR, SE VISUALIZA UN FEMENINO INGRESANDO Y EGRESANDO EN REITERADAS OPORTUNIDADES EN LO QUE SERIA LA FINCA.- CMU AMPLIA SE VISUALIZA EL ARRIBO DE MOVIL POLICIAL EN EL LUGAR.- CMU AMPLIA SE VISUALIZO PREVIO AL ARRIBO DE PERSONAL POLICIAL EL FEMENINO INGRESAR AL INTERIOR DEL GARAGE NO VOLVIENDO A EGRESAR DEL LUGAR.- | X32: 0 | Y32: 0 | Z32: 0 | AA32: 6A | AB32: U | AC32: CARTA | AF32: CARTA FINALIZADA | AL32: =VLOOKUP(G32,Hoja2!P:Q,2,0) -> 32874 | AM32: =IF(OR(Y32>0,X32>0),"IMPUTADO","NADA") -> NADA | AN32: =IF(AND(AM32="IMPUTADO",ISBLANK(M32)),"FALTO","NO") -> NO
A33: 45992 | B33: =IF(AND(VALUE(P33)>=VALUE("06:00"),VALUE(P33)<=VALUE("17:59")),"06 A 18","18 A 06") -> 06 A 18 | C33: =IF(AND(VALUE(P33)>=VALUE("00:00"),VALUE(P33)<=VALUE("01:59")),"00:00 a 02:00",IF(AND(VALUE(P33)>=VALUE("02:00"),VALUE(P33)<=VALUE("03:59")),"02:00 a 04:00",IF(AND(VALUE(P33)>=VALUE("04:00"),VALUE(P33)<=VALUE("05:59")),"04:00 a 06:00",IF(AND(VALUE(P33)>=VALUE("06:00"),VALUE(P33)<=VALUE("07:59")),"06:00 a 08:00",IF(AND(VALUE(P33)>=VALUE("08:00"),VALUE(P33)<=VALUE("09:59")),"08:00 a 10:00",IF(AND(VALUE(P33)>=VALUE("10:00"),VALUE(P33)<=VALUE("11:59")),"10:00 a 12:00",IF(AND(VALUE(P33)>=VALUE("12:00"),VALUE(P33)<=VALUE("13:59")),"12:00 a 14:00",IF(AND(VALUE(P33)>=VALUE("14:00"),VALUE(P33)<=VALUE("15:59")),"14:00 a 16:00",IF(AND(VALUE(P33)>=VALUE("16:00"),VALUE(P33)<=VALUE("17:59")),"16:00 a 18:00",IF(AND(VALUE(P33)>=VALUE("18:00"),VALUE(P33)<=VALUE("19:59")),"18:00 a 20:00",IF(AND(VALUE(P33)>=VALUE("20:00"),VALUE(P33)<=VALUE("21:59")),"20:00 a 22:00",IF(AND(VALUE(P33)>=VALUE("22:00"),VALUE(P33)<=VALUE("23:59")),"22:00 a 00:00","no corresponde")))))))))))) -> 06:00 a 08:00 | D33: MARTINEZ. R | E33: MEZA, GASTON | F33: 1 | G33: GOMEZ, VALERIA SOLEDAD | H33: 918544 | I33: 46738585 | J33: CMU 9 DE JULIO | K33: APARENTE COMERCIALIZACION ESTUPEFACIENTES | N33: CONSTITUCION 32 | O33: Constitucion | P33: 0.32569444 | Q33: 0.3375 | R33: 0.33125 | V33: - | W33: SE VISUALIZA POR CAMARA CONSTITUCION 32 A UN FEMENINO REALIZANDO APARENTE PASAMANOS. SE DA AVISO A COMANDO. SE AMPLIA 701C INF SE IDENTIFICO A DOS MASCULINOS CON LAS DESCRIPCIONES APORTADAS POR MONITOREO, LAS MISMA CORRESPONDEN Y NO POSEEN IMPEDIMENTOS,NO POSEE ELEMENTOS CONSTITUTIVOS DE DELITO.- | X33: 0 | Y33: 0 | Z33: 0 | AA33: 1C | AB33: U | AC33: MONITOREO | AF33: CARTA FINALIZADA | AL33: =VLOOKUP(G33,Hoja2!P:Q,2,0) -> 12149 | AM33: =IF(OR(Y33>0,X33>0),"IMPUTADO","NADA") -> NADA | AN33: =IF(AND(AM33="IMPUTADO",ISBLANK(M33)),"FALTO","NO") -> NO
A34: 45992 | B34: =IF(AND(VALUE(P34)>=VALUE("06:00"),VALUE(P34)<=VALUE("17:59")),"06 A 18","18 A 06") -> 06 A 18 | C34: =IF(AND(VALUE(P34)>=VALUE("00:00"),VALUE(P34)<=VALUE("01:59")),"00:00 a 02:00",IF(AND(VALUE(P34)>=VALUE("02:00"),VALUE(P34)<=VALUE("03:59")),"02:00 a 04:00",IF(AND(VALUE(P34)>=VALUE("04:00"),VALUE(P34)<=VALUE("05:59")),"04:00 a 06:00",IF(AND(VALUE(P34)>=VALUE("06:00"),VALUE(P34)<=VALUE("07:59")),"06:00 a 08:00",IF(AND(VALUE(P34)>=VALUE("08:00"),VALUE(P34)<=VALUE("09:59")),"08:00 a 10:00",IF(AND(VALUE(P34)>=VALUE("10:00"),VALUE(P34)<=VALUE("11:59")),"10:00 a 12:00",IF(AND(VALUE(P34)>=VALUE("12:00"),VALUE(P34)<=VALUE("13:59")),"12:00 a 14:00",IF(AND(VALUE(P34)>=VALUE("14:00"),VALUE(P34)<=VALUE("15:59")),"14:00 a 16:00",IF(AND(VALUE(P34)>=VALUE("16:00"),VALUE(P34)<=VALUE("17:59")),"16:00 a 18:00",IF(AND(VALUE(P34)>=VALUE("18:00"),VALUE(P34)<=VALUE("19:59")),"18:00 a 20:00",IF(AND(VALUE(P34)>=VALUE("20:00"),VALUE(P34)<=VALUE("21:59")),"20:00 a 22:00",IF(AND(VALUE(P34)>=VALUE("22:00"),VALUE(P34)<=VALUE("23:59")),"22:00 a 00:00","no corresponde")))))))))))) -> 08:00 a 10:00 | D34: MARTINEZ. R | E34: MEZA, GASTON | F34: 1 | G34: KRAKOVSKY, FLORENCIA | H34: 918457 | I34: 46738674 | J34: CMU 9 DE JULIO | K34: APARENTE COMERCIALIZACION ESTUPEFACIENTES | N34: SAN TELMO 21 | O34: San Telmo | P34: 0.33888889 | Q34: 0.35625 | R34: 0.34166667 | V34: - | W34: SE VISUALIZA POR CAMARA SAN TELMO 21 A UN MASCULINO REALIZANDO PASAMANOS. SE DA AVISO A COMANDO. ARRIBA PERSONAL POLICIAL DANDO EL MASCULINO EN MENCION. SE AMPLIA MOVIL 1001 INF SE ENCUENTRA CON LOS DOS MASCULINOS SE LOS REQUIZO NO POSEEN ELEMENTOS CONSTITUTIVO DE ILICITO. SE RETIRAN DEL LUGAR SIN NOVEDAD. | X34: 0 | Y34: 0 | Z34: 0 | AA34: 1F | AB34: U | AC34: MONITOREO | AF34: CARTA FINALIZADA | AL34: =VLOOKUP(G34,Hoja2!P:Q,2,0) -> 41290026 | AM34: =IF(OR(Y34>0,X34>0),"IMPUTADO","NADA") -> NADA | AN34: =IF(AND(AM34="IMPUTADO",ISBLANK(M34)),"FALTO","NO") -> NO
A35: 45992 | B35: =IF(AND(VALUE(P35)>=VALUE("06:00"),VALUE(P35)<=VALUE("17:59")),"06 A 18","18 A 06") -> 06 A 18 | C35: =IF(AND(VALUE(P35)>=VALUE("00:00"),VALUE(P35)<=VALUE("01:59")),"00:00 a 02:00",IF(AND(VALUE(P35)>=VALUE("02:00"),VALUE(P35)<=VALUE("03:59")),"02:00 a 04:00",IF(AND(VALUE(P35)>=VALUE("04:00"),VALUE(P35)<=VALUE("05:59")),"04:00 a 06:00",IF(AND(VALUE(P35)>=VALUE("06:00"),VALUE(P35)<=VALUE("07:59")),"06:00 a 08:00",IF(AND(VALUE(P35)>=VALUE("08:00"),VALUE(P35)<=VALUE("09:59")),"08:00 a 10:00",IF(AND(VALUE(P35)>=VALUE("10:00"),VALUE(P35)<=VALUE("11:59")),"10:00 a 12:00",IF(AND(VALUE(P35)>=VALUE("12:00"),VALUE(P35)<=VALUE("13:59")),"12:00 a 14:00",IF(AND(VALUE(P35)>=VALUE("14:00"),VALUE(P35)<=VALUE("15:59")),"14:00 a 16:00",IF(AND(VALUE(P35)>=VALUE("16:00"),VALUE(P35)<=VALUE("17:59")),"16:00 a 18:00",IF(AND(VALUE(P35)>=VALUE("18:00"),VALUE(P35)<=VALUE("19:59")),"18:00 a 20:00",IF(AND(VALUE(P35)>=VALUE("20:00"),VALUE(P35)<=VALUE("21:59")),"20:00 a 22:00",IF(AND(VALUE(P35)>=VALUE("22:00"),VALUE(P35)<=VALUE("23:59")),"22:00 a 00:00","no corresponde")))))))))))) -> 08:00 a 10:00 | D35: MARTINEZ. R | E35: MEZA, GASTON | F35: 1 | G35: GOMEZ, VALERIA SOLEDAD | I35: 46738904 | J35: CMU 9 DE JULIO | K35: APARENTE COMERCIALIZACION ESTUPEFACIENTES | M35: LEY 23.737 | N35: CONSTITUCION O 122 | O35: Constitucion | P35: 0.3625 | Q35: 0.44236111 | R35: 0.36736111 | S35: 0.43611111 | V35: - | W35: SE VISUALIZA POR CAMARA CONSTITUCION O122 A UN FEMENINO EN APARENTEMENTE MANIPULACION Y COMERCIALIZACION DE ESTUPEFACIENTES. SE DA AVISO A COMANDO. SE AMPLIA HT INF SE RECORRIO LA ZONA CON RESULTADO NEGATIVO, PRESENCIA NOTORIA, PMA EXTERNO NORMAL SE RETIRAN SIN NOVEDAD. | X35: 0 | Y35: 1 | Z35: 0 | AA35: 1C | AB35: U | AC35: MONITOREO | AE35: 1 DETENIDO | AF35: FINALIZA CON IMPUTADO/S | AL35: =VLOOKUP(G35,Hoja2!P:Q,2,0) -> 12149 | AM35: =IF(OR(Y35>0,X35>0),"IMPUTADO","NADA") -> IMPUTADO | AN35: =IF(AND(AM35="IMPUTADO",ISBLANK(M35)),"FALTO","NO") -> NO
A36: 45992 | B36: =IF(AND(VALUE(P36)>=VALUE("06:00"),VALUE(P36)<=VALUE("17:59")),"06 A 18","18 A 06") -> 06 A 18 | C36: =IF(AND(VALUE(P36)>=VALUE("00:00"),VALUE(P36)<=VALUE("01:59")),"00:00 a 02:00",IF(AND(VALUE(P36)>=VALUE("02:00"),VALUE(P36)<=VALUE("03:59")),"02:00 a 04:00",IF(AND(VALUE(P36)>=VALUE("04:00"),VALUE(P36)<=VALUE("05:59")),"04:00 a 06:00",IF(AND(VALUE(P36)>=VALUE("06:00"),VALUE(P36)<=VALUE("07:59")),"06:00 a 08:00",IF(AND(VALUE(P36)>=VALUE("08:00"),VALUE(P36)<=VALUE("09:59")),"08:00 a 10:00",IF(AND(VALUE(P36)>=VALUE("10:00"),VALUE(P36)<=VALUE("11:59")),"10:00 a 12:00",IF(AND(VALUE(P36)>=VALUE("12:00"),VALUE(P36)<=VALUE("13:59")),"12:00 a 14:00",IF(AND(VALUE(P36)>=VALUE("14:00"),VALUE(P36)<=VALUE("15:59")),"14:00 a 16:00",IF(AND(VALUE(P36)>=VALUE("16:00"),VALUE(P36)<=VALUE("17:59")),"16:00 a 18:00",IF(AND(VALUE(P36)>=VALUE("18:00"),VALUE(P36)<=VALUE("19:59")),"18:00 a 20:00",IF(AND(VALUE(P36)>=VALUE("20:00"),VALUE(P36)<=VALUE("21:59")),"20:00 a 22:00",IF(AND(VALUE(P36)>=VALUE("22:00"),VALUE(P36)<=VALUE("23:59")),"22:00 a 00:00","no corresponde")))))))))))) -> 08:00 a 10:00 | D36: MARTINEZ. R | E36: GAUNA, MICAELA | F36: 1 | G36: DIAZ, MARIA BELEN | H36: 918292 | I36: 46738922 | J36: PUERTO MADERO | K36: ROBO/HURTO | N36: NUEVA POMPEYAO100 | O36: Nueva Pompeya | P36: 0.36458333 | Q36: 0.37638889 | R36: 0.37013889 | V36: - | W36: SE TOMA CONOCIMIENTO MEDIANTE CARTA SAE N°46738922. DENUNCIANTE REFIERE QUE HABRÍA DEJADO SU VEHÍCULO EN EL LUGAR Y LE HABRÍAN ROTO EL VIDRIO PARA ROBARLE. 08:49HS SE TOMA CÁMARA POMPEYA O100 EMPLAZADA EN PEPIRI898 Y ANCASTE. SE VISUALIZA A TRES MASCULINOS EN EL LUGAR CON EL VEHÍCULO VIOLENTADO. 08:53HS ARRIBA MÓVIL POLICIAL 08:57HS SE REALIZA LINEA DE TIEMPO MEDIANTE CÁMARA POMPEYAO100CAM03 SE LOGRA VISUALIZAR ALAS 04:08HS SE APROXIMA UN MASCULINO AL RODADO Y A LOS POCOS MINUTOS SE RETIRA DEL LUGAR. EL MASCULINO VISTE DE ZAPATILLAS NEGRAS PANTALONES NEGRAS CAMPERA AZUL GORRA NEGRA CON INSCRIPCIONES BLANCAS . SE LO VISUALIZA EN COMPAÑÍA DE UN SEGUNDO MASCULINO EL CUAL LLEVABA UNA RUEDA EN SU PODER. EL SEGUNDO MASCULINO VESTÍA CAMPERA NEGRA CON LINEAS BLANCAS Y ROJAS EN EL PECHO PANTALÓN NEGRO AMBOS SE RETIRAN POR PEPIRI HACIA ANCASTE. 09:02HS SE RETIRA PERSONAL POLICIAL DEJANDO ESTE EVENTO POR FINALIZADO . POSTERIORMENTE SE TOMA CONOCIMIENTO MEDIANTE AMPLIACIÓN MÓVIL INFORMA ARRIBADO AL LUGAR SE ENTREVISTA CON EL LLAMANTE EL CUAL REFIERE QUE AL SALIR DE SU DOMICILIO VISUALIZA QUE EL VIDRIO DEL LADO DEL ACOMPAÑANTE DE SU VEHÍCULO SE ENCUENTRA VIOLENTADO ASI MISMO CON FALTANTE DE UNA RUEDA DE AUXILIO Y EL INTERIOR REVUELTO POR CUAL ARRIBO DEL PERSONAL SE REALIZA CONSULTA CON FISCALÍA 61 A CARGO FERRANDO SECRETARIA ÚNICA A CARGO ALONZO QUIEN DISPUSO LABRAR ACTUACIONES POR ROBO NO SE REQUIEREN SERVICIO AL LUGAR DEBIDO A LAS MANIPULACIONES DE LOS ELEMENTOS. ESTE EVENTO FUE MONITOREADO POR DIAZ ANALIA DNI 24646968 CON LA COLABORACIÓN DE MOLINAS ANALIA | X36: 0 | Y36: 0 | Z36: 0 | AA36: 4A | AB36: U | AC36: CARTA | AF36: CARTA FINALIZADA | AL36: =VLOOKUP(G36,Hoja2!P:Q,2,0) -> 35166947 | AM36: =IF(OR(Y36>0,X36>0),"IMPUTADO","NADA") -> NADA | AN36: =IF(AND(AM36="IMPUTADO",ISBLANK(M36)),"FALTO","NO") -> NO
A37: 45992 | B37: =IF(AND(VALUE(P37)>=VALUE("06:00"),VALUE(P37)<=VALUE("17:59")),"06 A 18","18 A 06") -> 06 A 18 | C37: =IF(AND(VALUE(P37)>=VALUE("00:00"),VALUE(P37)<=VALUE("01:59")),"00:00 a 02:00",IF(AND(VALUE(P37)>=VALUE("02:00"),VALUE(P37)<=VALUE("03:59")),"02:00 a 04:00",IF(AND(VALUE(P37)>=VALUE("04:00"),VALUE(P37)<=VALUE("05:59")),"04:00 a 06:00",IF(AND(VALUE(P37)>=VALUE("06:00"),VALUE(P37)<=VALUE("07:59")),"06:00 a 08:00",IF(AND(VALUE(P37)>=VALUE("08:00"),VALUE(P37)<=VALUE("09:59")),"08:00 a 10:00",IF(AND(VALUE(P37)>=VALUE("10:00"),VALUE(P37)<=VALUE("11:59")),"10:00 a 12:00",IF(AND(VALUE(P37)>=VALUE("12:00"),VALUE(P37)<=VALUE("13:59")),"12:00 a 14:00",IF(AND(VALUE(P37)>=VALUE("14:00"),VALUE(P37)<=VALUE("15:59")),"14:00 a 16:00",IF(AND(VALUE(P37)>=VALUE("16:00"),VALUE(P37)<=VALUE("17:59")),"16:00 a 18:00",IF(AND(VALUE(P37)>=VALUE("18:00"),VALUE(P37)<=VALUE("19:59")),"18:00 a 20:00",IF(AND(VALUE(P37)>=VALUE("20:00"),VALUE(P37)<=VALUE("21:59")),"20:00 a 22:00",IF(AND(VALUE(P37)>=VALUE("22:00"),VALUE(P37)<=VALUE("23:59")),"22:00 a 00:00","no corresponde")))))))))))) -> 08:00 a 10:00 | D37: MARTINEZ. R | E37: MOLINA, JOSE MANUEL | F37: 1 | G37: BENDITTI, JULIETA | H37: 918274 | I37: 46738951 | J37: CHACARITA | K37: COLABORACION | L37: IDENT. DE PERSONAS | N37: PALERMO O201 | O37: Palermo | P37: 0.375 | Q37: 0.42916667 | R37: 0.375 | S37: - | T37: - | U37: 0.40833333 | V37: - | W37: SE TOMA CONOCIMIENTO MEDIANTE CARTA SAE MOVIL 214 SOLICITA PERSONAL DE BRIGADA DE EXPLOSIVOS POR UNA VALIJA EN LA OCHAVA // POC 1134804517.-CMU INF, NO SE POSEE CAMARA EN EL LUGAR.-CMU SE VERIFICA CAMARA PALERMOO201 SE VISUALIZA PERSONAL POLICIAL TRABAJANDO EN EL LUGAR.-214 C FINALIZO ESCUADRON ANTIBOMBAS SIN NOVEDAD DONDE INDICA QUE SE TRATO DE UNA VALIJA SIN CONTENIDO EN SU INTERIOR.-CMU AMPLIA QUE SE VISUALIZA EL RETIRO DE PERSONAL POLICIAL DEL QTH.- 214C ARRIBO MOVIL INT 9020 AC INSPECTOR LP 2133 MARIANO MONROU // MOVIL INT 2277 AC INSPECTOR LP 15617 MOREL DE ESCUADRON ANTIBOMBAS . SE LABRAN ACTUACIONES POR INTIMIDACION PUBLICA INTERVIENE JUZGADO CRIM CORR N 2 DR RAMOS SEC 03 | X37: 0 | Y37: 0 | Z37: 0 | AA37: 14C | AB37: U | AC37: CARTA | AF37: CARTA FINALIZADA | AL37: =VLOOKUP(G37,Hoja2!P:Q,2,0) -> 38919576 | AM37: =IF(OR(Y37>0,X37>0),"IMPUTADO","NADA") -> NADA | AN37: =IF(AND(AM37="IMPUTADO",ISBLANK(M37)),"FALTO","NO") -> NO
A38: 45992 | B38: =IF(AND(VALUE(P38)>=VALUE("06:00"),VALUE(P38)<=VALUE("17:59")),"06 A 18","18 A 06") -> 06 A 18 | C38: =IF(AND(VALUE(P38)>=VALUE("00:00"),VALUE(P38)<=VALUE("01:59")),"00:00 a 02:00",IF(AND(VALUE(P38)>=VALUE("02:00"),VALUE(P38)<=VALUE("03:59")),"02:00 a 04:00",IF(AND(VALUE(P38)>=VALUE("04:00"),VALUE(P38)<=VALUE("05:59")),"04:00 a 06:00",IF(AND(VALUE(P38)>=VALUE("06:00"),VALUE(P38)<=VALUE("07:59")),"06:00 a 08:00",IF(AND(VALUE(P38)>=VALUE("08:00"),VALUE(P38)<=VALUE("09:59")),"08:00 a 10:00",IF(AND(VALUE(P38)>=VALUE("10:00"),VALUE(P38)<=VALUE("11:59")),"10:00 a 12:00",IF(AND(VALUE(P38)>=VALUE("12:00"),VALUE(P38)<=VALUE("13:59")),"12:00 a 14:00",IF(AND(VALUE(P38)>=VALUE("14:00"),VALUE(P38)<=VALUE("15:59")),"14:00 a 16:00",IF(AND(VALUE(P38)>=VALUE("16:00"),VALUE(P38)<=VALUE("17:59")),"16:00 a 18:00",IF(AND(VALUE(P38)>=VALUE("18:00"),VALUE(P38)<=VALUE("19:59")),"18:00 a 20:00",IF(AND(VALUE(P38)>=VALUE("20:00"),VALUE(P38)<=VALUE("21:59")),"20:00 a 22:00",IF(AND(VALUE(P38)>=VALUE("22:00"),VALUE(P38)<=VALUE("23:59")),"22:00 a 00:00","no corresponde")))))))))))) -> 08:00 a 10:00 | D38: MARTINEZ. R | E38: ARREGUI, FERNANDO | F38: 1 | G38: RIBEIRO GUADALUPE | H38: 918323 | I38: 46739002 | J38: CHACARITA | K38: COLABORACION | L38: CHOQUE | N38: V. SOLDATI O117 | O38: Villa Soldati | P38: 0.38194444 | Q38: 0.51388889 | R38: 0.38402778 | S38: 0.38472222 | T38: - | U38: - | V38: - | W38: SE TOMA CONOCIMIENTO MEDIANTE CARTA SAE AUTOVIAS SOLICITA APOYO POR CHOQUE CON HERIDOS.-CMU INFORMA QUE MEDIANTE CAMARA VILLA SOLDATIOI117 SE VISUALIZA VEHICULOS DETENIDOS EN EL LUGAR.-CMU AMPLIA: MEDIOS PERIODISTICOS EN EL LUGAR.-CMU AMPLIA: VEHICULO VOLKSWAGEN DOMINIO COLOCADO BIX961 CON DAÑOS VISISBLES. ASIMISMO EN EL LUGAR UN CAMION DE TRANSPORTE DE PRODUCTOS ALIMENTICIOS Y VEHICULO COLOR GRIS.-CMU AMPLIA LINEA DE TIEMPO REALIZADA POR CAMARA FIJA VILLA SOLDATIO117CAM03: SIENDO LAS 08:48HS. SE VISUALIZA A UN VEHICULO SIMIL SURAN COLOR GRIS EL CUAL CIRCULA A GRAN VELOCIDAD POR AU CAMPORA Y EMBISTE AL VEHICULO VOLKSWAGEN COLOR BLANCO EN SU PARTE TRASERA, EL CUAL AL MOMENTO SE ENCONTRABA CIRCULANDO POR EL CARRIL DERECHO A VELOCIDAD REDUCIDA APARENTEMENTE DEBIDO AL TRANSITO. PRODUCTO DEL CHOQUE EL VEHICULO SIMIL SURAN CAMBIA DE CARRIL, QUEDANDO DEL LADO IZQUIERDO.-CMU AMPLIA: ARRIBO PERSONAL POLICIAL-CMU AMPLIA: ARRIBO SAME AEREO.-CMU AMPLIA: SE RETIRA SAME AEREO.-SAME AEREO A/C DOC VIAJORI EUGENIA 176482 ASISITE Y TRASLADA AL SANTOJANNI CON DIAG POLITRAUMA // ULFA OESTE DOC GALVANO EN LA VOZ DEL DOC GUERRINI ACT POR SOLICITA VIALES CON ALCOTEST Y NARCOTEST.- SAME AEREO A/C DOC VIAJORI EUGENIA 176482 ASISITE Y TRASLADA AL SANTOJANNI CON DIAG POLITRAUMA // ULFA OESTE DOC GALVANO EN LA VOZ DEL DOC GUERRINI ACT POR SOLICITA VIALES CON ALCOTEST Y NARCOTEST.- SE SOLICITA LOS SERVICIOS DE ALCOTEST Y NARCOTEST PARA EL SR ADIMARI CONDUCTOR DE LA BMW X5 | X38: 0 | Y38: 0 | Z38: 1 | AA38: 7A | AB38: U | AC38: CARTA | AE38: 1 TRASLADO SAME | AF38: CARTA FINALIZADA | AL38: =VLOOKUP(G38,Hoja2!P:Q,2,0) -> 32874 | AM38: =IF(OR(Y38>0,X38>0),"IMPUTADO","NADA") -> NADA | AN38: =IF(AND(AM38="IMPUTADO",ISBLANK(M38)),"FALTO","NO") -> NO
A39: 45992 | B39: =IF(AND(VALUE(P39)>=VALUE("06:00"),VALUE(P39)<=VALUE("17:59")),"06 A 18","18 A 06") -> 06 A 18 | C39: =IF(AND(VALUE(P39)>=VALUE("00:00"),VALUE(P39)<=VALUE("01:59")),"00:00 a 02:00",IF(AND(VALUE(P39)>=VALUE("02:00"),VALUE(P39)<=VALUE("03:59")),"02:00 a 04:00",IF(AND(VALUE(P39)>=VALUE("04:00"),VALUE(P39)<=VALUE("05:59")),"04:00 a 06:00",IF(AND(VALUE(P39)>=VALUE("06:00"),VALUE(P39)<=VALUE("07:59")),"06:00 a 08:00",IF(AND(VALUE(P39)>=VALUE("08:00"),VALUE(P39)<=VALUE("09:59")),"08:00 a 10:00",IF(AND(VALUE(P39)>=VALUE("10:00"),VALUE(P39)<=VALUE("11:59")),"10:00 a 12:00",IF(AND(VALUE(P39)>=VALUE("12:00"),VALUE(P39)<=VALUE("13:59")),"12:00 a 14:00",IF(AND(VALUE(P39)>=VALUE("14:00"),VALUE(P39)<=VALUE("15:59")),"14:00 a 16:00",IF(AND(VALUE(P39)>=VALUE("16:00"),VALUE(P39)<=VALUE("17:59")),"16:00 a 18:00",IF(AND(VALUE(P39)>=VALUE("18:00"),VALUE(P39)<=VALUE("19:59")),"18:00 a 20:00",IF(AND(VALUE(P39)>=VALUE("20:00"),VALUE(P39)<=VALUE("21:59")),"20:00 a 22:00",IF(AND(VALUE(P39)>=VALUE("22:00"),VALUE(P39)<=VALUE("23:59")),"22:00 a 00:00","no corresponde")))))))))))) -> 08:00 a 10:00 | D39: MARTINEZ. R | E39: MEZA, GASTON | F39: 1 | G39: KRAKOVSKY, FLORENCIA | H39: 918528 | I39: 46739030 | J39: CMU 9 DE JULIO | K39: APARENTE COMERCIALIZACION ESTUPEFACIENTES | M39: LEY 23.737 | N39: CONSTITUCION 74 | O39: Constitucion | P39: 0.37777778 | Q39: 0.40902778 | R39: 0.38055556 | V39: - | W39: SE VISUALIZA POR CAMARA CONSTITUCION 74 A UN FEMENINO EN APARENTEMENTE MANIPULACION Y COMERCIALIZACION DE ESTUPEFACIENTES. SE DA AVISO A COMANDO. ARRIBA PERSONAL POLICIAL DANDO CON LAS PARTES. SE AMPLIA MOVIL 601 INF SE REALIZO CONSULTA FLAGRANCIA ESTE AC DR MARCELIRI ACT POR LA LEY 23737 ART 5 INSICISO C NOTOFICACION DE LOS ART 29 Y 30. | X39: 0 | Y39: 1 | Z39: 0 | AA39: 1C | AB39: U | AC39: MONITOREO | AE39: 1 IMPUTADO | AF39: FINALIZA CON IMPUTADO/S | AL39: =VLOOKUP(G39,Hoja2!P:Q,2,0) -> 41290026 | AM39: =IF(OR(Y39>0,X39>0),"IMPUTADO","NADA") -> IMPUTADO | AN39: =IF(AND(AM39="IMPUTADO",ISBLANK(M39)),"FALTO","NO") -> NO
A40: 45992 | B40: =IF(AND(VALUE(P40)>=VALUE("06:00"),VALUE(P40)<=VALUE("17:59")),"06 A 18","18 A 06") -> 06 A 18 | C40: =IF(AND(VALUE(P40)>=VALUE("00:00"),VALUE(P40)<=VALUE("01:59")),"00:00 a 02:00",IF(AND(VALUE(P40)>=VALUE("02:00"),VALUE(P40)<=VALUE("03:59")),"02:00 a 04:00",IF(AND(VALUE(P40)>=VALUE("04:00"),VALUE(P40)<=VALUE("05:59")),"04:00 a 06:00",IF(AND(VALUE(P40)>=VALUE("06:00"),VALUE(P40)<=VALUE("07:59")),"06:00 a 08:00",IF(AND(VALUE(P40)>=VALUE("08:00"),VALUE(P40)<=VALUE("09:59")),"08:00 a 10:00",IF(AND(VALUE(P40)>=VALUE("10:00"),VALUE(P40)<=VALUE("11:59")),"10:00 a 12:00",IF(AND(VALUE(P40)>=VALUE("12:00"),VALUE(P40)<=VALUE("13:59")),"12:00 a 14:00",IF(AND(VALUE(P40)>=VALUE("14:00"),VALUE(P40)<=VALUE("15:59")),"14:00 a 16:00",IF(AND(VALUE(P40)>=VALUE("16:00"),VALUE(P40)<=VALUE("17:59")),"16:00 a 18:00",IF(AND(VALUE(P40)>=VALUE("18:00"),VALUE(P40)<=VALUE("19:59")),"18:00 a 20:00",IF(AND(VALUE(P40)>=VALUE("20:00"),VALUE(P40)<=VALUE("21:59")),"20:00 a 22:00",IF(AND(VALUE(P40)>=VALUE("22:00"),VALUE(P40)<=VALUE("23:59")),"22:00 a 00:00","no corresponde")))))))))))) -> 08:00 a 10:00 | D40: MARTINEZ. R | E40: MEZA, GASTON | F40: 1 | G40: ROJAS MELANIE | H40: 918217 | I40: 46739126 | J40: CMU 9 DE JULIO | K40: MANIFESTACION | N40: SAN TELMO 28 | O40: San Telmo | P40: 0.39305556 | Q40: 0.40972222 | R40: 0.39305556 | V40: - | W40: SE TOMA CONOCIMIENTO MEDIANTE CARTA SAE EN EL LUGAR SE ESTA LLEVANDO A CAO ELECCION DE AUTORIDADES EN PRESENCIA DE UN JUEZ FEDERAL. SE POSEE CAMARA SAN TELMO 28 SE VISUALIZA APROXIMADAMENTE 50 PERSONAS EN EL LUGAR CON BOMBOS. SE AMPLIA 201 INF ES AFIRMATIVO SE ENCUENTRA MODULANDO POR METRO DOS POR ORDE DE SERVICIO 8240 | X40: 0 | Y40: 0 | Z40: 0 | AA40: 1F | AB40: U | AC40: CARTA | AF40: CARTA FINALIZADA | AL40: =VLOOKUP(G40,Hoja2!P:Q,2,0) -> 40097155 | AM40: =IF(OR(Y40>0,X40>0),"IMPUTADO","NADA") -> NADA | AN40: =IF(AND(AM40="IMPUTADO",ISBLANK(M40)),"FALTO","NO") -> NO
A41: 45992 | B41: =IF(AND(VALUE(P41)>=VALUE("06:00"),VALUE(P41)<=VALUE("17:59")),"06 A 18","18 A 06") -> 06 A 18 | C41: =IF(AND(VALUE(P41)>=VALUE("00:00"),VALUE(P41)<=VALUE("01:59")),"00:00 a 02:00",IF(AND(VALUE(P41)>=VALUE("02:00"),VALUE(P41)<=VALUE("03:59")),"02:00 a 04:00",IF(AND(VALUE(P41)>=VALUE("04:00"),VALUE(P41)<=VALUE("05:59")),"04:00 a 06:00",IF(AND(VALUE(P41)>=VALUE("06:00"),VALUE(P41)<=VALUE("07:59")),"06:00 a 08:00",IF(AND(VALUE(P41)>=VALUE("08:00"),VALUE(P41)<=VALUE("09:59")),"08:00 a 10:00",IF(AND(VALUE(P41)>=VALUE("10:00"),VALUE(P41)<=VALUE("11:59")),"10:00 a 12:00",IF(AND(VALUE(P41)>=VALUE("12:00"),VALUE(P41)<=VALUE("13:59")),"12:00 a 14:00",IF(AND(VALUE(P41)>=VALUE("14:00"),VALUE(P41)<=VALUE("15:59")),"14:00 a 16:00",IF(AND(VALUE(P41)>=VALUE("16:00"),VALUE(P41)<=VALUE("17:59")),"16:00 a 18:00",IF(AND(VALUE(P41)>=VALUE("18:00"),VALUE(P41)<=VALUE("19:59")),"18:00 a 20:00",IF(AND(VALUE(P41)>=VALUE("20:00"),VALUE(P41)<=VALUE("21:59")),"20:00 a 22:00",IF(AND(VALUE(P41)>=VALUE("22:00"),VALUE(P41)<=VALUE("23:59")),"22:00 a 00:00","no corresponde")))))))))))) -> 08:00 a 10:00 | D41: MARTINEZ. R | E41: ARREGUI, FERNANDO | F41: 1 | G41: KOSELSTEIN, SILVINA | H41: 918157 | I41: 46739135 | J41: CHACARITA | K41: COLABORACION | L41: INCIDENCIA | N41: BELGRANO 23 | O41: Belgrano | P41: 0.39791667 | Q41: 0.44444444 | R41: 0.39791667 | V41: - | W41: SIENDO LAS 9.33HS SE TOMA CONOCIMIENTO MEDIANTE CARTA SAE N°46739135 POR UN MASCULINO REALIZANDO EXHIBICIONES OBSCENAS SE TOMA MACARA BELGRANO23 EMPLAZADA EN ECHEVERRIA 1687 Y VIRREY VERTIZ VISUALIZANDO PERSONAL POLICIAL CON UN MASCULINO TORSO DESNUDO Y BERMUDAS 10.04HS SE RETIRA DEL LUGAR EL MASCULINO POR SUS PROPIOS MEDIOS SE AMPLIA MEDIANTE CARTA SAE HT INDICO QUE SE HIZO CONSULTA CON LA FISCALIA GENERAL A CARGO DRA GIMENEZ DISPUSO ACTUACIONES CONTRAVENXCION ART 139 POR EXHIBICIONES OBSCENAS SE RETIRA DEL LUGAR. | X41: 0 | Y41: 0 | Z41: 0 | AA41: 12A | AB41: U | AC41: CARTA | AD41: SISEP | AF41: CARTA FINALIZADA | AL41: =VLOOKUP(G41,Hoja2!P:Q,2,0) -> 24293262 | AM41: =IF(OR(Y41>0,X41>0),"IMPUTADO","NADA") -> NADA | AN41: =IF(AND(AM41="IMPUTADO",ISBLANK(M41)),"FALTO","NO") -> NO
A42: 45992 | B42: =IF(AND(VALUE(P42)>=VALUE("06:00"),VALUE(P42)<=VALUE("17:59")),"06 A 18","18 A 06") -> 06 A 18 | C42: =IF(AND(VALUE(P42)>=VALUE("00:00"),VALUE(P42)<=VALUE("01:59")),"00:00 a 02:00",IF(AND(VALUE(P42)>=VALUE("02:00"),VALUE(P42)<=VALUE("03:59")),"02:00 a 04:00",IF(AND(VALUE(P42)>=VALUE("04:00"),VALUE(P42)<=VALUE("05:59")),"04:00 a 06:00",IF(AND(VALUE(P42)>=VALUE("06:00"),VALUE(P42)<=VALUE("07:59")),"06:00 a 08:00",IF(AND(VALUE(P42)>=VALUE("08:00"),VALUE(P42)<=VALUE("09:59")),"08:00 a 10:00",IF(AND(VALUE(P42)>=VALUE("10:00"),VALUE(P42)<=VALUE("11:59")),"10:00 a 12:00",IF(AND(VALUE(P42)>=VALUE("12:00"),VALUE(P42)<=VALUE("13:59")),"12:00 a 14:00",IF(AND(VALUE(P42)>=VALUE("14:00"),VALUE(P42)<=VALUE("15:59")),"14:00 a 16:00",IF(AND(VALUE(P42)>=VALUE("16:00"),VALUE(P42)<=VALUE("17:59")),"16:00 a 18:00",IF(AND(VALUE(P42)>=VALUE("18:00"),VALUE(P42)<=VALUE("19:59")),"18:00 a 20:00",IF(AND(VALUE(P42)>=VALUE("20:00"),VALUE(P42)<=VALUE("21:59")),"20:00 a 22:00",IF(AND(VALUE(P42)>=VALUE("22:00"),VALUE(P42)<=VALUE("23:59")),"22:00 a 00:00","no corresponde")))))))))))) -> 08:00 a 10:00 | D42: MARTINEZ. R | E42: MEZA, GASTON | F42: 1 | G42: GOMEZ, VALERIA SOLEDAD | H42: 918198 | I42: 46739147 | J42: CMU 9 DE JULIO | K42: APARENTE COMERCIALIZACION ESTUPEFACIENTES | N42: CONSTITUCION O137 | O42: Constitucion | P42: 0.39027778 | Q42: 0.4125 | R42: 0.39027778 | V42: - | W42: SE VISUALIZA POR CAMARA CONSTITUCION O137 A UN FEMENINO EN APARENTEMENTE MANIPULACION Y COMERCIALIZACION DE ESTUPEFACIENTES. SE DA AVISO A COMANDO. ARRIBA PERSONAL POLICIAL. SE AMPLIA MOTO ID 2001660 INF SE IDENTIFICO LAS PERSONAS CON LAS DESCRIPCIONES APORTADAS , CORRESPONDE Y NO POSEE IMPEDIMENTOS,NO POSEE ELEMENTOS CONSTITUTIVOS DE DELITO.- | X42: 0 | Y42: 0 | Z42: 0 | AA42: 1C | AB42: U | AC42: MONITOREO | AF42: CARTA FINALIZADA | AL42: =VLOOKUP(G42,Hoja2!P:Q,2,0) -> 12149 | AM42: =IF(OR(Y42>0,X42>0),"IMPUTADO","NADA") -> NADA | AN42: =IF(AND(AM42="IMPUTADO",ISBLANK(M42)),"FALTO","NO") -> NO
A43: 45992 | B43: =IF(AND(VALUE(P43)>=VALUE("06:00"),VALUE(P43)<=VALUE("17:59")),"06 A 18","18 A 06") -> 06 A 18 | C43: =IF(AND(VALUE(P43)>=VALUE("00:00"),VALUE(P43)<=VALUE("01:59")),"00:00 a 02:00",IF(AND(VALUE(P43)>=VALUE("02:00"),VALUE(P43)<=VALUE("03:59")),"02:00 a 04:00",IF(AND(VALUE(P43)>=VALUE("04:00"),VALUE(P43)<=VALUE("05:59")),"04:00 a 06:00",IF(AND(VALUE(P43)>=VALUE("06:00"),VALUE(P43)<=VALUE("07:59")),"06:00 a 08:00",IF(AND(VALUE(P43)>=VALUE("08:00"),VALUE(P43)<=VALUE("09:59")),"08:00 a 10:00",IF(AND(VALUE(P43)>=VALUE("10:00"),VALUE(P43)<=VALUE("11:59")),"10:00 a 12:00",IF(AND(VALUE(P43)>=VALUE("12:00"),VALUE(P43)<=VALUE("13:59")),"12:00 a 14:00",IF(AND(VALUE(P43)>=VALUE("14:00"),VALUE(P43)<=VALUE("15:59")),"14:00 a 16:00",IF(AND(VALUE(P43)>=VALUE("16:00"),VALUE(P43)<=VALUE("17:59")),"16:00 a 18:00",IF(AND(VALUE(P43)>=VALUE("18:00"),VALUE(P43)<=VALUE("19:59")),"18:00 a 20:00",IF(AND(VALUE(P43)>=VALUE("20:00"),VALUE(P43)<=VALUE("21:59")),"20:00 a 22:00",IF(AND(VALUE(P43)>=VALUE("22:00"),VALUE(P43)<=VALUE("23:59")),"22:00 a 00:00","no corresponde")))))))))))) -> 08:00 a 10:00 | D43: MARTINEZ. R | E43: MARTINEZ, VERONICA | F43: 1 | G43: VILLEGAS, RODRIGO | H43: 923789 | I43: 46739152 | J43: VILLA LUGANO | K43: COLABORACION | L43: INCIDENCIA | M43: AT. Y RES. A LA AUTORIDAD | N43: LINIERS 09 / CAM 02 | O43: Liniers | P43: 0.39236111 | Q43: 0.39583333 | R43: 0.39236111 | S43: - | T43: - | U43: - | V43: - | W43: SE TOMA CONOCIMIENTO MEDIANTE CARTA SAE POR PEROSNAL POLICIAL QUE TENDIRA UNA INCIDENCIA CON UN MASC QUE NO SE QUERIA IDENTIFICAR.- SE APORTA LINEA DE TIEMPO,- SE COMUNICA VIA QSO OFICIAL LP 36348 FRANCO INF SE REALIZA CONSN UFLA SUR AC DR AUXILIAR DEL FISCAL DIAZ OSCAR SECRETARIA AC DR FLORENCIA BASIARONE QUIEN DISPUSO ACT POR ART 239 DETENCION DE MISMO /// PERSONAL ILESO .- | X43: 0 | Y43: 1 | Z43: 0 | AA43: 9B | AB43: U | AC43: CARTA | AE43: 1 DETENIDO | AF43: COLABORACION CON IMPUTADO/S | AL43: =VLOOKUP(G43,Hoja2!P:Q,2,0) -> 37989460 | AM43: =IF(OR(Y43>0,X43>0),"IMPUTADO","NADA") -> IMPUTADO | AN43: =IF(AND(AM43="IMPUTADO",ISBLANK(M43)),"FALTO","NO") -> NO
A44: 45992 | B44: =IF(AND(VALUE(P44)>=VALUE("06:00"),VALUE(P44)<=VALUE("17:59")),"06 A 18","18 A 06") -> 06 A 18 | C44: =IF(AND(VALUE(P44)>=VALUE("00:00"),VALUE(P44)<=VALUE("01:59")),"00:00 a 02:00",IF(AND(VALUE(P44)>=VALUE("02:00"),VALUE(P44)<=VALUE("03:59")),"02:00 a 04:00",IF(AND(VALUE(P44)>=VALUE("04:00"),VALUE(P44)<=VALUE("05:59")),"04:00 a 06:00",IF(AND(VALUE(P44)>=VALUE("06:00"),VALUE(P44)<=VALUE("07:59")),"06:00 a 08:00",IF(AND(VALUE(P44)>=VALUE("08:00"),VALUE(P44)<=VALUE("09:59")),"08:00 a 10:00",IF(AND(VALUE(P44)>=VALUE("10:00"),VALUE(P44)<=VALUE("11:59")),"10:00 a 12:00",IF(AND(VALUE(P44)>=VALUE("12:00"),VALUE(P44)<=VALUE("13:59")),"12:00 a 14:00",IF(AND(VALUE(P44)>=VALUE("14:00"),VALUE(P44)<=VALUE("15:59")),"14:00 a 16:00",IF(AND(VALUE(P44)>=VALUE("16:00"),VALUE(P44)<=VALUE("17:59")),"16:00 a 18:00",IF(AND(VALUE(P44)>=VALUE("18:00"),VALUE(P44)<=VALUE("19:59")),"18:00 a 20:00",IF(AND(VALUE(P44)>=VALUE("20:00"),VALUE(P44)<=VALUE("21:59")),"20:00 a 22:00",IF(AND(VALUE(P44)>=VALUE("22:00"),VALUE(P44)<=VALUE("23:59")),"22:00 a 00:00","no corresponde")))))))))))) -> 08:00 a 10:00 | D44: MARTINEZ. R | E44: PEREZ, RAMON | F44: 1 | G44: GARCIA, ORIANA | H44: 918541 | I44: 46739335 | J44: CHACARITA | K44: PERSONA CAIDA | N44: BALVANERA 01 | O44: Balvanera | P44: 0.41111111 | Q44: 0.42361111 | R44: 0.4125 | V44: - | W44: SE TOMA CONOCIMIENTO POR CARTA POR DTE REFIERE QUE HAY UN MASCULINO TENDIDO EN EL PISO ESTA COMO TEMBLANDO. ESTA CONCIENTE SOLICITA SAME,, AL TOMAR LA CAMARA SE VISUALIZA A UN MASCULINO CAIDO JUNTO A TRANSEUNTES. ARRIBA PERSONAL POLICIAL.-HT 3258 INF SE TRATO DE PERSONAS EN SITUACION VULNERABLE SE RETIRAN SIN NOVEDAD,PANORAMA NORMAL -107:NEGATIVO SAME SIN EFECTO.-CMU INF SE RETIRA PERSONAL POLICIAL DEL LUGAR.- | X44: 0 | Y44: 0 | Z44: 0 | AA44: 3A | AB44: U | AC44: CARTA | AF44: CARTA FINALIZADA | AL44: =VLOOKUP(G44,Hoja2!P:Q,2,0) -> 12595 | AM44: =IF(OR(Y44>0,X44>0),"IMPUTADO","NADA") -> NADA | AN44: =IF(AND(AM44="IMPUTADO",ISBLANK(M44)),"FALTO","NO") -> NO
A45: 45992 | B45: =IF(AND(VALUE(P45)>=VALUE("06:00"),VALUE(P45)<=VALUE("17:59")),"06 A 18","18 A 06") -> 06 A 18 | C45: =IF(AND(VALUE(P45)>=VALUE("00:00"),VALUE(P45)<=VALUE("01:59")),"00:00 a 02:00",IF(AND(VALUE(P45)>=VALUE("02:00"),VALUE(P45)<=VALUE("03:59")),"02:00 a 04:00",IF(AND(VALUE(P45)>=VALUE("04:00"),VALUE(P45)<=VALUE("05:59")),"04:00 a 06:00",IF(AND(VALUE(P45)>=VALUE("06:00"),VALUE(P45)<=VALUE("07:59")),"06:00 a 08:00",IF(AND(VALUE(P45)>=VALUE("08:00"),VALUE(P45)<=VALUE("09:59")),"08:00 a 10:00",IF(AND(VALUE(P45)>=VALUE("10:00"),VALUE(P45)<=VALUE("11:59")),"10:00 a 12:00",IF(AND(VALUE(P45)>=VALUE("12:00"),VALUE(P45)<=VALUE("13:59")),"12:00 a 14:00",IF(AND(VALUE(P45)>=VALUE("14:00"),VALUE(P45)<=VALUE("15:59")),"14:00 a 16:00",IF(AND(VALUE(P45)>=VALUE("16:00"),VALUE(P45)<=VALUE("17:59")),"16:00 a 18:00",IF(AND(VALUE(P45)>=VALUE("18:00"),VALUE(P45)<=VALUE("19:59")),"18:00 a 20:00",IF(AND(VALUE(P45)>=VALUE("20:00"),VALUE(P45)<=VALUE("21:59")),"20:00 a 22:00",IF(AND(VALUE(P45)>=VALUE("22:00"),VALUE(P45)<=VALUE("23:59")),"22:00 a 00:00","no corresponde")))))))))))) -> 10:00 a 12:00 | D45: MARTINEZ. R | E45: GAUNA, MICAELA | F45: 1 | G45: DIAZ, MARIA BELEN | H45: 918279 | I45: 46739385 | J45: PUERTO MADERO | K45: COLABORACION | L45: IDENT. DE PERSONAS | N45: RETIRO34 | O45: Retiro | P45: 0.43055556 | Q45: 0.43680556 | R45: 0.42708333 | V45: - | W45: SE TOMA CONOCIMIENTO MEDIANTE CARTA SAE SE MANTIENE AL DENUNCIANTE EN LINEA A LOS FINES DE APORTAR MAYORES DATOS DEL HECHO. NO ASOCIAR ESTA CARTA HASTA FINALIZAR LA COMUNICACION CON EL LLAMANTE.CMU INF SE VISUALIZA PUERTA DE FARMACITY.ARRIBO DE SAME | X45: 0 | Y45: 0 | Z45: 0 | AA45: 1A | AB45: U | AC45: CARTA | AF45: CARTA FINALIZADA | AL45: =VLOOKUP(G45,Hoja2!P:Q,2,0) -> 35166947 | AM45: =IF(OR(Y45>0,X45>0),"IMPUTADO","NADA") -> NADA | AN45: =IF(AND(AM45="IMPUTADO",ISBLANK(M45)),"FALTO","NO") -> NO
A46: 45992 | B46: =IF(AND(VALUE(P46)>=VALUE("06:00"),VALUE(P46)<=VALUE("17:59")),"06 A 18","18 A 06") -> 06 A 18 | C46: =IF(AND(VALUE(P46)>=VALUE("00:00"),VALUE(P46)<=VALUE("01:59")),"00:00 a 02:00",IF(AND(VALUE(P46)>=VALUE("02:00"),VALUE(P46)<=VALUE("03:59")),"02:00 a 04:00",IF(AND(VALUE(P46)>=VALUE("04:00"),VALUE(P46)<=VALUE("05:59")),"04:00 a 06:00",IF(AND(VALUE(P46)>=VALUE("06:00"),VALUE(P46)<=VALUE("07:59")),"06:00 a 08:00",IF(AND(VALUE(P46)>=VALUE("08:00"),VALUE(P46)<=VALUE("09:59")),"08:00 a 10:00",IF(AND(VALUE(P46)>=VALUE("10:00"),VALUE(P46)<=VALUE("11:59")),"10:00 a 12:00",IF(AND(VALUE(P46)>=VALUE("12:00"),VALUE(P46)<=VALUE("13:59")),"12:00 a 14:00",IF(AND(VALUE(P46)>=VALUE("14:00"),VALUE(P46)<=VALUE("15:59")),"14:00 a 16:00",IF(AND(VALUE(P46)>=VALUE("16:00"),VALUE(P46)<=VALUE("17:59")),"16:00 a 18:00",IF(AND(VALUE(P46)>=VALUE("18:00"),VALUE(P46)<=VALUE("19:59")),"18:00 a 20:00",IF(AND(VALUE(P46)>=VALUE("20:00"),VALUE(P46)<=VALUE("21:59")),"20:00 a 22:00",IF(AND(VALUE(P46)>=VALUE("22:00"),VALUE(P46)<=VALUE("23:59")),"22:00 a 00:00","no corresponde")))))))))))) -> 08:00 a 10:00 | D46: MARTINEZ. R | E46: MEZA, GASTON | F46: 1 | G46: KRAKOVSKY, FLORENCIA | H46: 918269 | I46: 46739414 | J46: CMU 9 DE JULIO | K46: ROBO/HURTO | M46: ROBO/HURTO | N46: CONSTITUCION O137 | O46: Constitucion | P46: 0.41388889 | Q46: 0.47916667 | R46: 0.42430556 | V46: - | W46: SE VISUALIZA A UN MASCULINO DESCARTANDO ELEMENTOS. CAMARA CONSTITUCION 75. SE DA AVISO A COMANDO. ARRIBA PERSONAL POLICIAL DANDO CON EL MASCULINO EN MENCIOPN. SE APORTA LINEA DE TIEMPO POR CAMARA CONSTITUCION 12 DONDE SE VISUALIZA EL MOMENTO DEL HECHO. SE AMPLIA HT INF VIA QSO SE REALIZO CONSULTA CON EL JUZGADO NCC NRO 40 AC DRA PAULA GONZALEZ SECRETARIA NRO 139 AC DR DE SIMONI PABLO, QUIEN DISPUSO SE LABREN ACTUACIONES POR ROBO , DETENCION DE AMBOS MASCULINOS,DECLARACION Y VISTA FILMICA DE MONITOREO.- | X46: 0 | Y46: 1 | Z46: 0 | AA46: 1C | AB46: U | AC46: MONITOREO | AE46: 1 DETENIDO | AF46: FINALIZA CON IMPUTADO/S | AL46: =VLOOKUP(G46,Hoja2!P:Q,2,0) -> 41290026 | AM46: =IF(OR(Y46>0,X46>0),"IMPUTADO","NADA") -> IMPUTADO | AN46: =IF(AND(AM46="IMPUTADO",ISBLANK(M46)),"FALTO","NO") -> NO
A47: 45992 | B47: =IF(AND(VALUE(P47)>=VALUE("06:00"),VALUE(P47)<=VALUE("17:59")),"06 A 18","18 A 06") -> 06 A 18 | C47: =IF(AND(VALUE(P47)>=VALUE("00:00"),VALUE(P47)<=VALUE("01:59")),"00:00 a 02:00",IF(AND(VALUE(P47)>=VALUE("02:00"),VALUE(P47)<=VALUE("03:59")),"02:00 a 04:00",IF(AND(VALUE(P47)>=VALUE("04:00"),VALUE(P47)<=VALUE("05:59")),"04:00 a 06:00",IF(AND(VALUE(P47)>=VALUE("06:00"),VALUE(P47)<=VALUE("07:59")),"06:00 a 08:00",IF(AND(VALUE(P47)>=VALUE("08:00"),VALUE(P47)<=VALUE("09:59")),"08:00 a 10:00",IF(AND(VALUE(P47)>=VALUE("10:00"),VALUE(P47)<=VALUE("11:59")),"10:00 a 12:00",IF(AND(VALUE(P47)>=VALUE("12:00"),VALUE(P47)<=VALUE("13:59")),"12:00 a 14:00",IF(AND(VALUE(P47)>=VALUE("14:00"),VALUE(P47)<=VALUE("15:59")),"14:00 a 16:00",IF(AND(VALUE(P47)>=VALUE("16:00"),VALUE(P47)<=VALUE("17:59")),"16:00 a 18:00",IF(AND(VALUE(P47)>=VALUE("18:00"),VALUE(P47)<=VALUE("19:59")),"18:00 a 20:00",IF(AND(VALUE(P47)>=VALUE("20:00"),VALUE(P47)<=VALUE("21:59")),"20:00 a 22:00",IF(AND(VALUE(P47)>=VALUE("22:00"),VALUE(P47)<=VALUE("23:59")),"22:00 a 00:00","no corresponde")))))))))))) -> 10:00 a 12:00 | D47: MARTINEZ. R | E47: PEREZ, RAMON | F47: 1 | G47: MOLINA, MARIA LAURA | H47: 918261 | I47: 46739564 | J47: CHACARITA | K47: TENENCIA ESTUPEFACIENTES | N47: BALVANERA 03 | O47: Balvanera | P47: 0.42847222 | Q47: 0.44236111 | R47: 0.43125 | S47: - | T47: - | U47: - | V47: - | W47: SE VISUALIZA MEDIANTE CAMARA BALVANERA 03 A 3 MASCULINOS MANIPULANDO LO QUE APARENTEMENTE SERIA SUSTANCIA ESTUPEFACIENTES EN EL INTERIOR DE LA PLAZA MISERERE.-CMU AMPLIA UN MASCULINO VISTE GORRA AZUL, CAMPERA AMARILLA CON CELESTE, JEAN CLARO, EL OTRO MASCULINO GORRA BLANCA, CAMPERA OSCURA, JEAN AZUL, CALZADO CLARO, OTRO MASCULINO VISTE CAMPERA OSCURA CON CAPUCHA COLOCADA, PANTALON GRIS.-CMU AMPLIA SE VISUALIZA EL PERSONAL POLICIAL DAR CON LOS MASCULINOS.-CMU AMPLIA LAS PERSONAS SE ENCONTRABAN MANIPULANDO UN ENVOLTORIO SIMIL BOLSA.- CICLISTA INF NEGATIVO ESTUPEFACIENTES EN EL LUGAR SE TRATO DE UNA BOLSA DE GALLETITAS.- | X47: 0 | Y47: 0 | Z47: 0 | AA47: 3A | AB47: U | AC47: MONITOREO | AF47: CARTA FINALIZADA | AL47: =VLOOKUP(G47,Hoja2!P:Q,2,0) -> 12826 | AM47: =IF(OR(Y47>0,X47>0),"IMPUTADO","NADA") -> NADA | AN47: =IF(AND(AM47="IMPUTADO",ISBLANK(M47)),"FALTO","NO") -> NO
A48: 45992 | B48: =IF(AND(VALUE(P48)>=VALUE("06:00"),VALUE(P48)<=VALUE("17:59")),"06 A 18","18 A 06") -> 06 A 18 | C48: =IF(AND(VALUE(P48)>=VALUE("00:00"),VALUE(P48)<=VALUE("01:59")),"00:00 a 02:00",IF(AND(VALUE(P48)>=VALUE("02:00"),VALUE(P48)<=VALUE("03:59")),"02:00 a 04:00",IF(AND(VALUE(P48)>=VALUE("04:00"),VALUE(P48)<=VALUE("05:59")),"04:00 a 06:00",IF(AND(VALUE(P48)>=VALUE("06:00"),VALUE(P48)<=VALUE("07:59")),"06:00 a 08:00",IF(AND(VALUE(P48)>=VALUE("08:00"),VALUE(P48)<=VALUE("09:59")),"08:00 a 10:00",IF(AND(VALUE(P48)>=VALUE("10:00"),VALUE(P48)<=VALUE("11:59")),"10:00 a 12:00",IF(AND(VALUE(P48)>=VALUE("12:00"),VALUE(P48)<=VALUE("13:59")),"12:00 a 14:00",IF(AND(VALUE(P48)>=VALUE("14:00"),VALUE(P48)<=VALUE("15:59")),"14:00 a 16:00",IF(AND(VALUE(P48)>=VALUE("16:00"),VALUE(P48)<=VALUE("17:59")),"16:00 a 18:00",IF(AND(VALUE(P48)>=VALUE("18:00"),VALUE(P48)<=VALUE("19:59")),"18:00 a 20:00",IF(AND(VALUE(P48)>=VALUE("20:00"),VALUE(P48)<=VALUE("21:59")),"20:00 a 22:00",IF(AND(VALUE(P48)>=VALUE("22:00"),VALUE(P48)<=VALUE("23:59")),"22:00 a 00:00","no corresponde")))))))))))) -> 10:00 a 12:00 | D48: MARTINEZ. R | E48: PEREZ, RAMON | F48: 1 | G48: BENDITTI, JULIETA | H48: 918454 | I48: 46739724 | J48: CHACARITA | K48: INCIDENCIA EN VIA PUBLICA | N48: PALERMO O166 | O48: Palermo | P48: 0.45069444 | Q48: 0.45138889 | R48: 0.45069444 | S48: - | T48: - | U48: - | V48: - | W48: SE TOMA CONOCIMIENTO MEDIANTE CARTA SAE MASCULINO REFIERE QUE HABRIA UN MASCULINO QUE SE ENCONTRARIA AGRESIVO EN EL INTERIOR DEL PARQUE, APARENTEMENTE ESTE MASCULINO SE ENCONTRARIA BAJO LOS EFECTOS DE ESTUPEFACIENTES, SOLICITA MOVIL.- CUATRI R 184 AL ARRIBO SE TRATO DE PERSONA EN SITUACION DE VULNERABILIDAD SE RETIRA DEL LUGAR | X48: 0 | Y48: 0 | Z48: 0 | AA48: 14C | AB48: U | AC48: CARTA | AF48: CARTA FINALIZADA | AL48: =VLOOKUP(G48,Hoja2!P:Q,2,0) -> 38919576 | AM48: =IF(OR(Y48>0,X48>0),"IMPUTADO","NADA") -> NADA | AN48: =IF(AND(AM48="IMPUTADO",ISBLANK(M48)),"FALTO","NO") -> NO
A49: 45992 | B49: =IF(AND(VALUE(P49)>=VALUE("06:00"),VALUE(P49)<=VALUE("17:59")),"06 A 18","18 A 06") -> 06 A 18 | C49: =IF(AND(VALUE(P49)>=VALUE("00:00"),VALUE(P49)<=VALUE("01:59")),"00:00 a 02:00",IF(AND(VALUE(P49)>=VALUE("02:00"),VALUE(P49)<=VALUE("03:59")),"02:00 a 04:00",IF(AND(VALUE(P49)>=VALUE("04:00"),VALUE(P49)<=VALUE("05:59")),"04:00 a 06:00",IF(AND(VALUE(P49)>=VALUE("06:00"),VALUE(P49)<=VALUE("07:59")),"06:00 a 08:00",IF(AND(VALUE(P49)>=VALUE("08:00"),VALUE(P49)<=VALUE("09:59")),"08:00 a 10:00",IF(AND(VALUE(P49)>=VALUE("10:00"),VALUE(P49)<=VALUE("11:59")),"10:00 a 12:00",IF(AND(VALUE(P49)>=VALUE("12:00"),VALUE(P49)<=VALUE("13:59")),"12:00 a 14:00",IF(AND(VALUE(P49)>=VALUE("14:00"),VALUE(P49)<=VALUE("15:59")),"14:00 a 16:00",IF(AND(VALUE(P49)>=VALUE("16:00"),VALUE(P49)<=VALUE("17:59")),"16:00 a 18:00",IF(AND(VALUE(P49)>=VALUE("18:00"),VALUE(P49)<=VALUE("19:59")),"18:00 a 20:00",IF(AND(VALUE(P49)>=VALUE("20:00"),VALUE(P49)<=VALUE("21:59")),"20:00 a 22:00",IF(AND(VALUE(P49)>=VALUE("22:00"),VALUE(P49)<=VALUE("23:59")),"22:00 a 00:00","no corresponde")))))))))))) -> 10:00 a 12:00 | D49: MARTINEZ. R | E49: ARREGUI, FERNANDO | F49: 1 | G49: CARRIZO RODRIGO | H49: 918540 | I49: 46739873 | J49: CHACARITA | K49: IDENTIFICACION DE PERSONAS | N49: FLORES O245 | O49: Flores | P49: 0.47222222 | Q49: 0.50833333 | R49: 0.47222222 | S49: - | T49: - | U49: - | V49: - | W49: SE TOMA CONOCIMIENTO MEDIANTE CARTA SAE EVENTO DE ALARMA.- CMU SE REALIZA LINEA DE TIEMPO POR LA CAMARA FLORESO245 SIENDO LAS 10:52:26 SE VISUALIZO UN MOTOVEHICULO MODELO AFZ COLOR NEGRO UNO DE LOS MASCULINO VESTIMENTA NEGRA CON CASCO COLOCADO NEGRO. TRIPULANDO EL MOTOVEHICULO. EL SEGUNDO MASCULINO ROPAS NEGRAS CASCO COLOCADO COLOR NEGRO PROXIMO A LA VENTANILLA DEL CONDUCTOR. NO SE VISUALIZA EL HECHO ILICITO. ESTOS SE RETIRAN POR PUMACAHUA SENTIDO . JUAN B ALBERDI.- SE COMUNICA VIA QSO INSP LP 2871 PIGNOME ALEJANDRO , QUIEN INF AL DAMNIFICADO LE SUSTRAEN SU MOCHILA DE REPARTO Y LLAVES DE LA CAMIONETA , SE REALIZO CONSULTA CON LA FIS 55 A/C DOC TRONCOZO SECRET UNICA A/C DOC SANDELA ACT POR ROBO AMA .- SE REALIZO CONSULTA CON LA FIS 55 A/C DOC TRONCOZO SECRET UNICA A/C DOC SANDELA ACT POR ROBO AMA . SE SOLICITAN LOS SERVICIOS DE RASTROS PARA EL VEHICULO , PERSONAL DE CONSIGNA OF PRIMERO LP 11092 MARTINEZ POC 1171663989 | X49: 0 | Y49: 0 | Z49: 0 | AA49: 7C | AB49: U | AC49: CARTA | AF49: CARTA FINALIZADA | AL49: =VLOOKUP(G49,Hoja2!P:Q,2,0) -> 43444086 | AM49: =IF(OR(Y49>0,X49>0),"IMPUTADO","NADA") -> NADA | AN49: =IF(AND(AM49="IMPUTADO",ISBLANK(M49)),"FALTO","NO") -> NO
A50: 45992 | B50: =IF(AND(VALUE(P50)>=VALUE("06:00"),VALUE(P50)<=VALUE("17:59")),"06 A 18","18 A 06") -> 06 A 18 | C50: =IF(AND(VALUE(P50)>=VALUE("00:00"),VALUE(P50)<=VALUE("01:59")),"00:00 a 02:00",IF(AND(VALUE(P50)>=VALUE("02:00"),VALUE(P50)<=VALUE("03:59")),"02:00 a 04:00",IF(AND(VALUE(P50)>=VALUE("04:00"),VALUE(P50)<=VALUE("05:59")),"04:00 a 06:00",IF(AND(VALUE(P50)>=VALUE("06:00"),VALUE(P50)<=VALUE("07:59")),"06:00 a 08:00",IF(AND(VALUE(P50)>=VALUE("08:00"),VALUE(P50)<=VALUE("09:59")),"08:00 a 10:00",IF(AND(VALUE(P50)>=VALUE("10:00"),VALUE(P50)<=VALUE("11:59")),"10:00 a 12:00",IF(AND(VALUE(P50)>=VALUE("12:00"),VALUE(P50)<=VALUE("13:59")),"12:00 a 14:00",IF(AND(VALUE(P50)>=VALUE("14:00"),VALUE(P50)<=VALUE("15:59")),"14:00 a 16:00",IF(AND(VALUE(P50)>=VALUE("16:00"),VALUE(P50)<=VALUE("17:59")),"16:00 a 18:00",IF(AND(VALUE(P50)>=VALUE("18:00"),VALUE(P50)<=VALUE("19:59")),"18:00 a 20:00",IF(AND(VALUE(P50)>=VALUE("20:00"),VALUE(P50)<=VALUE("21:59")),"20:00 a 22:00",IF(AND(VALUE(P50)>=VALUE("22:00"),VALUE(P50)<=VALUE("23:59")),"22:00 a 00:00","no corresponde")))))))))))) -> 10:00 a 12:00 | D50: MARTINEZ. R | E50: PEREZ, RAMON | F50: 1 | G50: VORPAGEL, SABRINA | H50: 918118 | I50: 46739946 | J50: CHACARITA | K50: COLABORACION | L50: CHOQUE | N50: ALMAGRO 30 | O50: Almagro | P50: 0.46527778 | Q50: 0.48611111 | R50: 0.46597222 | S50: - | T50: - | U50: - | V50: - | W50: SE TOMA CONOCIMIENTO MEDIANTE CARTA SAE MASCULINO REFIERE QUE HABRIA UN CHOQUE ENTRE DOS VEHICULOS.- 605 INF SE TRATO DE UN CHOQUE SIMPLE - ASI MISMO DE REMITE EL VEHIVULO EN MENCION POR FALTA DE SEG Y LICENCIA DE CONDUCIR | X50: 0 | Y50: 0 | Z50: 0 | AA50: 3B | AB50: U | AC50: CARTA | AF50: CARTA FINALIZADA | AL50: =VLOOKUP(G50,Hoja2!P:Q,2,0) -> 40835168 | AM50: =IF(OR(Y50>0,X50>0),"IMPUTADO","NADA") -> NADA | AN50: =IF(AND(AM50="IMPUTADO",ISBLANK(M50)),"FALTO","NO") -> NO
A51: 45992 | B51: =IF(AND(VALUE(P51)>=VALUE("06:00"),VALUE(P51)<=VALUE("17:59")),"06 A 18","18 A 06") -> 06 A 18 | C51: =IF(AND(VALUE(P51)>=VALUE("00:00"),VALUE(P51)<=VALUE("01:59")),"00:00 a 02:00",IF(AND(VALUE(P51)>=VALUE("02:00"),VALUE(P51)<=VALUE("03:59")),"02:00 a 04:00",IF(AND(VALUE(P51)>=VALUE("04:00"),VALUE(P51)<=VALUE("05:59")),"04:00 a 06:00",IF(AND(VALUE(P51)>=VALUE("06:00"),VALUE(P51)<=VALUE("07:59")),"06:00 a 08:00",IF(AND(VALUE(P51)>=VALUE("08:00"),VALUE(P51)<=VALUE("09:59")),"08:00 a 10:00",IF(AND(VALUE(P51)>=VALUE("10:00"),VALUE(P51)<=VALUE("11:59")),"10:00 a 12:00",IF(AND(VALUE(P51)>=VALUE("12:00"),VALUE(P51)<=VALUE("13:59")),"12:00 a 14:00",IF(AND(VALUE(P51)>=VALUE("14:00"),VALUE(P51)<=VALUE("15:59")),"14:00 a 16:00",IF(AND(VALUE(P51)>=VALUE("16:00"),VALUE(P51)<=VALUE("17:59")),"16:00 a 18:00",IF(AND(VALUE(P51)>=VALUE("18:00"),VALUE(P51)<=VALUE("19:59")),"18:00 a 20:00",IF(AND(VALUE(P51)>=VALUE("20:00"),VALUE(P51)<=VALUE("21:59")),"20:00 a 22:00",IF(AND(VALUE(P51)>=VALUE("22:00"),VALUE(P51)<=VALUE("23:59")),"22:00 a 00:00","no corresponde")))))))))))) -> 10:00 a 12:00 | D51: MARTINEZ. R | E51: MOLINA, JOSE MANUEL | F51: 1 | G51: BENDITTI, JULIETA | H51: 918267 | I51: 46739961 | J51: CHACARITA | K51: PERSONA DESCOMPUESTA | N51: BELGRANO O100 | O51: Belgrano | P51: 0.46875 | Q51: 0.47708333 | R51: 0.47083333 | S51: - | T51: - | U51: - | V51: - | W51: SE TOMA CONOCIMIENTO MEDIANTE CARTA SAE LLAMANTE SOLICITA ASISTENCIA MEDICA PARA FEMENINO DESVANECIDA / INCONSCIENTE DENTRO DE COLECTIVO LINEA 80.- HT IND QUE EN EL LUGAR EL FEM SE RETIRA DEL LUGAR POR SUS MEDIOS,A LA MISMA LE BAJO LA PRESION SE RECOMPONE Y SE RETIRA DEL LUGAR SIN NOVEDAD | X51: 0 | Y51: 0 | Z51: 0 | AA51: 13A | AB51: U | AC51: CARTA | AF51: CARTA FINALIZADA | AL51: =VLOOKUP(G51,Hoja2!P:Q,2,0) -> 38919576 | AM51: =IF(OR(Y51>0,X51>0),"IMPUTADO","NADA") -> NADA | AN51: =IF(AND(AM51="IMPUTADO",ISBLANK(M51)),"FALTO","NO") -> NO
A52: 45992 | B52: =IF(AND(VALUE(P52)>=VALUE("06:00"),VALUE(P52)<=VALUE("17:59")),"06 A 18","18 A 06") -> 06 A 18 | C52: =IF(AND(VALUE(P52)>=VALUE("00:00"),VALUE(P52)<=VALUE("01:59")),"00:00 a 02:00",IF(AND(VALUE(P52)>=VALUE("02:00"),VALUE(P52)<=VALUE("03:59")),"02:00 a 04:00",IF(AND(VALUE(P52)>=VALUE("04:00"),VALUE(P52)<=VALUE("05:59")),"04:00 a 06:00",IF(AND(VALUE(P52)>=VALUE("06:00"),VALUE(P52)<=VALUE("07:59")),"06:00 a 08:00",IF(AND(VALUE(P52)>=VALUE("08:00"),VALUE(P52)<=VALUE("09:59")),"08:00 a 10:00",IF(AND(VALUE(P52)>=VALUE("10:00"),VALUE(P52)<=VALUE("11:59")),"10:00 a 12:00",IF(AND(VALUE(P52)>=VALUE("12:00"),VALUE(P52)<=VALUE("13:59")),"12:00 a 14:00",IF(AND(VALUE(P52)>=VALUE("14:00"),VALUE(P52)<=VALUE("15:59")),"14:00 a 16:00",IF(AND(VALUE(P52)>=VALUE("16:00"),VALUE(P52)<=VALUE("17:59")),"16:00 a 18:00",IF(AND(VALUE(P52)>=VALUE("18:00"),VALUE(P52)<=VALUE("19:59")),"18:00 a 20:00",IF(AND(VALUE(P52)>=VALUE("20:00"),VALUE(P52)<=VALUE("21:59")),"20:00 a 22:00",IF(AND(VALUE(P52)>=VALUE("22:00"),VALUE(P52)<=VALUE("23:59")),"22:00 a 00:00","no corresponde")))))))))))) -> 10:00 a 12:00 | D52: MARTINEZ. R | E52: PEREZ, RAMON | F52: 1 | G52: CARDOZO, ROMINA | H52: 918301 | I52: 46740009 | J52: CHACARITA | K52: IDENTIFICACION DE PERSONAS | N52: CHACARITA 76 | O52: Chacarita | P52: 0.46944444 | Q52: 0.49305556 | R52: 0.46944444 | S52: - | T52: - | U52: - | V52: - | W52: SE VISUALIZA MEDIANTE CAMARA CHACARITA76 A PERSONAL POLICIAL CON APARENTE DAMNIFICADA.- CMU AMPLIA: SE TOMA CONOCIMIENTO MEDIANTE QSO SOBRE ROBO CON MOTOVEHICULO EN EL LUGAR. REALIZADA LINEA DE TIEMPO MEDIANTE CAMRA CHCARITA76 TANTO DOMO COMO CAMARAS FIJAS SIENDO LAS 10:55HS. SE VISUALIZA A UN MOTOVEHICULO COLOR NEGRO TRIPULADO POR UN MASCULINO CASCO COLOCADO COLOR NEGRO, CAMPERA COLOR NEGRA Y PANTALON LARGO COLOR NEGRO CON FRANJAS BLANCAS. EL MISMO CIRCULABA POR FRAGA Y ASCIENDE A LA VEREDA CIRCULANDO ALGUNOS METROS SOBRE LA MISMA PARA LUEGO DESCENDER Y RETIRARSE POR MAURE. SE DEJA CONSTANCIA DE QUE NO SE LOGRA VISUALIZAR EL MOMENTO DEL HECHO ILICITO.-CMU AMPLIA: SE RETIRO PERSONAL POLICIAL.-ACTS POR ROBO CON INTERV DE FISC N 14 AC DR MADREA SECR AC DRA GARRIT-.MOTO INF DAMNIFICADA ILESA-. | X52: 0 | Y52: 0 | Z52: 0 | AA52: 15A | AB52: U | AC52: MONITOREO | AF52: CARTA FINALIZADA | AL52: =VLOOKUP(G52,Hoja2!P:Q,2,0) -> 32445282 | AM52: =IF(OR(Y52>0,X52>0),"IMPUTADO","NADA") -> NADA | AN52: =IF(AND(AM52="IMPUTADO",ISBLANK(M52)),"FALTO","NO") -> NO
A53: 45992 | B53: =IF(AND(VALUE(P53)>=VALUE("06:00"),VALUE(P53)<=VALUE("17:59")),"06 A 18","18 A 06") -> 06 A 18 | C53: =IF(AND(VALUE(P53)>=VALUE("00:00"),VALUE(P53)<=VALUE("01:59")),"00:00 a 02:00",IF(AND(VALUE(P53)>=VALUE("02:00"),VALUE(P53)<=VALUE("03:59")),"02:00 a 04:00",IF(AND(VALUE(P53)>=VALUE("04:00"),VALUE(P53)<=VALUE("05:59")),"04:00 a 06:00",IF(AND(VALUE(P53)>=VALUE("06:00"),VALUE(P53)<=VALUE("07:59")),"06:00 a 08:00",IF(AND(VALUE(P53)>=VALUE("08:00"),VALUE(P53)<=VALUE("09:59")),"08:00 a 10:00",IF(AND(VALUE(P53)>=VALUE("10:00"),VALUE(P53)<=VALUE("11:59")),"10:00 a 12:00",IF(AND(VALUE(P53)>=VALUE("12:00"),VALUE(P53)<=VALUE("13:59")),"12:00 a 14:00",IF(AND(VALUE(P53)>=VALUE("14:00"),VALUE(P53)<=VALUE("15:59")),"14:00 a 16:00",IF(AND(VALUE(P53)>=VALUE("16:00"),VALUE(P53)<=VALUE("17:59")),"16:00 a 18:00",IF(AND(VALUE(P53)>=VALUE("18:00"),VALUE(P53)<=VALUE("19:59")),"18:00 a 20:00",IF(AND(VALUE(P53)>=VALUE("20:00"),VALUE(P53)<=VALUE("21:59")),"20:00 a 22:00",IF(AND(VALUE(P53)>=VALUE("22:00"),VALUE(P53)<=VALUE("23:59")),"22:00 a 00:00","no corresponde")))))))))))) -> 10:00 a 12:00 | D53: MARTINEZ. R | E53: MARTINEZ, VERONICA | F53: 1 | G53: LAMELA, AGUSTIN | H53: 923794 | I53: 46740098 | J53: VILLA LUGANO | K53: COLABORACION | L53: CHOQUE | M53: LESIONES | N53: MATADEROS 54 / CAM 02 | O53: Mataderos | P53: 0.475 | Q53: 0.54166667 | R53: 0.47569444 | S53: 0.49166667 | T53: - | U53: - | V53: - | W53: SE VISUALIZA MEIDNATE CAMARA UN CHOQUE Y PEROSNAL POLICIAL EN EL LUGAR,A RRIBA SAME Y SE RETIRA OCN TRASLADO ,- SAME INT 417 AC DR VILLALBA MN 201026 ASISTE Y DERIVA CON POLITRAUMATISMO AL HOSPITAL SANTOJANI,- 709A INF EVACUO CONSULTA CON UFLA SUR AC DR ESPADA ACTS POR LESIONES 94 .- NO SE REQUIEREN SERVICIOS | X53: 0 | Y53: 1 | Z53: 1 | AA53: 9A | AB53: U | AC53: MONITOREO | AE53: 1 IMPUTADO / 1 TRASLADO DE SAME | AF53: COLABORACION CON IMPUTADO/S | AL53: =VLOOKUP(G53,Hoja2!P:Q,2,0) -> 42949397 | AM53: =IF(OR(Y53>0,X53>0),"IMPUTADO","NADA") -> IMPUTADO | AN53: =IF(AND(AM53="IMPUTADO",ISBLANK(M53)),"FALTO","NO") -> NO
A54: 45992 | B54: =IF(AND(VALUE(P54)>=VALUE("06:00"),VALUE(P54)<=VALUE("17:59")),"06 A 18","18 A 06") -> 06 A 18 | C54: =IF(AND(VALUE(P54)>=VALUE("00:00"),VALUE(P54)<=VALUE("01:59")),"00:00 a 02:00",IF(AND(VALUE(P54)>=VALUE("02:00"),VALUE(P54)<=VALUE("03:59")),"02:00 a 04:00",IF(AND(VALUE(P54)>=VALUE("04:00"),VALUE(P54)<=VALUE("05:59")),"04:00 a 06:00",IF(AND(VALUE(P54)>=VALUE("06:00"),VALUE(P54)<=VALUE("07:59")),"06:00 a 08:00",IF(AND(VALUE(P54)>=VALUE("08:00"),VALUE(P54)<=VALUE("09:59")),"08:00 a 10:00",IF(AND(VALUE(P54)>=VALUE("10:00"),VALUE(P54)<=VALUE("11:59")),"10:00 a 12:00",IF(AND(VALUE(P54)>=VALUE("12:00"),VALUE(P54)<=VALUE("13:59")),"12:00 a 14:00",IF(AND(VALUE(P54)>=VALUE("14:00"),VALUE(P54)<=VALUE("15:59")),"14:00 a 16:00",IF(AND(VALUE(P54)>=VALUE("16:00"),VALUE(P54)<=VALUE("17:59")),"16:00 a 18:00",IF(AND(VALUE(P54)>=VALUE("18:00"),VALUE(P54)<=VALUE("19:59")),"18:00 a 20:00",IF(AND(VALUE(P54)>=VALUE("20:00"),VALUE(P54)<=VALUE("21:59")),"20:00 a 22:00",IF(AND(VALUE(P54)>=VALUE("22:00"),VALUE(P54)<=VALUE("23:59")),"22:00 a 00:00","no corresponde")))))))))))) -> 10:00 a 12:00 | D54: MARTINEZ. R | E54: PEREZ, RAMON | F54: 1 | G54: ISLEÑO, LUCAS | H54: 918808 | I54: 46740250 | J54: CHACARITA | K54: COLABORACION | L54: IDENT. DE PERSONAS | N54: PATERNAL 19 | O54: La Paternal | P54: 0.49652778 | Q54: 0.51041667 | R54: 0.48958333 | V54: - | W54: SE VISUALIZA MEDIANTE CAMARA PATERNAL19 A PERSONAL POLICIAL IDENTIFICACNDO A UN MASCULINO EN WARNES Y OSORIO.- CMU AMPLIA QUE SE VISUALIZA EL RETIRO DE PERSONAL POLICIAL- CMU AMPLIA QUE SE VISUALIZA EL RETIRO DE PERSONAL POLICIAL.- | X54: 0 | Y54: 0 | Z54: 0 | AA54: 15A | AB54: U | AC54: MONITOREO | AF54: CARTA FINALIZADA | AL54: =VLOOKUP(G54,Hoja2!P:Q,2,0) -> 11675 | AM54: =IF(OR(Y54>0,X54>0),"IMPUTADO","NADA") -> NADA | AN54: =IF(AND(AM54="IMPUTADO",ISBLANK(M54)),"FALTO","NO") -> NO
A55: 45992 | B55: =IF(AND(VALUE(P55)>=VALUE("06:00"),VALUE(P55)<=VALUE("17:59")),"06 A 18","18 A 06") -> 06 A 18 | C55: =IF(AND(VALUE(P55)>=VALUE("00:00"),VALUE(P55)<=VALUE("01:59")),"00:00 a 02:00",IF(AND(VALUE(P55)>=VALUE("02:00"),VALUE(P55)<=VALUE("03:59")),"02:00 a 04:00",IF(AND(VALUE(P55)>=VALUE("04:00"),VALUE(P55)<=VALUE("05:59")),"04:00 a 06:00",IF(AND(VALUE(P55)>=VALUE("06:00"),VALUE(P55)<=VALUE("07:59")),"06:00 a 08:00",IF(AND(VALUE(P55)>=VALUE("08:00"),VALUE(P55)<=VALUE("09:59")),"08:00 a 10:00",IF(AND(VALUE(P55)>=VALUE("10:00"),VALUE(P55)<=VALUE("11:59")),"10:00 a 12:00",IF(AND(VALUE(P55)>=VALUE("12:00"),VALUE(P55)<=VALUE("13:59")),"12:00 a 14:00",IF(AND(VALUE(P55)>=VALUE("14:00"),VALUE(P55)<=VALUE("15:59")),"14:00 a 16:00",IF(AND(VALUE(P55)>=VALUE("16:00"),VALUE(P55)<=VALUE("17:59")),"16:00 a 18:00",IF(AND(VALUE(P55)>=VALUE("18:00"),VALUE(P55)<=VALUE("19:59")),"18:00 a 20:00",IF(AND(VALUE(P55)>=VALUE("20:00"),VALUE(P55)<=VALUE("21:59")),"20:00 a 22:00",IF(AND(VALUE(P55)>=VALUE("22:00"),VALUE(P55)<=VALUE("23:59")),"22:00 a 00:00","no corresponde")))))))))))) -> 10:00 a 12:00 | D55: MARTINEZ. R | E55: MARTINEZ, VERONICA | F55: 1 | G55: VILLEGAS, RODRIGO | H55: 923796 | I55: 46740283 | J55: VILLA LUGANO | K55: COLABORACION | L55: PERSONA CAIDA/DEMANDA DE AUXILIO | N55: LINIERS 40 | O55: Liniers | P55: 0.49930556 | Q55: 0.52083333 | R55: 0.49930556 | S55: 0.5125 | T55: - | U55: - | V55: - | W55: SE TOMA CONOCIMIENTO MEIDANTE CARTA SAE POR UNA PERSONA QUE ESTARIA CON UN ATAQUE DE ACV EN VIA PUBLICA.- AL MOMENTO DE TOMAR LA CAMARA SE BRINDA APOYO OPTICO A PEROSNAL POLICIAL ASISITNEOD A UNA PEROSNA ,-HT 179 INF ARRIO SAME INT 381 DE HOSP SANTOJANNI AC DRA DEBORRA VILLALBA MN 201026 ASISTE Y DERIVA CON DIAG DETERIORO SENSORIAL | X55: 0 | Y55: 0 | Z55: 1 | AA55: 9B | AB55: U | AC55: CARTA | AE55: 1 TRASLADO DE SAME | AF55: CARTA FINALIZADA | AL55: =VLOOKUP(G55,Hoja2!P:Q,2,0) -> 37989460 | AM55: =IF(OR(Y55>0,X55>0),"IMPUTADO","NADA") -> NADA | AN55: =IF(AND(AM55="IMPUTADO",ISBLANK(M55)),"FALTO","NO") -> NO
A56: 45992 | B56: =IF(AND(VALUE(P56)>=VALUE("06:00"),VALUE(P56)<=VALUE("17:59")),"06 A 18","18 A 06") -> 06 A 18 | C56: =IF(AND(VALUE(P56)>=VALUE("00:00"),VALUE(P56)<=VALUE("01:59")),"00:00 a 02:00",IF(AND(VALUE(P56)>=VALUE("02:00"),VALUE(P56)<=VALUE("03:59")),"02:00 a 04:00",IF(AND(VALUE(P56)>=VALUE("04:00"),VALUE(P56)<=VALUE("05:59")),"04:00 a 06:00",IF(AND(VALUE(P56)>=VALUE("06:00"),VALUE(P56)<=VALUE("07:59")),"06:00 a 08:00",IF(AND(VALUE(P56)>=VALUE("08:00"),VALUE(P56)<=VALUE("09:59")),"08:00 a 10:00",IF(AND(VALUE(P56)>=VALUE("10:00"),VALUE(P56)<=VALUE("11:59")),"10:00 a 12:00",IF(AND(VALUE(P56)>=VALUE("12:00"),VALUE(P56)<=VALUE("13:59")),"12:00 a 14:00",IF(AND(VALUE(P56)>=VALUE("14:00"),VALUE(P56)<=VALUE("15:59")),"14:00 a 16:00",IF(AND(VALUE(P56)>=VALUE("16:00"),VALUE(P56)<=VALUE("17:59")),"16:00 a 18:00",IF(AND(VALUE(P56)>=VALUE("18:00"),VALUE(P56)<=VALUE("19:59")),"18:00 a 20:00",IF(AND(VALUE(P56)>=VALUE("20:00"),VALUE(P56)<=VALUE("21:59")),"20:00 a 22:00",IF(AND(VALUE(P56)>=VALUE("22:00"),VALUE(P56)<=VALUE("23:59")),"22:00 a 00:00","no corresponde")))))))))))) -> 10:00 a 12:00 | D56: MARTINEZ. R | E56: PEREZ, RAMON | F56: 1 | G56: VORPAGEL, SABRINA | H56: 918166 | I56: 46740296 | J56: CHACARITA | K56: COLABORACION | L56: PERSONA CAIDA/DEMANDA DE AUXILIO | N56: ALMAGRO O100 | O56: Almagro | P56: 0.49930556 | Q56: 0.50486111 | R56: 0.49930556 | S56: - | T56: - | U56: - | V56: - | W56: SE TOMA CONOCIMIENTO MEDIANTE CARTA SAE LLAMANTE INDICA QUE HABRIA UN MASCULINO CON PANTALN DE JEANS Y REMERA BLANCA, EL MISMO HABRIA TENIDO UNA PELEA, Y ESTARIA INCONCIENTE EN LA VIA PUBLICA.- CMU AMPLIA VERIFICADA LINEA DE TIEMPO DE LA CAMARA ALMAGRO O100 CAM03, A TRAVES DE ESTA SE VISUALIZO, SIENDO LAS 11:50 HORAS EL PASO DE UN MASCULINO DE ROPAS OSCURAS EL CUAL CIRCULABA ACOMPAÑADO DE DOS MENORES CON GUARDA POLVO ESCOLAR ESTAS TRES PERSONAS CIRCULABAN POR LA VEREDA DE ROCAMORA EN SENTIDO CONTRARIO AL TRANSITO POR DETRAS DE ELLOS CIRCULABA UN MASCULINO DE REMERA BLANCA MOCHILA Y PANTALON DE JEANS EL CUAL EN SU PASO APARENTEMENTE COMEZO A INCREPAR AL MASCULINO QUE CIRCULABA CON LOS MENORES DE EDAD PRODUCTO DE ESTO COMENZO UNA RIÑA ENTRE AMBOS SUJETOS, POSTERIOR A ESTA RIÑA EL MASCULINO DE REMERA COLOR NEGRA JUNTO CON LOS MENORES SE RETIRARON DEL LUGAR PERDIENDOSE DE LA VISUAL DE LA CAMARA SIENDO QUE EL MASCULINO DE REMERA COLOR BLANCA PERMANECIO TENDIDO SOBRE LA VEREDA.- PERSONAL INF SE ENTREVISTO CON EL MASCLINO EL CUAL SE ENCONTRABA BAJO LOS EFECTOS DEL ALCOHOL APARENTEMENTE- EL MISMO INDICO QUE SE HABIA CAIDO DE SU PROPIA ALTURA NO APORTA DATOS.- | X56: 0 | Y56: 0 | Z56: 0 | AA56: 5A | AB56: U | AC56: CARTA | AF56: CARTA FINALIZADA | AL56: =VLOOKUP(G56,Hoja2!P:Q,2,0) -> 40835168 | AM56: =IF(OR(Y56>0,X56>0),"IMPUTADO","NADA") -> NADA | AN56: =IF(AND(AM56="IMPUTADO",ISBLANK(M56)),"FALTO","NO") -> NO
A57: 45992 | B57: =IF(AND(VALUE(P57)>=VALUE("06:00"),VALUE(P57)<=VALUE("17:59")),"06 A 18","18 A 06") -> 06 A 18 | C57: =IF(AND(VALUE(P57)>=VALUE("00:00"),VALUE(P57)<=VALUE("01:59")),"00:00 a 02:00",IF(AND(VALUE(P57)>=VALUE("02:00"),VALUE(P57)<=VALUE("03:59")),"02:00 a 04:00",IF(AND(VALUE(P57)>=VALUE("04:00"),VALUE(P57)<=VALUE("05:59")),"04:00 a 06:00",IF(AND(VALUE(P57)>=VALUE("06:00"),VALUE(P57)<=VALUE("07:59")),"06:00 a 08:00",IF(AND(VALUE(P57)>=VALUE("08:00"),VALUE(P57)<=VALUE("09:59")),"08:00 a 10:00",IF(AND(VALUE(P57)>=VALUE("10:00"),VALUE(P57)<=VALUE("11:59")),"10:00 a 12:00",IF(AND(VALUE(P57)>=VALUE("12:00"),VALUE(P57)<=VALUE("13:59")),"12:00 a 14:00",IF(AND(VALUE(P57)>=VALUE("14:00"),VALUE(P57)<=VALUE("15:59")),"14:00 a 16:00",IF(AND(VALUE(P57)>=VALUE("16:00"),VALUE(P57)<=VALUE("17:59")),"16:00 a 18:00",IF(AND(VALUE(P57)>=VALUE("18:00"),VALUE(P57)<=VALUE("19:59")),"18:00 a 20:00",IF(AND(VALUE(P57)>=VALUE("20:00"),VALUE(P57)<=VALUE("21:59")),"20:00 a 22:00",IF(AND(VALUE(P57)>=VALUE("22:00"),VALUE(P57)<=VALUE("23:59")),"22:00 a 00:00","no corresponde")))))))))))) -> 10:00 a 12:00 | D57: MARTINEZ. R | E57: MEZA, GASTON | F57: 1 | G57: KRAKOVSKY, FLORENCIA | H57: 918221 | I57: 46740324 | J57: CMU 9 DE JULIO | K57: IDENTIFICACION DE PERSONAS | M57: PORT. ARMA NO CONVENCIONAL | N57: CONSTITUCION 55 | O57: Constitucion | P57: 0.49444444 | Q57: 0.52083333 | R57: 0.49722222 | V57: - | W57: SE VISUALIZA POR CAMARA CONSTITU.CION 55A UN MASCULINO CON APARENTEMENTE UN ARMA BLANCA . SE DA AVISO A COMANDO. ARRIBA PERSONAL POLICIAL DANDO CON EL MASCULINO EN MENCION. SE AMPLIA HT INF SE REALIZO CONSULTA CON LA UFLA ESTE AC DR MERCURIANI ACT POR EL ART 103 . SE PROCEDE AL SECUESTRO DE UN CUCHILLO TIPO CARNICERO SE LO NOTIFICA Y SE RETIRAN SIN NOVEDAD. | X57: 1 | Y57: 0 | Z57: 0 | AA57: 1C | AB57: U | AC57: MONITOREO | AE57: 1 CONTRAVENTOR | AF57: FINALIZA CON IMPUTADO/S | AL57: =VLOOKUP(G57,Hoja2!P:Q,2,0) -> 41290026 | AM57: =IF(OR(Y57>0,X57>0),"IMPUTADO","NADA") -> IMPUTADO | AN57: =IF(AND(AM57="IMPUTADO",ISBLANK(M57)),"FALTO","NO") -> NO
A58: 45992 | B58: =IF(AND(VALUE(P58)>=VALUE("06:00"),VALUE(P58)<=VALUE("17:59")),"06 A 18","18 A 06") -> 06 A 18 | C58: =IF(AND(VALUE(P58)>=VALUE("00:00"),VALUE(P58)<=VALUE("01:59")),"00:00 a 02:00",IF(AND(VALUE(P58)>=VALUE("02:00"),VALUE(P58)<=VALUE("03:59")),"02:00 a 04:00",IF(AND(VALUE(P58)>=VALUE("04:00"),VALUE(P58)<=VALUE("05:59")),"04:00 a 06:00",IF(AND(VALUE(P58)>=VALUE("06:00"),VALUE(P58)<=VALUE("07:59")),"06:00 a 08:00",IF(AND(VALUE(P58)>=VALUE("08:00"),VALUE(P58)<=VALUE("09:59")),"08:00 a 10:00",IF(AND(VALUE(P58)>=VALUE("10:00"),VALUE(P58)<=VALUE("11:59")),"10:00 a 12:00",IF(AND(VALUE(P58)>=VALUE("12:00"),VALUE(P58)<=VALUE("13:59")),"12:00 a 14:00",IF(AND(VALUE(P58)>=VALUE("14:00"),VALUE(P58)<=VALUE("15:59")),"14:00 a 16:00",IF(AND(VALUE(P58)>=VALUE("16:00"),VALUE(P58)<=VALUE("17:59")),"16:00 a 18:00",IF(AND(VALUE(P58)>=VALUE("18:00"),VALUE(P58)<=VALUE("19:59")),"18:00 a 20:00",IF(AND(VALUE(P58)>=VALUE("20:00"),VALUE(P58)<=VALUE("21:59")),"20:00 a 22:00",IF(AND(VALUE(P58)>=VALUE("22:00"),VALUE(P58)<=VALUE("23:59")),"22:00 a 00:00","no corresponde")))))))))))) -> 12:00 a 14:00 | D58: MARTINEZ. R | E58: GAUNA, MICAELA | F58: 1 | G58: VIALE, GISELA SOLEDAD | H58: 918226 | I58: 46740461 | J58: PUERTO MADERO | K58: COLABORACION | L58: IDENT. DE PERSONAS | N58: BARRACASO141 | O58: Barracas | P58: 0.52083333 | Q58: 0.55555556 | R58: 0.51041667 | V58: - | W58: SE TOMA CONOCIMIENTO MEDIANTE CARTA FEMENINO REFIERE QUE LE ESTARIAN ROBANDO SU CASA SE MANTIENE AL DENUNCIANTE EN LINEA A LOS FINES DE APORTAR MAYORES DATOS DEL HECHO. NO ASOCIAR ESTA CARTA HASTA FINALIZAR LA COMUNICACION CON EL LLAMANTE.INF SE POSEE CAMARA BARRACASO141 SE VISUALIZA PERSONAL EN EL LUGAR | X58: 0 | Y58: 0 | Z58: 0 | AA58: 4A | AB58: U | AC58: CARTA | AF58: CARTA FINALIZADA | AL58: =VLOOKUP(G58,Hoja2!P:Q,2,0) -> 31651283 | AM58: =IF(OR(Y58>0,X58>0),"IMPUTADO","NADA") -> NADA | AN58: =IF(AND(AM58="IMPUTADO",ISBLANK(M58)),"FALTO","NO") -> NO
A59: 45992 | B59: =IF(AND(VALUE(P59)>=VALUE("06:00"),VALUE(P59)<=VALUE("17:59")),"06 A 18","18 A 06") -> 06 A 18 | C59: =IF(AND(VALUE(P59)>=VALUE("00:00"),VALUE(P59)<=VALUE("01:59")),"00:00 a 02:00",IF(AND(VALUE(P59)>=VALUE("02:00"),VALUE(P59)<=VALUE("03:59")),"02:00 a 04:00",IF(AND(VALUE(P59)>=VALUE("04:00"),VALUE(P59)<=VALUE("05:59")),"04:00 a 06:00",IF(AND(VALUE(P59)>=VALUE("06:00"),VALUE(P59)<=VALUE("07:59")),"06:00 a 08:00",IF(AND(VALUE(P59)>=VALUE("08:00"),VALUE(P59)<=VALUE("09:59")),"08:00 a 10:00",IF(AND(VALUE(P59)>=VALUE("10:00"),VALUE(P59)<=VALUE("11:59")),"10:00 a 12:00",IF(AND(VALUE(P59)>=VALUE("12:00"),VALUE(P59)<=VALUE("13:59")),"12:00 a 14:00",IF(AND(VALUE(P59)>=VALUE("14:00"),VALUE(P59)<=VALUE("15:59")),"14:00 a 16:00",IF(AND(VALUE(P59)>=VALUE("16:00"),VALUE(P59)<=VALUE("17:59")),"16:00 a 18:00",IF(AND(VALUE(P59)>=VALUE("18:00"),VALUE(P59)<=VALUE("19:59")),"18:00 a 20:00",IF(AND(VALUE(P59)>=VALUE("20:00"),VALUE(P59)<=VALUE("21:59")),"20:00 a 22:00",IF(AND(VALUE(P59)>=VALUE("22:00"),VALUE(P59)<=VALUE("23:59")),"22:00 a 00:00","no corresponde")))))))))))) -> 12:00 a 14:00 | D59: MARTINEZ. R | E59: ARREGUI, FERNANDO | F59: 1 | G59: CAMAÑO, NAHUEL ELIAS | H59: 918161 | I59: 46740467 | J59: CHACARITA | K59: COLABORACION | L59: ROBO/HURTO | N59: ALMAGRO 46 | O59: Almagro | P59: 0.51180556 | Q59: 0.54791667 | R59: 0.51180556 | S59: - | T59: - | U59: - | V59: - | W59: SE TOMA CONOCIMIENTO MEDIANTE CARTA SAE LLAMANTE JESICA INDICA QUE LE ROBARON A SU SOBRINO EL CELULAR.-CMU AMPLIA AL MOMENTO MEDIANTE CAMARA ALMAGRO46 SE VISUALIZA PERSONAL ENTREVISTANDO A FEMENINOS.-CMU INF SE REALIZO LINEA DE TIEMPO DE CAMARA BEODO31CAM03 VISUALIZANDO 12:03 HS A MASCULINO DE GORRA OSCURA, ABRIGO NEGRO, BERMUDA NEGRA, CALZADO NEGRO EGRESAR DE ALTURA APROXIMADA Y CIRCULAR POR INDEPENDENCIA SENTIDO TREINTA Y TRES ORIENTALES DOBLANDO EN ESTA ULTIMA SENTIDO AGRELO, ULTIMO QTH VISUALIZADO POR VENEZUELA Y TREINTA Y TRES ORIENTALES 12:07 HS.-CMU INF SE CONTINUA MONITOREANDO MEDIANTE CAMARA BOEDO31 POR DESPERFECTOS EN CAMARA ALMAGRO46.-MOVIL INF SE ENTREVISTA CON LA DAMNIFICADA/ LLAMANTE QUIEN LE INDICO QUE MOMENTO EN QUE SE ENCONTRABA EN SU HABITACION FUE SORPRENDIA POR UNA PERSONA LA CUAL SERIA UN OCASIONAL CLIENTE- CON QUIEN HABIA ACORDADO UN ENCUENTRO Y COMO SE HIZO PRESENTE TIEMPO ANTES DE LO PACTADO LA DAMNIFICADA LE INDICO QUE AUN NO ERA MOMENTO, EL MASC SE OFUSCA LE EFECTUA ADEMANES DE COMO POEER UN ARMA DE FUEGO Y LE SUSTRAE UN CELULAR IPHONE 16 LO UNICO APORTADO.-MOVIL INF QUE LA DAMANIFICADA DESCONOCE COMO INGRESO, PERO QUE INGRESO CON SU LLAVE. ASIMISMO SE LECONSULTO POR LA VETIMENTA QUE PORTABA INDICANDO UNA EN PRIMERA INSTANCIA, LUEGO OTRA NO SIENDO CLARA CON LA INFORMACION APORTADA- SE AGUARDA LOS DATOS DE LA CONSULTA JUDICIAL.-MOVIL INF SE EFECTUO CONSULTA CON LA FISCALIA NAC EN LO CRIM Y CORR NRO 51 AC DRA NANCY OLIVIERI SEC UNICA AC DR MIGUEL INTERIORIZADO DE LOS PORMENORES DISPUSO ACT POR ROBO- NEGATIVO SERVICIOS- FEMENINO ILESO.- | X59: 0 | Y59: 0 | Z59: 0 | AA59: 5B | AB59: U | AC59: CARTA | AF59: CARTA FINALIZADA | AL59: =VLOOKUP(G59,Hoja2!P:Q,2,0) -> 44006317 | AM59: =IF(OR(Y59>0,X59>0),"IMPUTADO","NADA") -> NADA | AN59: =IF(AND(AM59="IMPUTADO",ISBLANK(M59)),"FALTO","NO") -> NO
A60: 45992 | B60: =IF(AND(VALUE(P60)>=VALUE("06:00"),VALUE(P60)<=VALUE("17:59")),"06 A 18","18 A 06") -> 06 A 18 | C60: =IF(AND(VALUE(P60)>=VALUE("00:00"),VALUE(P60)<=VALUE("01:59")),"00:00 a 02:00",IF(AND(VALUE(P60)>=VALUE("02:00"),VALUE(P60)<=VALUE("03:59")),"02:00 a 04:00",IF(AND(VALUE(P60)>=VALUE("04:00"),VALUE(P60)<=VALUE("05:59")),"04:00 a 06:00",IF(AND(VALUE(P60)>=VALUE("06:00"),VALUE(P60)<=VALUE("07:59")),"06:00 a 08:00",IF(AND(VALUE(P60)>=VALUE("08:00"),VALUE(P60)<=VALUE("09:59")),"08:00 a 10:00",IF(AND(VALUE(P60)>=VALUE("10:00"),VALUE(P60)<=VALUE("11:59")),"10:00 a 12:00",IF(AND(VALUE(P60)>=VALUE("12:00"),VALUE(P60)<=VALUE("13:59")),"12:00 a 14:00",IF(AND(VALUE(P60)>=VALUE("14:00"),VALUE(P60)<=VALUE("15:59")),"14:00 a 16:00",IF(AND(VALUE(P60)>=VALUE("16:00"),VALUE(P60)<=VALUE("17:59")),"16:00 a 18:00",IF(AND(VALUE(P60)>=VALUE("18:00"),VALUE(P60)<=VALUE("19:59")),"18:00 a 20:00",IF(AND(VALUE(P60)>=VALUE("20:00"),VALUE(P60)<=VALUE("21:59")),"20:00 a 22:00",IF(AND(VALUE(P60)>=VALUE("22:00"),VALUE(P60)<=VALUE("23:59")),"22:00 a 00:00","no corresponde")))))))))))) -> 12:00 a 14:00 | D60: MARTINEZ. R | E60: MOLINA, JOSE MANUEL | F60: 1 | G60: RIOS, GABRIELA | H60: 918202 | I60: 46740555 | J60: CHACARITA | K60: COLABORACION | L60: PERSONA CAIDA/DEMANDA DE AUXILIO | N60: BALVANERA 35 | O60: Balvanera | P60: 0.52222222 | Q60: 0.53611111 | R60: 0.52222222 | S60: 0.52777778 | T60: - | U60: - | V60: - | W60: SE TOMA CONOCIMIENTO MEDIANTE CARTA SAE ENTREVISTA SR BENJAMIN CEL 1540419263-REF QUE TIENE UNA FEM DISCPACITADA DESCOMPUESTA SOBRE UNIDAD YA QUE ES CHOFER DE LINEA 168.-CMU INFORMA QUE POSEE CAMARA BALVANERA 35, SE VERIFICA.-CMU AMPLIA SE VISUALIZA EL PERSONAL POLICIAL ASISTIENDO A UN FEMENINO EN LA VIA PUBLICA.-CMU INF SE VISUALIZA ARRIBO DE SAME AL LUGAR.-CMU INF SE RETIRA SAME SIN TRASLADO.-HT INF ARRIBO SAME INT 379 DE BASE CORDOBA, AC DE LA DRA MARIANA MADATIAS MN19419 ASISTE Y NO DERIVA CONTROL CLINICO.- | X60: 0 | Y60: 0 | Z60: 0 | AA60: 3A | AB60: U | AC60: CARTA | AF60: CARTA FINALIZADA | AL60: =VLOOKUP(G60,Hoja2!P:Q,2,0) -> 12841 | AM60: =IF(OR(Y60>0,X60>0),"IMPUTADO","NADA") -> NADA | AN60: =IF(AND(AM60="IMPUTADO",ISBLANK(M60)),"FALTO","NO") -> NO
A61: 45992 | B61: =IF(AND(VALUE(P61)>=VALUE("06:00"),VALUE(P61)<=VALUE("17:59")),"06 A 18","18 A 06") -> 06 A 18 | C61: =IF(AND(VALUE(P61)>=VALUE("00:00"),VALUE(P61)<=VALUE("01:59")),"00:00 a 02:00",IF(AND(VALUE(P61)>=VALUE("02:00"),VALUE(P61)<=VALUE("03:59")),"02:00 a 04:00",IF(AND(VALUE(P61)>=VALUE("04:00"),VALUE(P61)<=VALUE("05:59")),"04:00 a 06:00",IF(AND(VALUE(P61)>=VALUE("06:00"),VALUE(P61)<=VALUE("07:59")),"06:00 a 08:00",IF(AND(VALUE(P61)>=VALUE("08:00"),VALUE(P61)<=VALUE("09:59")),"08:00 a 10:00",IF(AND(VALUE(P61)>=VALUE("10:00"),VALUE(P61)<=VALUE("11:59")),"10:00 a 12:00",IF(AND(VALUE(P61)>=VALUE("12:00"),VALUE(P61)<=VALUE("13:59")),"12:00 a 14:00",IF(AND(VALUE(P61)>=VALUE("14:00"),VALUE(P61)<=VALUE("15:59")),"14:00 a 16:00",IF(AND(VALUE(P61)>=VALUE("16:00"),VALUE(P61)<=VALUE("17:59")),"16:00 a 18:00",IF(AND(VALUE(P61)>=VALUE("18:00"),VALUE(P61)<=VALUE("19:59")),"18:00 a 20:00",IF(AND(VALUE(P61)>=VALUE("20:00"),VALUE(P61)<=VALUE("21:59")),"20:00 a 22:00",IF(AND(VALUE(P61)>=VALUE("22:00"),VALUE(P61)<=VALUE("23:59")),"22:00 a 00:00","no corresponde")))))))))))) -> 12:00 a 14:00 | D61: MARTINEZ. R | E61: ALCOBA, DIEGO | F61: 1 | G61: ALMEDA, MICAELA | H61: 923502 | I61: 46740581 | J61: CHACARITA | K61: ROBO/HURTO | M61: ROBO/HURTO | N61: FLORESTA 62/44 | O61: Floresta | P61: 0.51666667 | Q61: 0.58680556 | R61: 0.51805556 | S61: - | T61: - | U61: - | V61: - | W61: SE VISUALIZA A TRES PERSONAS EN MODALIDAD PUNGA SUSTRAER PERTENECIAS. APOSTERIOR PERSONAL POLICIAL LOGRA DAR CON LAS PERSONAS. SE REALIZA CONSULTA CON EL JUZGADO NACIONAL EN LO CRIMINAL Nº29 A/C DRA.KARINA RODRIGUEZ, SECRETARIA Nº152 A/C DR.FEDERICO LADERATH QUIEN INTERIORIZADO DISPUSO LABRAR ACTUACIONES POR HURTO.- | X61: 0 | Y61: 3 | Z61: 0 | AA61: 10A | AB61: U | AC61: MONITOREO | AE61: 3 DETENIDOS | AF61: FINALIZA CON IMPUTADO/S | AL61: =VLOOKUP(G61,Hoja2!P:Q,2,0) -> 39664781 | AM61: =IF(OR(Y61>0,X61>0),"IMPUTADO","NADA") -> IMPUTADO | AN61: =IF(AND(AM61="IMPUTADO",ISBLANK(M61)),"FALTO","NO") -> NO
A62: 45992 | B62: =IF(AND(VALUE(P62)>=VALUE("06:00"),VALUE(P62)<=VALUE("17:59")),"06 A 18","18 A 06") -> 06 A 18 | C62: =IF(AND(VALUE(P62)>=VALUE("00:00"),VALUE(P62)<=VALUE("01:59")),"00:00 a 02:00",IF(AND(VALUE(P62)>=VALUE("02:00"),VALUE(P62)<=VALUE("03:59")),"02:00 a 04:00",IF(AND(VALUE(P62)>=VALUE("04:00"),VALUE(P62)<=VALUE("05:59")),"04:00 a 06:00",IF(AND(VALUE(P62)>=VALUE("06:00"),VALUE(P62)<=VALUE("07:59")),"06:00 a 08:00",IF(AND(VALUE(P62)>=VALUE("08:00"),VALUE(P62)<=VALUE("09:59")),"08:00 a 10:00",IF(AND(VALUE(P62)>=VALUE("10:00"),VALUE(P62)<=VALUE("11:59")),"10:00 a 12:00",IF(AND(VALUE(P62)>=VALUE("12:00"),VALUE(P62)<=VALUE("13:59")),"12:00 a 14:00",IF(AND(VALUE(P62)>=VALUE("14:00"),VALUE(P62)<=VALUE("15:59")),"14:00 a 16:00",IF(AND(VALUE(P62)>=VALUE("16:00"),VALUE(P62)<=VALUE("17:59")),"16:00 a 18:00",IF(AND(VALUE(P62)>=VALUE("18:00"),VALUE(P62)<=VALUE("19:59")),"18:00 a 20:00",IF(AND(VALUE(P62)>=VALUE("20:00"),VALUE(P62)<=VALUE("21:59")),"20:00 a 22:00",IF(AND(VALUE(P62)>=VALUE("22:00"),VALUE(P62)<=VALUE("23:59")),"22:00 a 00:00","no corresponde")))))))))))) -> 12:00 a 14:00 | D62: MARTINEZ. R | E62: PEREZ, RAMON | F62: 1 | G62: PENOVI, LUCAS | H62: 918316 | I62: 46740632 | J62: CHACARITA | K62: INCIDENCIA EN VIA PUBLICA | N62: P. AVELLANEDA 82 | O62: Parque Avellaneda | P62: 0.53055556 | Q62: 0.55347222 | R62: 0.61111111 | S62: - | T62: - | U62: - | V62: - | W62: SE TOMA CONOCIMIENTO MEDIANTE CARTA SAE DENUNCIANTE INDICA QUE HABRIA UN MASCULINO QUE ESTARIA ROMPIENDO TODO EL LOCAL, HABRIA MENORES CON LA DENUNCIANTE.-CMU INFORMA QUE POSEE CAMARA PARQUE AVELLANEDA 82, SE VERIFICA.-CMU AMPLIA AL MOMENTO NO SE LOGRA VISUALIZAR LO APORTADO, ASI MISMO SE VISUALIZA EL PERSONAL POLICIAL EN EL LUGAR.-CMU AMPLIA SE VERIFICO LINEA DE TIEMPO POR MEDIO DE CAMARA PARQUE AVELLANEDA 82 CAM03 VISUALIZANDO A LAS 12:32 HORAS UNA PERSONA DE PRENDA CLARA SUPERIOR Y PANTALON OSCURO EGRESAR DEL INTERIOR DE LO QUE APARENTEMENTE SERIA UN COMERCIO SIN LA PUERTA DE LA PERSIANA METALICA DESPLAZANDOSE UNOS METROS INGRESANDO A LO QUE SERIA UNA PUERTA DE CHAPA DE COLOR OSCURO, ASI MISMO NO SE LOGRA VISUALIZAR INCIDENCIA EN EL LUGAR SOLAMENTE LA PERSONA EGRESANDO DEL LUGAR.-CMU AMPLIA SE VISUALIZA EL PERSONAL POLICIAL CON UNA PERSONA DE SIMILARES CARACTERISTICAS.-SECTOR 2 INFORMA SE TRATO DE UNA DISCUSION DE PAREJA LA CUAL FUE SOLUCIONADA ANTES DEL ARRIBO DE ESTE PERSONAL.-CMU AMPLIA SE VISUALIZA EL RETIRO DE PERSONAL POLICIAL- | X62: 0 | Y62: 0 | Z62: 0 | AA62: 10C | AB62: U | AC62: CARTA | AF62: CARTA FINALIZADA | AL62: =VLOOKUP(G62,Hoja2!P:Q,2,0) -> 12141 | AM62: =IF(OR(Y62>0,X62>0),"IMPUTADO","NADA") -> NADA | AN62: =IF(AND(AM62="IMPUTADO",ISBLANK(M62)),"FALTO","NO") -> NO
A63: 45992 | B63: =IF(AND(VALUE(P63)>=VALUE("06:00"),VALUE(P63)<=VALUE("17:59")),"06 A 18","18 A 06") -> 06 A 18 | C63: =IF(AND(VALUE(P63)>=VALUE("00:00"),VALUE(P63)<=VALUE("01:59")),"00:00 a 02:00",IF(AND(VALUE(P63)>=VALUE("02:00"),VALUE(P63)<=VALUE("03:59")),"02:00 a 04:00",IF(AND(VALUE(P63)>=VALUE("04:00"),VALUE(P63)<=VALUE("05:59")),"04:00 a 06:00",IF(AND(VALUE(P63)>=VALUE("06:00"),VALUE(P63)<=VALUE("07:59")),"06:00 a 08:00",IF(AND(VALUE(P63)>=VALUE("08:00"),VALUE(P63)<=VALUE("09:59")),"08:00 a 10:00",IF(AND(VALUE(P63)>=VALUE("10:00"),VALUE(P63)<=VALUE("11:59")),"10:00 a 12:00",IF(AND(VALUE(P63)>=VALUE("12:00"),VALUE(P63)<=VALUE("13:59")),"12:00 a 14:00",IF(AND(VALUE(P63)>=VALUE("14:00"),VALUE(P63)<=VALUE("15:59")),"14:00 a 16:00",IF(AND(VALUE(P63)>=VALUE("16:00"),VALUE(P63)<=VALUE("17:59")),"16:00 a 18:00",IF(AND(VALUE(P63)>=VALUE("18:00"),VALUE(P63)<=VALUE("19:59")),"18:00 a 20:00",IF(AND(VALUE(P63)>=VALUE("20:00"),VALUE(P63)<=VALUE("21:59")),"20:00 a 22:00",IF(AND(VALUE(P63)>=VALUE("22:00"),VALUE(P63)<=VALUE("23:59")),"22:00 a 00:00","no corresponde")))))))))))) -> 12:00 a 14:00 | D63: MARTINEZ. R | E63: MARTINEZ, VERONICA | F63: 1 | G63: VILLEGAS, RODRIGO | H63: 923798 | I63: 46740712 | J63: VILLA LUGANO | K63: PERSONA CAIDA | N63: LINIERS 82 | O63: Liniers | P63: 0.52986111 | Q63: 0.5625 | R63: 0.53125 | S63: 0.55625 | T63: - | U63: - | V63: - | W63: SE TOMA CONOCIMIENTO MEDIANTE CARTA SAE POR UNA PERSONA QUE SE ENCUENTRA CON ATAQUE EN VIA PUBLICA, AL MOMENTO DE TOMAR LC AMARA SE VISUALIZA A UNA PERSONA RECOSTADA EN LA VEREDA, ARRIBA PERSONAL POLICIAL,- SAME INT 385 AC DR BARRETO MN 195705 ASISTE Y NO DERIVA CON DIAG CONTROL CLINICO | X63: 0 | Y63: 0 | Z63: 0 | AA63: 9B | AB63: U | AC63: CARTA | AF63: CARTA FINALIZADA | AL63: =VLOOKUP(G63,Hoja2!P:Q,2,0) -> 37989460 | AM63: =IF(OR(Y63>0,X63>0),"IMPUTADO","NADA") -> NADA | AN63: =IF(AND(AM63="IMPUTADO",ISBLANK(M63)),"FALTO","NO") -> NO
A64: 45992 | B64: =IF(AND(VALUE(P64)>=VALUE("06:00"),VALUE(P64)<=VALUE("17:59")),"06 A 18","18 A 06") -> 06 A 18 | C64: =IF(AND(VALUE(P64)>=VALUE("00:00"),VALUE(P64)<=VALUE("01:59")),"00:00 a 02:00",IF(AND(VALUE(P64)>=VALUE("02:00"),VALUE(P64)<=VALUE("03:59")),"02:00 a 04:00",IF(AND(VALUE(P64)>=VALUE("04:00"),VALUE(P64)<=VALUE("05:59")),"04:00 a 06:00",IF(AND(VALUE(P64)>=VALUE("06:00"),VALUE(P64)<=VALUE("07:59")),"06:00 a 08:00",IF(AND(VALUE(P64)>=VALUE("08:00"),VALUE(P64)<=VALUE("09:59")),"08:00 a 10:00",IF(AND(VALUE(P64)>=VALUE("10:00"),VALUE(P64)<=VALUE("11:59")),"10:00 a 12:00",IF(AND(VALUE(P64)>=VALUE("12:00"),VALUE(P64)<=VALUE("13:59")),"12:00 a 14:00",IF(AND(VALUE(P64)>=VALUE("14:00"),VALUE(P64)<=VALUE("15:59")),"14:00 a 16:00",IF(AND(VALUE(P64)>=VALUE("16:00"),VALUE(P64)<=VALUE("17:59")),"16:00 a 18:00",IF(AND(VALUE(P64)>=VALUE("18:00"),VALUE(P64)<=VALUE("19:59")),"18:00 a 20:00",IF(AND(VALUE(P64)>=VALUE("20:00"),VALUE(P64)<=VALUE("21:59")),"20:00 a 22:00",IF(AND(VALUE(P64)>=VALUE("22:00"),VALUE(P64)<=VALUE("23:59")),"22:00 a 00:00","no corresponde")))))))))))) -> 12:00 a 14:00 | D64: MARTINEZ. R | E64: GAUNA, MICAELA | F64: 1 | G64: MOLINAS, ANALIA | H64: 926367 | I64: 46740746 | J64: PUERTO MADERO | K64: SUICIDIO/TENTATIVA DE SUICIDIO | N64: RECOLETAO132/136 | O64: Recoleta | P64: 0.53333333 | Q64: 0.81666667 | R64: 0.54722222 | V64: - | W64: SE TOMA CONOCIMIENTO MEDIANTE CARTA SAE LLAMANTE REFIERE QUE EL HERMANO LE DIJO QUE SE QUERIA QUITAR LA VIDA PEGANDOSE UN TIRO. MASCULINO DE 53 AÑOS.SE POSEE CAMARA RECOLETAO132/136 OP MASC SIN VIDA EN INGRESO A ESTACIONAMIENTO, LAS ARTERIAS GUEMES Y BUSITAMANTE CORTADA POR CM TAMBIEN SANTA FE Y BUSTAMANTE CORTADO | X64: 0 | Y64: 0 | Z64: 0 | AA64: 2B | AB64: U | AC64: CARTA | AF64: CARTA FINALIZADA | AL64: =VLOOKUP(G64,Hoja2!P:Q,2,0) -> 94243803 | AM64: =IF(OR(Y64>0,X64>0),"IMPUTADO","NADA") -> NADA | AN64: =IF(AND(AM64="IMPUTADO",ISBLANK(M64)),"FALTO","NO") -> NO
A65: 45992 | B65: =IF(AND(VALUE(P65)>=VALUE("06:00"),VALUE(P65)<=VALUE("17:59")),"06 A 18","18 A 06") -> 06 A 18 | C65: =IF(AND(VALUE(P65)>=VALUE("00:00"),VALUE(P65)<=VALUE("01:59")),"00:00 a 02:00",IF(AND(VALUE(P65)>=VALUE("02:00"),VALUE(P65)<=VALUE("03:59")),"02:00 a 04:00",IF(AND(VALUE(P65)>=VALUE("04:00"),VALUE(P65)<=VALUE("05:59")),"04:00 a 06:00",IF(AND(VALUE(P65)>=VALUE("06:00"),VALUE(P65)<=VALUE("07:59")),"06:00 a 08:00",IF(AND(VALUE(P65)>=VALUE("08:00"),VALUE(P65)<=VALUE("09:59")),"08:00 a 10:00",IF(AND(VALUE(P65)>=VALUE("10:00"),VALUE(P65)<=VALUE("11:59")),"10:00 a 12:00",IF(AND(VALUE(P65)>=VALUE("12:00"),VALUE(P65)<=VALUE("13:59")),"12:00 a 14:00",IF(AND(VALUE(P65)>=VALUE("14:00"),VALUE(P65)<=VALUE("15:59")),"14:00 a 16:00",IF(AND(VALUE(P65)>=VALUE("16:00"),VALUE(P65)<=VALUE("17:59")),"16:00 a 18:00",IF(AND(VALUE(P65)>=VALUE("18:00"),VALUE(P65)<=VALUE("19:59")),"18:00 a 20:00",IF(AND(VALUE(P65)>=VALUE("20:00"),VALUE(P65)<=VALUE("21:59")),"20:00 a 22:00",IF(AND(VALUE(P65)>=VALUE("22:00"),VALUE(P65)<=VALUE("23:59")),"22:00 a 00:00","no corresponde")))))))))))) -> 12:00 a 14:00 | D65: MARTINEZ. R | E65: PEREZ, RAMON | F65: 1 | G65: VORPAGEL, SABRINA | H65: 918517 | I65: 46740853 | J65: CHACARITA | K65: IDENTIFICACION DE PERSONAS | N65: FLORES 58 | O65: Flores | P65: 0.53819444 | Q65: 0.53888889 | S65: - | T65: - | U65: - | V65: - | W65: SE TOMA CONOCIMIENTO MEDIANTE CARTA SAE DENUNCIANTE REFIERE QUE A UN MASCULINO LE ROBARON SU COCHE. SE TRATARIA DE UN SOLO AUTOR. EL VEHCIULO ROBADO ES UN PEUGEOUT 504 COLOR BORDO DOMINIO: SBZ374. AGUARDA Y AMPLIA.-CMU SE VERIFICO CAMARA FLORESO111CAM02 EMPLAZADA EN FDEZ DE LA CRUZ Y CHARRUA. SIENDO LAS 12:55:31HS SE VISUALIZO EL PASO DE UN VEHICULO DE SIMILARES CARACTERISTICAS. PASAR POR CHARRUA SENTIDO A FERNANDEZ DE LA CRUZ. HACIA AV PERITO MORENO.-CMU AMPLIA A SI MISMO SE VERIFICO CAMARA FLORES58CAM02 12:56HS SE VISUALIZO EL PASO DEL VEHICULO POR FERNANDEZ DE LA CRUZ. DOBLANDO POR PERITO MORENO SENTIDO DEL BANCO CENTENERA.-M 904 FISCALIA 61 AC DR FERNANDO SEC UNICA ALONSO ACT POR HURTO AUTOMOTOR | X65: 0 | Y65: 0 | Z65: 0 | AA65: 7A | AB65: U | AC65: CARTA | AF65: CARTA FINALIZADA | AL65: =VLOOKUP(G65,Hoja2!P:Q,2,0) -> 40835168 | AM65: =IF(OR(Y65>0,X65>0),"IMPUTADO","NADA") -> NADA | AN65: =IF(AND(AM65="IMPUTADO",ISBLANK(M65)),"FALTO","NO") -> NO
A66: 45992 | B66: =IF(AND(VALUE(P66)>=VALUE("06:00"),VALUE(P66)<=VALUE("17:59")),"06 A 18","18 A 06") -> 06 A 18 | C66: =IF(AND(VALUE(P66)>=VALUE("00:00"),VALUE(P66)<=VALUE("01:59")),"00:00 a 02:00",IF(AND(VALUE(P66)>=VALUE("02:00"),VALUE(P66)<=VALUE("03:59")),"02:00 a 04:00",IF(AND(VALUE(P66)>=VALUE("04:00"),VALUE(P66)<=VALUE("05:59")),"04:00 a 06:00",IF(AND(VALUE(P66)>=VALUE("06:00"),VALUE(P66)<=VALUE("07:59")),"06:00 a 08:00",IF(AND(VALUE(P66)>=VALUE("08:00"),VALUE(P66)<=VALUE("09:59")),"08:00 a 10:00",IF(AND(VALUE(P66)>=VALUE("10:00"),VALUE(P66)<=VALUE("11:59")),"10:00 a 12:00",IF(AND(VALUE(P66)>=VALUE("12:00"),VALUE(P66)<=VALUE("13:59")),"12:00 a 14:00",IF(AND(VALUE(P66)>=VALUE("14:00"),VALUE(P66)<=VALUE("15:59")),"14:00 a 16:00",IF(AND(VALUE(P66)>=VALUE("16:00"),VALUE(P66)<=VALUE("17:59")),"16:00 a 18:00",IF(AND(VALUE(P66)>=VALUE("18:00"),VALUE(P66)<=VALUE("19:59")),"18:00 a 20:00",IF(AND(VALUE(P66)>=VALUE("20:00"),VALUE(P66)<=VALUE("21:59")),"20:00 a 22:00",IF(AND(VALUE(P66)>=VALUE("22:00"),VALUE(P66)<=VALUE("23:59")),"22:00 a 00:00","no corresponde")))))))))))) -> 12:00 a 14:00 | D66: MARTINEZ. R | E66: MARTINEZ, VERONICA | F66: 1 | G66: VILLEGAS, RODRIGO | H66: 923801 | I66: 46740966 | J66: VILLA LUGANO | K66: COLABORACION | L66: PORTACION DE ARMA DE FUEGO | M66: TENENCIA/USO ARMA DE GUERRA S/A | N66: V. LUGANOO 123 / CAM 02 Y 03 | O66: Villa Lugano | P66: 0.55069444 | Q66: 0.59444444 | R66: 0.55069444 | S66: - | T66: - | U66: - | V66: - | W66: SE TOMA CONOCIMIENTO MEDIANTE FRECUENCIA CONVENCIONAL POR UN MASC CON ARMA DE FUEGO , SE BRINDA APOYO OPTICO A PEROSNAL POLICIAL, SE APORTA LINEA DE TIEMPO ,- M 608A INF SE PROCEDE A A DETENCION DEL MASCULINO A EL CUAL SE LE SECUESTRA A PARTE DEL ARMA DE FUEGO M 1.2 GRAMOS SUSTANCIA SIMIL MARIHUANA Y UN CERTIFICADO DE DISCAPACIDAD EL CUAL NO LE CORRESPONDE SE REALIZA CONSULTA CON LA UFLA SUR AC DRA FLORENCIA BASIADONE SECRETARIA UNICA SE LABRAN ACT POR ART 189 BIS INCISO 2 ART 14 INSCISO 2 INFRACCION A LA LEY 23737 | X66: 0 | Y66: 1 | Z66: 0 | AA66: 8A | AB66: U | AC66: FRECUENCIA | AE66: 1 DETENIDO | AF66: COLABORACION CON IMPUTADO/S | AI66: LEY 23737 | AL66: =VLOOKUP(G66,Hoja2!P:Q,2,0) -> 37989460 | AM66: =IF(OR(Y66>0,X66>0),"IMPUTADO","NADA") -> IMPUTADO | AN66: =IF(AND(AM66="IMPUTADO",ISBLANK(M66)),"FALTO","NO") -> NO
A67: 45992 | B67: =IF(AND(VALUE(P67)>=VALUE("06:00"),VALUE(P67)<=VALUE("17:59")),"06 A 18","18 A 06") -> 06 A 18 | C67: =IF(AND(VALUE(P67)>=VALUE("00:00"),VALUE(P67)<=VALUE("01:59")),"00:00 a 02:00",IF(AND(VALUE(P67)>=VALUE("02:00"),VALUE(P67)<=VALUE("03:59")),"02:00 a 04:00",IF(AND(VALUE(P67)>=VALUE("04:00"),VALUE(P67)<=VALUE("05:59")),"04:00 a 06:00",IF(AND(VALUE(P67)>=VALUE("06:00"),VALUE(P67)<=VALUE("07:59")),"06:00 a 08:00",IF(AND(VALUE(P67)>=VALUE("08:00"),VALUE(P67)<=VALUE("09:59")),"08:00 a 10:00",IF(AND(VALUE(P67)>=VALUE("10:00"),VALUE(P67)<=VALUE("11:59")),"10:00 a 12:00",IF(AND(VALUE(P67)>=VALUE("12:00"),VALUE(P67)<=VALUE("13:59")),"12:00 a 14:00",IF(AND(VALUE(P67)>=VALUE("14:00"),VALUE(P67)<=VALUE("15:59")),"14:00 a 16:00",IF(AND(VALUE(P67)>=VALUE("16:00"),VALUE(P67)<=VALUE("17:59")),"16:00 a 18:00",IF(AND(VALUE(P67)>=VALUE("18:00"),VALUE(P67)<=VALUE("19:59")),"18:00 a 20:00",IF(AND(VALUE(P67)>=VALUE("20:00"),VALUE(P67)<=VALUE("21:59")),"20:00 a 22:00",IF(AND(VALUE(P67)>=VALUE("22:00"),VALUE(P67)<=VALUE("23:59")),"22:00 a 00:00","no corresponde")))))))))))) -> 12:00 a 14:00 | D67: MARTINEZ. R | E67: ARREGUI, FERNANDO | F67: 1 | G67: SEGOVIA, NOELIA | H67: 926188 | I67: 46741049 | J67: CHACARITA | K67: COLABORACION | L67: CHOQUE | N67: PALERMO 69 | O67: Palermo | P67: 0.55694444 | Q67: 0.62777778 | R67: 0.56527778 | V67: - | W67: SE TOMA CONOCIMIENTO MEDIANTE CARTA SAE MASCULINO REFIERE QUE HABRIA UN CHQOUE ENTRE DOS MOTOS UNO DE LOS MASCULINO ESTARIA EN EL SUELO Y UNA FEMENINO CON HERIDAS EN LAS PIERNAS.- 614 SE REALIZA CONSULTA CON LA UFLA NORTE DRA GARCIA ALEJANDRA QUIE DISPUSO ACT POR LESIONES LEVES. NEGATIVO PERSONA DE RELEVANCIA - 614 C IMFORMA QUE MOTO QUEDA A RESGUARDO EN DEPENDENCIA | X67: 0 | Y67: 0 | Z67: 0 | AA67: 14C | AB67: U | AC67: CARTA | AE67: 1 TRASLADO SAME | AF67: CARTA FINALIZADA | AL67: =VLOOKUP(G67,Hoja2!P:Q,2,0) -> 11677 | AM67: =IF(OR(Y67>0,X67>0),"IMPUTADO","NADA") -> NADA | AN67: =IF(AND(AM67="IMPUTADO",ISBLANK(M67)),"FALTO","NO") -> NO
A68: 45992 | B68: =IF(AND(VALUE(P68)>=VALUE("06:00"),VALUE(P68)<=VALUE("17:59")),"06 A 18","18 A 06") -> 06 A 18 | C68: =IF(AND(VALUE(P68)>=VALUE("00:00"),VALUE(P68)<=VALUE("01:59")),"00:00 a 02:00",IF(AND(VALUE(P68)>=VALUE("02:00"),VALUE(P68)<=VALUE("03:59")),"02:00 a 04:00",IF(AND(VALUE(P68)>=VALUE("04:00"),VALUE(P68)<=VALUE("05:59")),"04:00 a 06:00",IF(AND(VALUE(P68)>=VALUE("06:00"),VALUE(P68)<=VALUE("07:59")),"06:00 a 08:00",IF(AND(VALUE(P68)>=VALUE("08:00"),VALUE(P68)<=VALUE("09:59")),"08:00 a 10:00",IF(AND(VALUE(P68)>=VALUE("10:00"),VALUE(P68)<=VALUE("11:59")),"10:00 a 12:00",IF(AND(VALUE(P68)>=VALUE("12:00"),VALUE(P68)<=VALUE("13:59")),"12:00 a 14:00",IF(AND(VALUE(P68)>=VALUE("14:00"),VALUE(P68)<=VALUE("15:59")),"14:00 a 16:00",IF(AND(VALUE(P68)>=VALUE("16:00"),VALUE(P68)<=VALUE("17:59")),"16:00 a 18:00",IF(AND(VALUE(P68)>=VALUE("18:00"),VALUE(P68)<=VALUE("19:59")),"18:00 a 20:00",IF(AND(VALUE(P68)>=VALUE("20:00"),VALUE(P68)<=VALUE("21:59")),"20:00 a 22:00",IF(AND(VALUE(P68)>=VALUE("22:00"),VALUE(P68)<=VALUE("23:59")),"22:00 a 00:00","no corresponde")))))))))))) -> 12:00 a 14:00 | D68: MARTINEZ. R | E68: MARTINEZ, VERONICA | F68: 1 | G68: ANTUNEZ, NICOLAS | H68: 923802 | I68: 46741170 | J68: VILLA LUGANO | K68: ROBO/HURTO | N68: LINIERS 07 CAM 02 / LINIERS 26 | O68: Liniers | P68: 0.57152778 | Q68: 0.58333333 | R68: 0.57638889 | S68: - | T68: - | U68: - | V68: - | W68: SE TOMA CONOCIMIENOT MEIDANTE FRECUENCIA CONVENCIONAL POR PERSONAL POLICIAL IRRADIANDO ALERTA DE MTOOVEHICULO BITRIPULADO ACUSADO DE ILICITO.- SE VERIFICA LINEA D ETIEMPO SE APORTA ROBO.- PERSONAL POLICIAL IDENTIFICANDOA UN MOTOVHEICULO SIMILAR PROXIMO AL LUGAR .- SE COMUNICA VIA QSO OFICIAL PRIMERO LP 28361 PEREYRA INF EL HECHO INICIA EN IBARROLA Y SUAREZ UN MOTOVEHICULO SUSTRAE UN CELULAR A UN FEMENINO PERSONA DE PREVENCION EN ESE MOMENTO EL HT DE PARADA VISUAIZA EL HECHO Y EMPREDEN EL SEGUIMIENTO POR IBARROLA SENTIDO CONTRARIO AL TRANSITO EL MOTOVEHICILO DOBLA EN CARUHE Y LO PIERDE DE VISTA // , MOMENTO DESPUES UN SEGUNDO EFECTIVO DE PARADA VISUALIZA OTRO HECHO DONDE EL MISMO CONDUCTOR DE MOTOVEHICULO INTENTA SUSTRAER UN PAQUETE QUE UN MASCULINO EL CUAL DECENDIA DE UNA CAMIONETA EN UN FORCEJEO EL DAMNIFICADO SE CAE Y SE PROPINA EL GOLPE EN EL ROSTRO// MOTOVEHICULO SE DA A LA FUGA UN TRASEUNTE REALIZA UN SEGUIMIENTO Y CONDUCTOR TIRA LA CAJA SUSTRAIDA // SE REALIZA CONSULTA CON LA FISCALIA CRIMINAL Y CORRECIONAL N 10 AC DR ADRIAN GENTILE SECRETARIA AC DR JUAN JOSE TAGUADA ,QUIEN DISPUSO ACT POR ROBO / SIN SERVICIOS . ELEMENTO SUSTRAIDO CELULAR MARCA MOTOROLA MODELO G15 COLOR ROSA // | X68: 0 | Y68: 0 | Z68: 0 | AA68: 9B | AB68: U | AC68: FRECUENCIA | AF68: CARTA FINALIZADA | AL68: =VLOOKUP(G68,Hoja2!P:Q,2,0) -> 44259552 | AM68: =IF(OR(Y68>0,X68>0),"IMPUTADO","NADA") -> NADA | AN68: =IF(AND(AM68="IMPUTADO",ISBLANK(M68)),"FALTO","NO") -> NO
A69: 45992 | B69: =IF(AND(VALUE(P69)>=VALUE("06:00"),VALUE(P69)<=VALUE("17:59")),"06 A 18","18 A 06") -> 06 A 18 | C69: =IF(AND(VALUE(P69)>=VALUE("00:00"),VALUE(P69)<=VALUE("01:59")),"00:00 a 02:00",IF(AND(VALUE(P69)>=VALUE("02:00"),VALUE(P69)<=VALUE("03:59")),"02:00 a 04:00",IF(AND(VALUE(P69)>=VALUE("04:00"),VALUE(P69)<=VALUE("05:59")),"04:00 a 06:00",IF(AND(VALUE(P69)>=VALUE("06:00"),VALUE(P69)<=VALUE("07:59")),"06:00 a 08:00",IF(AND(VALUE(P69)>=VALUE("08:00"),VALUE(P69)<=VALUE("09:59")),"08:00 a 10:00",IF(AND(VALUE(P69)>=VALUE("10:00"),VALUE(P69)<=VALUE("11:59")),"10:00 a 12:00",IF(AND(VALUE(P69)>=VALUE("12:00"),VALUE(P69)<=VALUE("13:59")),"12:00 a 14:00",IF(AND(VALUE(P69)>=VALUE("14:00"),VALUE(P69)<=VALUE("15:59")),"14:00 a 16:00",IF(AND(VALUE(P69)>=VALUE("16:00"),VALUE(P69)<=VALUE("17:59")),"16:00 a 18:00",IF(AND(VALUE(P69)>=VALUE("18:00"),VALUE(P69)<=VALUE("19:59")),"18:00 a 20:00",IF(AND(VALUE(P69)>=VALUE("20:00"),VALUE(P69)<=VALUE("21:59")),"20:00 a 22:00",IF(AND(VALUE(P69)>=VALUE("22:00"),VALUE(P69)<=VALUE("23:59")),"22:00 a 00:00","no corresponde")))))))))))) -> 12:00 a 14:00 | D69: MARTINEZ. R | E69: PEREZ, RAMON | F69: 1 | G69: PENOVI, LUCAS | H69: 918151 | I69: 46741182 | J69: CHACARITA | K69: COLABORACION | L69: CHOQUE | M69: LESIONES | N69: V. DEVOTO O109 | O69: Villa Devoto | P69: 0.58055556 | Q69: 0.66666667 | R69: 0.58055556 | S69: 0.58333333 | T69: - | U69: - | V69: - | W69: SE TOMA CONOCIMIENTO POR CARTA SOBRE UN VEHICULO ARROJA AL PERSONAL PERSONAL POLICIA DOLOR PIERNA, AL TOMAR LA CAMARA SE VISUALIZA A UN PERSONAL POLICIAL MASCULINO SENTADO. EN EL LUGAR YA SE ENCUENTRA PERSONAL POLICIAL JUNTO AL MISMO,SE APORTA LINEA DE TIEMPO ARRIBA PERSONAL POLICIAL Y SAME QUIEN ASISTE Y TRASLADA 611B INF ARRIBO SAME INT 384 DEL HTAL ZUBIZARRETA AC DRA BOLAÑOS MN 177852 QUIEN ASISTE Y DERIVA A PERSONAL POLICIAL CON DIAG TRAUMATISMO PIERNA DERECHA.-611 INF SE REALIZA CONSULTA CON EL AREA DE FLAGRANCIA OESTE AC DR GRADELLA SEC UNICA DR GOTUZZO, DISPUSO SE ENVIE PERSONAL DE PFA PARA REALIZAR CONSULTA.- 611 INF SE REALIZA CONSULTA CON EL AREA DE FLAGRANCIA OESTE AC DR GRADELLA SEC UNICA DR GOTUZZO, DISPUSO SE ENVIE PERSONAL DE PFA PARA REALIZAR CONSULTA | X69: 0 | Y69: 1 | Z69: 1 | AA69: 11B | AB69: U | AC69: CARTA | AE69: 1 TRASLADO SAME | AF69: COLABORACION CON IMPUTADO/S | AG69: CIERRAN COMO CARTA FINALIZADA | AH69: NO CARGAN IMPUTADO - NO CARGAN ORIGEN | AL69: =VLOOKUP(G69,Hoja2!P:Q,2,0) -> 12141 | AM69: =IF(OR(Y69>0,X69>0),"IMPUTADO","NADA") -> IMPUTADO | AN69: =IF(AND(AM69="IMPUTADO",ISBLANK(M69)),"FALTO","NO") -> NO
A70: 45992 | B70: =IF(AND(VALUE(P70)>=VALUE("06:00"),VALUE(P70)<=VALUE("17:59")),"06 A 18","18 A 06") -> 06 A 18 | C70: =IF(AND(VALUE(P70)>=VALUE("00:00"),VALUE(P70)<=VALUE("01:59")),"00:00 a 02:00",IF(AND(VALUE(P70)>=VALUE("02:00"),VALUE(P70)<=VALUE("03:59")),"02:00 a 04:00",IF(AND(VALUE(P70)>=VALUE("04:00"),VALUE(P70)<=VALUE("05:59")),"04:00 a 06:00",IF(AND(VALUE(P70)>=VALUE("06:00"),VALUE(P70)<=VALUE("07:59")),"06:00 a 08:00",IF(AND(VALUE(P70)>=VALUE("08:00"),VALUE(P70)<=VALUE("09:59")),"08:00 a 10:00",IF(AND(VALUE(P70)>=VALUE("10:00"),VALUE(P70)<=VALUE("11:59")),"10:00 a 12:00",IF(AND(VALUE(P70)>=VALUE("12:00"),VALUE(P70)<=VALUE("13:59")),"12:00 a 14:00",IF(AND(VALUE(P70)>=VALUE("14:00"),VALUE(P70)<=VALUE("15:59")),"14:00 a 16:00",IF(AND(VALUE(P70)>=VALUE("16:00"),VALUE(P70)<=VALUE("17:59")),"16:00 a 18:00",IF(AND(VALUE(P70)>=VALUE("18:00"),VALUE(P70)<=VALUE("19:59")),"18:00 a 20:00",IF(AND(VALUE(P70)>=VALUE("20:00"),VALUE(P70)<=VALUE("21:59")),"20:00 a 22:00",IF(AND(VALUE(P70)>=VALUE("22:00"),VALUE(P70)<=VALUE("23:59")),"22:00 a 00:00","no corresponde")))))))))))) -> 12:00 a 14:00 | D70: MARTINEZ. R | E70: MOLINA, JOSE MANUEL | F70: 1 | G70: OLIVARES, SABRINA GISELLE | H70: 918435 | I70: 46741241 | J70: CHACARITA | K70: COLABORACION | L70: SUICIDIO/TTVA. SUICIDIO | M70: HOMICIDIO/TTVA. HOMICIDIO | N70: OLLEROS CAM04 | O70: Subte | P70: 0.57708333 | Q70: 0.60833333 | R70: 0.58263889 | S70: 0.58263889 | T70: 0.58263889 | U70: - | V70: - | W70: SIENDO LAS 13:51HS SE TOMA CONOCIMIENTO A TRAVES DE CARTA SAE 46741241 SOBRE UN MASCULINO QUE SE HABRIA ARROJADO A LAS VIAS EN ESTACION OLLEROS DE LA LINEA D DE SUBTE CON SENTIDO A CATEDRAL. SE TOMA CAMARA OLLEROSD01 Y CAM04 Y SE VISUALIZA A PERSONAL DE SAME Y BOMBEROS TRABAJANDO EN EL LUGAR. SE BRINDA APOYO OPTICO. SE REALIZA LINEA DE TIEMPO Y SE OBSERVA AL MASCULINO ARROJARSE A LAS VIAS A LAS 13:48HS. A LAS 14:10HS LO RETIRAN DE ABAJO DE LA FORMACION Y SE DIRIGEN A SUPERFICIE SIENDO VISUALIZADO POR CAMARA PALERMOO114 EMPLAZADA EN CABILDO Y OLLEROS. A LAS 14:12HS TRASLADAN AL MASCULINO. SE AMPLIA POR CARTA SAE JOSE HERN INF - SE TOMO CONTACTO CON FIS CRIM CONT NRO 29 DOC LUCIO HERRERA SEC UNICA AC DOC PAULA GONZALEZ. ACTUACIONES POR TENTATIVA DE SUICIDIO | X70: 0 | Y70: 1 | Z70: 1 | AA70: 14B | AB70: S | AC70: CARTA | AE70: 1 TRASLADO SAME | AF70: COLABORACION CON IMPUTADO/S | AG70: CIERRAN COMO CARTA FINALIZADA | AH70: NO CARGAN IMPUTADO - | AL70: =VLOOKUP(G70,Hoja2!P:Q,2,0) -> 12899 | AM70: =IF(OR(Y70>0,X70>0),"IMPUTADO","NADA") -> IMPUTADO | AN70: =IF(AND(AM70="IMPUTADO",ISBLANK(M70)),"FALTO","NO") -> NO
A71: 45992 | B71: =IF(AND(VALUE(P71)>=VALUE("06:00"),VALUE(P71)<=VALUE("17:59")),"06 A 18","18 A 06") -> 06 A 18 | C71: =IF(AND(VALUE(P71)>=VALUE("00:00"),VALUE(P71)<=VALUE("01:59")),"00:00 a 02:00",IF(AND(VALUE(P71)>=VALUE("02:00"),VALUE(P71)<=VALUE("03:59")),"02:00 a 04:00",IF(AND(VALUE(P71)>=VALUE("04:00"),VALUE(P71)<=VALUE("05:59")),"04:00 a 06:00",IF(AND(VALUE(P71)>=VALUE("06:00"),VALUE(P71)<=VALUE("07:59")),"06:00 a 08:00",IF(AND(VALUE(P71)>=VALUE("08:00"),VALUE(P71)<=VALUE("09:59")),"08:00 a 10:00",IF(AND(VALUE(P71)>=VALUE("10:00"),VALUE(P71)<=VALUE("11:59")),"10:00 a 12:00",IF(AND(VALUE(P71)>=VALUE("12:00"),VALUE(P71)<=VALUE("13:59")),"12:00 a 14:00",IF(AND(VALUE(P71)>=VALUE("14:00"),VALUE(P71)<=VALUE("15:59")),"14:00 a 16:00",IF(AND(VALUE(P71)>=VALUE("16:00"),VALUE(P71)<=VALUE("17:59")),"16:00 a 18:00",IF(AND(VALUE(P71)>=VALUE("18:00"),VALUE(P71)<=VALUE("19:59")),"18:00 a 20:00",IF(AND(VALUE(P71)>=VALUE("20:00"),VALUE(P71)<=VALUE("21:59")),"20:00 a 22:00",IF(AND(VALUE(P71)>=VALUE("22:00"),VALUE(P71)<=VALUE("23:59")),"22:00 a 00:00","no corresponde")))))))))))) -> 12:00 a 14:00 | D71: MARTINEZ. R | E71: ARREGUI, FERNANDO | F71: 1 | G71: LACABA, CAMILA | H71: 918090 | I71: 46741272 | J71: CHACARITA | K71: COLABORACION | L71: CHOQUE | M71: LESIONES | N71: PARQUE CHAS 01 | O71: Parque Chas | P71: 0.58055556 | Q71: 0.61111111 | R71: 0.58055556 | V71: - | W71: SE TOMA CONOCIMIENTO POR CARTA POR FEMENINO REFIERE QUE UN VEHICULO AL DOBLAR CHOCO A UN JOVEN EN MOTO . AL TOMAR LA CAMARA SE VISUALIZA A UN MASCULINO CAIDO EN LA VIA PUGLICA. SE APORTA LINEA DE TIEMPO.. ARRIBA PERSONAL POLICIAL Y SAME QUIEN ASISTE Y SE RETIRA CON TRASLADO.-CMU AMPLIA SE RETIRA MOVIL POLICIAL.-HT R 229 INFORMA EN EL LUGAR ARRIBO SAME DE BASE PIROBANO INTERNO 425 ASISTE Y TRASLADA AL SEÑOR CON DNI:35636990 LASTORIA CLAUDIO DIAGNOSTICA POLITRAUMATISMO EDAD 35 AÑOS., EN BREVE AMPLIA DEMAS DATOS.-SE REALIZA LA CONSULTA CON LA UFLA NORTE AC DR BROTO SECRE UNA MANI DISPONE ACT POR ATICULO 94.- | X71: 0 | Y71: 1 | Z71: 1 | AA71: 15C | AB71: U | AC71: CARTA | AE71: 1 TRASLADO SAME | AF71: COLABORACION CON IMPUTADO/S | AH71: NO CARGAN IMPUTADO - | AL71: =VLOOKUP(G71,Hoja2!P:Q,2,0) -> 39849206 | AM71: =IF(OR(Y71>0,X71>0),"IMPUTADO","NADA") -> IMPUTADO | AN71: =IF(AND(AM71="IMPUTADO",ISBLANK(M71)),"FALTO","NO") -> NO
A72: 45992 | B72: =IF(AND(VALUE(P72)>=VALUE("06:00"),VALUE(P72)<=VALUE("17:59")),"06 A 18","18 A 06") -> 06 A 18 | C72: =IF(AND(VALUE(P72)>=VALUE("00:00"),VALUE(P72)<=VALUE("01:59")),"00:00 a 02:00",IF(AND(VALUE(P72)>=VALUE("02:00"),VALUE(P72)<=VALUE("03:59")),"02:00 a 04:00",IF(AND(VALUE(P72)>=VALUE("04:00"),VALUE(P72)<=VALUE("05:59")),"04:00 a 06:00",IF(AND(VALUE(P72)>=VALUE("06:00"),VALUE(P72)<=VALUE("07:59")),"06:00 a 08:00",IF(AND(VALUE(P72)>=VALUE("08:00"),VALUE(P72)<=VALUE("09:59")),"08:00 a 10:00",IF(AND(VALUE(P72)>=VALUE("10:00"),VALUE(P72)<=VALUE("11:59")),"10:00 a 12:00",IF(AND(VALUE(P72)>=VALUE("12:00"),VALUE(P72)<=VALUE("13:59")),"12:00 a 14:00",IF(AND(VALUE(P72)>=VALUE("14:00"),VALUE(P72)<=VALUE("15:59")),"14:00 a 16:00",IF(AND(VALUE(P72)>=VALUE("16:00"),VALUE(P72)<=VALUE("17:59")),"16:00 a 18:00",IF(AND(VALUE(P72)>=VALUE("18:00"),VALUE(P72)<=VALUE("19:59")),"18:00 a 20:00",IF(AND(VALUE(P72)>=VALUE("20:00"),VALUE(P72)<=VALUE("21:59")),"20:00 a 22:00",IF(AND(VALUE(P72)>=VALUE("22:00"),VALUE(P72)<=VALUE("23:59")),"22:00 a 00:00","no corresponde")))))))))))) -> 14:00 a 16:00 | D72: MARTINEZ. R | E72: PEREZ, RAMON | F72: 1 | G72: ZAMUDIO, ALEJANDRO | H72: 926236 | I72: 46741350 | J72: CHACARITA | K72: COLABORACION | L72: IDENT. DE PERSONAS | N72: CABALLITO O166 | O72: Caballito | P72: 0.59027778 | Q72: 0.59722222 | S72: - | T72: - | U72: - | V72: - | W72: SE TOMA CONOCIMIENTO POR CARTA POR MASCULINO INDICA QUE PASO CORRIENDO UN HOMBRE CON UN SUERO EN EL BRAZO MUY MAL VESTIDO . Y SE ESCONDIO DETRAS DE UN AUTO , ESPERO QUE EL MOVIL PASARA Y AHORA SE VA SENTIDO ACOYTE POR VALLESE . EL HOMBRE VISTE MAYA CON TRES COLORES Y REMERA CLARA SOLICITAN MOVIL - , SE AMPLIA POR CARTA QUE HT INF ARRIBADO AL LUGAR PANAMA NORML // PRESENCIA NOTORIA NO SE APROXIMA DENUNCIANTE SE AGUARDA TIEMPO PRUDENCIAL// CONTINUA CON EL RECORRIDO.-CMU INFORMA QUE POSEE CAMARA CABALLITOO166. SE BEROFOCA.-CMU AMPLIA AL MOMENTO NO SE LOGRA VISUALIZAR LO APORTADO.-CMU AMPLIA SE VERIFICO LINEA DE TIEMPO POR MEDIO DE CAMARA CABALLITOO166 CAM02 VISUALIZANDO A LAS 14:01 HORAS UN MASCULINO DE REMERA GRIS CON ESTAMPADO CLARO, UN ELEMENTO CLARO EN LA MANO, SHORT DE COLOR OSCURO, AMARILLO Y VERDE, DESCALZO CIRCULANDO POR VALLESE SENTIDO COLPAYO.- | X72: 0 | Y72: 0 | Z72: 0 | AA72: 6A | AB72: U | AC72: CARTA | AF72: CARTA FINALIZADA | AH72: NO CARGA ORIGEN | AL72: =VLOOKUP(G72,Hoja2!P:Q,2,0) -> 45524794 | AM72: =IF(OR(Y72>0,X72>0),"IMPUTADO","NADA") -> NADA | AN72: =IF(AND(AM72="IMPUTADO",ISBLANK(M72)),"FALTO","NO") -> NO
A73: 45992 | B73: =IF(AND(VALUE(P73)>=VALUE("06:00"),VALUE(P73)<=VALUE("17:59")),"06 A 18","18 A 06") -> 06 A 18 | C73: =IF(AND(VALUE(P73)>=VALUE("00:00"),VALUE(P73)<=VALUE("01:59")),"00:00 a 02:00",IF(AND(VALUE(P73)>=VALUE("02:00"),VALUE(P73)<=VALUE("03:59")),"02:00 a 04:00",IF(AND(VALUE(P73)>=VALUE("04:00"),VALUE(P73)<=VALUE("05:59")),"04:00 a 06:00",IF(AND(VALUE(P73)>=VALUE("06:00"),VALUE(P73)<=VALUE("07:59")),"06:00 a 08:00",IF(AND(VALUE(P73)>=VALUE("08:00"),VALUE(P73)<=VALUE("09:59")),"08:00 a 10:00",IF(AND(VALUE(P73)>=VALUE("10:00"),VALUE(P73)<=VALUE("11:59")),"10:00 a 12:00",IF(AND(VALUE(P73)>=VALUE("12:00"),VALUE(P73)<=VALUE("13:59")),"12:00 a 14:00",IF(AND(VALUE(P73)>=VALUE("14:00"),VALUE(P73)<=VALUE("15:59")),"14:00 a 16:00",IF(AND(VALUE(P73)>=VALUE("16:00"),VALUE(P73)<=VALUE("17:59")),"16:00 a 18:00",IF(AND(VALUE(P73)>=VALUE("18:00"),VALUE(P73)<=VALUE("19:59")),"18:00 a 20:00",IF(AND(VALUE(P73)>=VALUE("20:00"),VALUE(P73)<=VALUE("21:59")),"20:00 a 22:00",IF(AND(VALUE(P73)>=VALUE("22:00"),VALUE(P73)<=VALUE("23:59")),"22:00 a 00:00","no corresponde")))))))))))) -> 12:00 a 14:00 | D73: MARTINEZ. R | E73: MEZA, GASTON | F73: 1 | G73: CASTILLO, GISELL | H73: 918408 | I73: 46741378 | J73: CMU 9 DE JULIO | K73: CHOQUE | N73: CONSTITUCION 02 | O73: Constitucion | P73: 0.57291667 | Q73: 0.59513889 | R73: 0.58819444 | V73: - | W73: SE TOMA CONOCIMIENTO MEDIANTE CARTA SAE HT SOLICITA SAME POR PERSONAL POLICIAL COLISIONADO. SE BRINDA APOYO OPTICO POR CAMARA CONSTITUCION 02. SE VERIFICO LINEA DE TIEMPO CAM 02 HORA 14:04 SE LOGRA VER MOMENTO DEL CHOQUE, SOBRE EEUU SEMAFORO EN VERDE PARA LOS VEHICULOS, MOTO POLICIAL POR CALLE 9 DE JULIO ENVISTE AL RODADO DE COLOR CLARO | X73: 0 | Y73: 0 | Z73: 0 | AA73: 1B | AB73: U | AC73: CARTA | AF73: CARTA FINALIZADA | AL73: =VLOOKUP(G73,Hoja2!P:Q,2,0) -> 36405101 | AM73: =IF(OR(Y73>0,X73>0),"IMPUTADO","NADA") -> NADA | AN73: =IF(AND(AM73="IMPUTADO",ISBLANK(M73)),"FALTO","NO") -> NO
A74: 45992 | B74: =IF(AND(VALUE(P74)>=VALUE("06:00"),VALUE(P74)<=VALUE("17:59")),"06 A 18","18 A 06") -> 06 A 18 | C74: =IF(AND(VALUE(P74)>=VALUE("00:00"),VALUE(P74)<=VALUE("01:59")),"00:00 a 02:00",IF(AND(VALUE(P74)>=VALUE("02:00"),VALUE(P74)<=VALUE("03:59")),"02:00 a 04:00",IF(AND(VALUE(P74)>=VALUE("04:00"),VALUE(P74)<=VALUE("05:59")),"04:00 a 06:00",IF(AND(VALUE(P74)>=VALUE("06:00"),VALUE(P74)<=VALUE("07:59")),"06:00 a 08:00",IF(AND(VALUE(P74)>=VALUE("08:00"),VALUE(P74)<=VALUE("09:59")),"08:00 a 10:00",IF(AND(VALUE(P74)>=VALUE("10:00"),VALUE(P74)<=VALUE("11:59")),"10:00 a 12:00",IF(AND(VALUE(P74)>=VALUE("12:00"),VALUE(P74)<=VALUE("13:59")),"12:00 a 14:00",IF(AND(VALUE(P74)>=VALUE("14:00"),VALUE(P74)<=VALUE("15:59")),"14:00 a 16:00",IF(AND(VALUE(P74)>=VALUE("16:00"),VALUE(P74)<=VALUE("17:59")),"16:00 a 18:00",IF(AND(VALUE(P74)>=VALUE("18:00"),VALUE(P74)<=VALUE("19:59")),"18:00 a 20:00",IF(AND(VALUE(P74)>=VALUE("20:00"),VALUE(P74)<=VALUE("21:59")),"20:00 a 22:00",IF(AND(VALUE(P74)>=VALUE("22:00"),VALUE(P74)<=VALUE("23:59")),"22:00 a 00:00","no corresponde")))))))))))) -> 14:00 a 16:00 | D74: MARTINEZ. R | E74: ARREGUI, FERNANDO | F74: 1 | G74: PERGOLA, BRIAN SEBASTIÀN | H74: 918542 | I74: 46741391 | J74: CHACARITA | K74: COLABORACION | L74: ROBO/HURTO | N74: FLORESTA 20 | O74: Floresta | P74: 0.59375 | Q74: 0.60277778 | R74: 0.59375 | S74: - | T74: - | U74: - | V74: - | W74: SE TOMA CONOCIMIENTO POR CARTA POR DENUNCIANTE REFIERE QUE LE HABRIAN ROBADO SU CELULAR- REFIERE QUE 5 MASCULINOS DE APROX 12 AÑOS- REFIERE QUE TODOS TENDRIAN PELO NEGRO, UNO TENDRIA LABIO BIPORINO LE HABRIAN ROBADO EN BAHIA BLANCA Y JUAN B JUSTO- DENUNCIANTE VALENTIN- VISTE GORRA ADELANTE - CAMPERA Y SHORT Y BICI NARANJA- TENDRIA 13 AÑOS-AL TOMR LA CAMARTAS E VISUALIZA A PERSONAL POLICIAL CON DANMIFICADO. SE AMPLIA POR CARTA QUE SE TOMO CONOCIMIENTO. SE SOLICITA QUE, EN CASO DE SURGIR O CONTAR CON ALGUN VEHICULO EN FUGA, EN SEGUIMIENTO O PARA CURSAR A MODO DE ALERTA O HALLAZGO AUTOMOTOR, VOLVER A COMPARTIR CON ESTA AGENCIA.- | X74: 0 | Y74: 0 | Z74: 0 | AA74: 10A | AB74: U | AC74: CARTA | AF74: CARTA FINALIZADA | AH74: NO CARGA ORIGEN | AL74: =VLOOKUP(G74,Hoja2!P:Q,2,0) -> 46124914 | AM74: =IF(OR(Y74>0,X74>0),"IMPUTADO","NADA") -> NADA | AN74: =IF(AND(AM74="IMPUTADO",ISBLANK(M74)),"FALTO","NO") -> NO
A75: 45992 | B75: =IF(AND(VALUE(P75)>=VALUE("06:00"),VALUE(P75)<=VALUE("17:59")),"06 A 18","18 A 06") -> 06 A 18 | C75: =IF(AND(VALUE(P75)>=VALUE("00:00"),VALUE(P75)<=VALUE("01:59")),"00:00 a 02:00",IF(AND(VALUE(P75)>=VALUE("02:00"),VALUE(P75)<=VALUE("03:59")),"02:00 a 04:00",IF(AND(VALUE(P75)>=VALUE("04:00"),VALUE(P75)<=VALUE("05:59")),"04:00 a 06:00",IF(AND(VALUE(P75)>=VALUE("06:00"),VALUE(P75)<=VALUE("07:59")),"06:00 a 08:00",IF(AND(VALUE(P75)>=VALUE("08:00"),VALUE(P75)<=VALUE("09:59")),"08:00 a 10:00",IF(AND(VALUE(P75)>=VALUE("10:00"),VALUE(P75)<=VALUE("11:59")),"10:00 a 12:00",IF(AND(VALUE(P75)>=VALUE("12:00"),VALUE(P75)<=VALUE("13:59")),"12:00 a 14:00",IF(AND(VALUE(P75)>=VALUE("14:00"),VALUE(P75)<=VALUE("15:59")),"14:00 a 16:00",IF(AND(VALUE(P75)>=VALUE("16:00"),VALUE(P75)<=VALUE("17:59")),"16:00 a 18:00",IF(AND(VALUE(P75)>=VALUE("18:00"),VALUE(P75)<=VALUE("19:59")),"18:00 a 20:00",IF(AND(VALUE(P75)>=VALUE("20:00"),VALUE(P75)<=VALUE("21:59")),"20:00 a 22:00",IF(AND(VALUE(P75)>=VALUE("22:00"),VALUE(P75)<=VALUE("23:59")),"22:00 a 00:00","no corresponde")))))))))))) -> 14:00 a 16:00 | D75: MARTINEZ. R | E75: PEREZ, RAMON | F75: 1 | G75: MOYA, PRISCILLA ANA LEONOR | H75: 918421 | I75: 46741473 | J75: CHACARITA | K75: COLABORACION | L75: IDENT. DE PERSONAS | N75: FLORES 57 CAM01 | O75: Flores | P75: 0.6 | Q75: 0.68125 | R75: 0.6 | S75: - | T75: - | U75: - | V75: - | W75: SE TOMA CONOCIMIENTOPOR CARTA POR MASCULINO REFIERE QUE PARTICULARES TIENEN RETENIDO A MASCULINO VESTIDO DE NEGRO POR ILICITO EN VIA UBLICA, ALT OMAR LA CAMARA SE VISUALZIA PERSONAL POLICIAL CON EL MASCULINO.-CMU INF SE REALIZO LINEA DE TIEMPO DE CAMARA FLORES57CAM01 VISUALIZANDO 14:13 HS A MASCULINO DE GORRA OSCURA, ABRIGO Y PANTALON NEGRO, CALZADO OSCURO Y MOCHILA OSCURA CON FRANJAS TIPO ADIDAS BLANCAS COLOCADA A LA VELOZ CARRERA POR LAMAS SENTIDO A NEUQUEN EL MISMO SIENDO PERSEGUIDO POR DOS FEMENINOS, ASI MISMO SE VISUALIZA 14:15 HS A EL MISMO MASCULINO EL CUAL REGRESA EN SUS PASOS TRAIDO POR APARENTES OBREROS Y FEMENINO ANTES MENCIONADO.-SECTOR 1 INF EVACUO CONSULTA CON EL JUSGADO CRIMINAL Y CORRECCIONAL DE MENORRES NR 7 AC DEL DR GINELI SECRETARIA NR 21 DISPONE NO ADOPTA TEMPERAMENTO / EL MISMO SE NOTIFICA QUE SE TIENE QUE PRESENTAR EN ALCALDANA 550.-CMU INF MASCULINO SE RETIRA DEL LUGAR POR SUS PROPIOS MEDIOS.- | X75: 0 | Y75: 0 | Z75: 0 | AA75: 7C | AB75: U | AC75: CARTA | AF75: CARTA FINALIZADA | AH75: NO CARGA ORIGEN | AL75: =VLOOKUP(G75,Hoja2!P:Q,2,0) -> 41623311 | AM75: =IF(OR(Y75>0,X75>0),"IMPUTADO","NADA") -> NADA | AN75: =IF(AND(AM75="IMPUTADO",ISBLANK(M75)),"FALTO","NO") -> NO
A76: 45992 | B76: =IF(AND(VALUE(P76)>=VALUE("06:00"),VALUE(P76)<=VALUE("17:59")),"06 A 18","18 A 06") -> 06 A 18 | C76: =IF(AND(VALUE(P76)>=VALUE("00:00"),VALUE(P76)<=VALUE("01:59")),"00:00 a 02:00",IF(AND(VALUE(P76)>=VALUE("02:00"),VALUE(P76)<=VALUE("03:59")),"02:00 a 04:00",IF(AND(VALUE(P76)>=VALUE("04:00"),VALUE(P76)<=VALUE("05:59")),"04:00 a 06:00",IF(AND(VALUE(P76)>=VALUE("06:00"),VALUE(P76)<=VALUE("07:59")),"06:00 a 08:00",IF(AND(VALUE(P76)>=VALUE("08:00"),VALUE(P76)<=VALUE("09:59")),"08:00 a 10:00",IF(AND(VALUE(P76)>=VALUE("10:00"),VALUE(P76)<=VALUE("11:59")),"10:00 a 12:00",IF(AND(VALUE(P76)>=VALUE("12:00"),VALUE(P76)<=VALUE("13:59")),"12:00 a 14:00",IF(AND(VALUE(P76)>=VALUE("14:00"),VALUE(P76)<=VALUE("15:59")),"14:00 a 16:00",IF(AND(VALUE(P76)>=VALUE("16:00"),VALUE(P76)<=VALUE("17:59")),"16:00 a 18:00",IF(AND(VALUE(P76)>=VALUE("18:00"),VALUE(P76)<=VALUE("19:59")),"18:00 a 20:00",IF(AND(VALUE(P76)>=VALUE("20:00"),VALUE(P76)<=VALUE("21:59")),"20:00 a 22:00",IF(AND(VALUE(P76)>=VALUE("22:00"),VALUE(P76)<=VALUE("23:59")),"22:00 a 00:00","no corresponde")))))))))))) -> 14:00 a 16:00 | D76: MARTINEZ. R | E76: PEREZ, RAMON | F76: 1 | G76: LURASCHI, IGNACIO | H76: 918094 | I76: 46741522 | J76: CHACARITA | K76: CHOQUE | N76: PALERMO 90 | O76: Palermo | P76: 0.59652778 | Q76: 0.60625 | R76: 0.60138889 | S76: - | T76: - | V76: - | W76: SE VISULAIZA POR LA CAMARA UN CHOQUE EN EL LUGAR. SE VISUALZIA A PERSONAL POLICIAL Y PERSONAL DE TRANSITO SE AMPLIA POR CARTA QUE 107:HT R 321 IMFORMA QUE SE TRATO DE UN CHOQUE SIMPLE ENTRE TRES VEHICULOS NEGATIVO LESIONADOS , SE PASAN LOS DATOS Y SE RETIRAN DEL LUGAR . | X76: 0 | Y76: 0 | Z76: 0 | AA76: 14B | AB76: U | AC76: MONITOREO | AF76: CARTA FINALIZADA | AH76: NO CARGA ORIGEN | AL76: =VLOOKUP(G76,Hoja2!P:Q,2,0) -> 43988966 | AM76: =IF(OR(Y76>0,X76>0),"IMPUTADO","NADA") -> NADA | AN76: =IF(AND(AM76="IMPUTADO",ISBLANK(M76)),"FALTO","NO") -> NO
A77: 45992 | B77: =IF(AND(VALUE(P77)>=VALUE("06:00"),VALUE(P77)<=VALUE("17:59")),"06 A 18","18 A 06") -> 06 A 18 | C77: =IF(AND(VALUE(P77)>=VALUE("00:00"),VALUE(P77)<=VALUE("01:59")),"00:00 a 02:00",IF(AND(VALUE(P77)>=VALUE("02:00"),VALUE(P77)<=VALUE("03:59")),"02:00 a 04:00",IF(AND(VALUE(P77)>=VALUE("04:00"),VALUE(P77)<=VALUE("05:59")),"04:00 a 06:00",IF(AND(VALUE(P77)>=VALUE("06:00"),VALUE(P77)<=VALUE("07:59")),"06:00 a 08:00",IF(AND(VALUE(P77)>=VALUE("08:00"),VALUE(P77)<=VALUE("09:59")),"08:00 a 10:00",IF(AND(VALUE(P77)>=VALUE("10:00"),VALUE(P77)<=VALUE("11:59")),"10:00 a 12:00",IF(AND(VALUE(P77)>=VALUE("12:00"),VALUE(P77)<=VALUE("13:59")),"12:00 a 14:00",IF(AND(VALUE(P77)>=VALUE("14:00"),VALUE(P77)<=VALUE("15:59")),"14:00 a 16:00",IF(AND(VALUE(P77)>=VALUE("16:00"),VALUE(P77)<=VALUE("17:59")),"16:00 a 18:00",IF(AND(VALUE(P77)>=VALUE("18:00"),VALUE(P77)<=VALUE("19:59")),"18:00 a 20:00",IF(AND(VALUE(P77)>=VALUE("20:00"),VALUE(P77)<=VALUE("21:59")),"20:00 a 22:00",IF(AND(VALUE(P77)>=VALUE("22:00"),VALUE(P77)<=VALUE("23:59")),"22:00 a 00:00","no corresponde")))))))))))) -> 16:00 a 18:00 | D77: MARTINEZ. R | E77: GAUNA, MICAELA | F77: 1 | G77: YAPURA, JOHANA | H77: 926374 | I77: 46741570 | J77: PUERTO MADERO | K77: COLABORACION | L77: ROBO/HURTO | N77: BARRIO 31 07 | O77: Retiro | P77: 0.68055556 | Q77: 0.62361111 | R77: 0.61527778 | V77: - | W77: SE TOMA CONOCIMIENTO MEDIANTE CARTA SAE DENUNCIANTE INFORMA QUE DOS MASCULINOS LE ROBARON LA MOTO A OTRO MASCULINO , INFORMA QUE VAN EN DIRECCION A LA VILLA 31 EN UNA MOTO NEGRA SIN CASCOS,LLAMANTE NO PUDO VER EL DOMINIO E INFORMA QUE EL MASCULINO QUEDO EN EL LUGAR DEL ROBO.AMPLIA SE VISUALIZA POR CAMARA BARRIO 31 07 PERSONAL POLICIAL JUNTO A UN MASCULINO CON CASCO EN LA MANO APARENTE DAMNIFICADO DE HECHO | X77: 0 | Y77: 0 | Z77: 0 | AA77: 1A | AB77: U | AC77: CARTA | AF77: CARTA FINALIZADA | AL77: =VLOOKUP(G77,Hoja2!P:Q,2,0) -> 35092747 | AM77: =IF(OR(Y77>0,X77>0),"IMPUTADO","NADA") -> NADA | AN77: =IF(AND(AM77="IMPUTADO",ISBLANK(M77)),"FALTO","NO") -> NO
A78: 45992 | B78: =IF(AND(VALUE(P78)>=VALUE("06:00"),VALUE(P78)<=VALUE("17:59")),"06 A 18","18 A 06") -> 06 A 18 | C78: =IF(AND(VALUE(P78)>=VALUE("00:00"),VALUE(P78)<=VALUE("01:59")),"00:00 a 02:00",IF(AND(VALUE(P78)>=VALUE("02:00"),VALUE(P78)<=VALUE("03:59")),"02:00 a 04:00",IF(AND(VALUE(P78)>=VALUE("04:00"),VALUE(P78)<=VALUE("05:59")),"04:00 a 06:00",IF(AND(VALUE(P78)>=VALUE("06:00"),VALUE(P78)<=VALUE("07:59")),"06:00 a 08:00",IF(AND(VALUE(P78)>=VALUE("08:00"),VALUE(P78)<=VALUE("09:59")),"08:00 a 10:00",IF(AND(VALUE(P78)>=VALUE("10:00"),VALUE(P78)<=VALUE("11:59")),"10:00 a 12:00",IF(AND(VALUE(P78)>=VALUE("12:00"),VALUE(P78)<=VALUE("13:59")),"12:00 a 14:00",IF(AND(VALUE(P78)>=VALUE("14:00"),VALUE(P78)<=VALUE("15:59")),"14:00 a 16:00",IF(AND(VALUE(P78)>=VALUE("16:00"),VALUE(P78)<=VALUE("17:59")),"16:00 a 18:00",IF(AND(VALUE(P78)>=VALUE("18:00"),VALUE(P78)<=VALUE("19:59")),"18:00 a 20:00",IF(AND(VALUE(P78)>=VALUE("20:00"),VALUE(P78)<=VALUE("21:59")),"20:00 a 22:00",IF(AND(VALUE(P78)>=VALUE("22:00"),VALUE(P78)<=VALUE("23:59")),"22:00 a 00:00","no corresponde")))))))))))) -> 14:00 a 16:00 | D78: MARTINEZ. R | E78: GAUNA, MICAELA | F78: 1 | G78: YAPURA, JOHANA | H78: 926373 | I78: 46741609 | J78: PUERTO MADERO | K78: ROBO/HURTO | M78: ROBO/HURTO | N78: BARRIO 31 24 | O78: Retiro | P78: 0.60277778 | Q78: 0.71736111 | R78: 0.61666667 | V78: - | W78: SE POSEE CAMARA BARRIO 31 24 MASCULINO DE ROPAS OSCURAS, REMERA NEGRA CON ESTAMPADO JORGAN SHORT NEGRO CON LOGO DE JORDAN INGRESA MITAD DE SU CUERPO DEL LADO DEL ACOMPAÑANTE DE UN VEHICULO Y SE DA ALA FUGA | X78: 0 | Y78: 2 | Z78: 0 | AA78: 1A | AB78: U | AC78: MONITOREO | AE78: 2 DETENIDOS | AF78: FINALIZA CON IMPUTADO/S | AH78: NO CARGA ORIGEN | AL78: =VLOOKUP(G78,Hoja2!P:Q,2,0) -> 35092747 | AM78: =IF(OR(Y78>0,X78>0),"IMPUTADO","NADA") -> IMPUTADO | AN78: =IF(AND(AM78="IMPUTADO",ISBLANK(M78)),"FALTO","NO") -> NO
A79: 45992 | B79: =IF(AND(VALUE(P79)>=VALUE("06:00"),VALUE(P79)<=VALUE("17:59")),"06 A 18","18 A 06") -> 06 A 18 | C79: =IF(AND(VALUE(P79)>=VALUE("00:00"),VALUE(P79)<=VALUE("01:59")),"00:00 a 02:00",IF(AND(VALUE(P79)>=VALUE("02:00"),VALUE(P79)<=VALUE("03:59")),"02:00 a 04:00",IF(AND(VALUE(P79)>=VALUE("04:00"),VALUE(P79)<=VALUE("05:59")),"04:00 a 06:00",IF(AND(VALUE(P79)>=VALUE("06:00"),VALUE(P79)<=VALUE("07:59")),"06:00 a 08:00",IF(AND(VALUE(P79)>=VALUE("08:00"),VALUE(P79)<=VALUE("09:59")),"08:00 a 10:00",IF(AND(VALUE(P79)>=VALUE("10:00"),VALUE(P79)<=VALUE("11:59")),"10:00 a 12:00",IF(AND(VALUE(P79)>=VALUE("12:00"),VALUE(P79)<=VALUE("13:59")),"12:00 a 14:00",IF(AND(VALUE(P79)>=VALUE("14:00"),VALUE(P79)<=VALUE("15:59")),"14:00 a 16:00",IF(AND(VALUE(P79)>=VALUE("16:00"),VALUE(P79)<=VALUE("17:59")),"16:00 a 18:00",IF(AND(VALUE(P79)>=VALUE("18:00"),VALUE(P79)<=VALUE("19:59")),"18:00 a 20:00",IF(AND(VALUE(P79)>=VALUE("20:00"),VALUE(P79)<=VALUE("21:59")),"20:00 a 22:00",IF(AND(VALUE(P79)>=VALUE("22:00"),VALUE(P79)<=VALUE("23:59")),"22:00 a 00:00","no corresponde")))))))))))) -> 16:00 a 18:00 | D79: MARTINEZ. R | E79: PEREZ, RAMON | F79: 1 | G79: GONZALEZ, MONICA | H79: 918530 | I79: 46741700 | J79: CHACARITA | K79: PERSONA DESCOMPUESTA | N79: PALERMO 81 | O79: PALERMO | P79: 0.72916667 | Q79: 0.62083333 | R79: 0.61944444 | V79: - | W79: SE TOMA CONOCIMIENTO MEDIANTE CARTA SAE CMU INFORMA QUE POSEE CAMARA PALERMO 81, SE VERIFICA.-CMU AMPLIA SE VISUALIZA PERSONAL POLICIAL CON UNA CAIDA EN LA VIA PUBLICA PARCIALMENTE POR OBSTRUCCION DE ARBOLEDA.-CMU AMPLIA LA PERSONA SE REINCORPORA.-SE TOMA CONOCIMIENTO DE LO NOTIFICADO POR CMU ASI MISMO PERSONAL VERIFICO LA ZONA.-HT INF PERSONAL VERIFICO LA ZONA Y NEG PERSONA CAIDA EN VIA PUBLICA PAN NORMAL.- | X79: 0 | Y79: 0 | Z79: 0 | AA79: 14A | AB79: U | AC79: CARTA | AF79: CARTA FINALIZADA | AL79: =VLOOKUP(G79,Hoja2!P:Q,2,0) -> 18224482 | AM79: =IF(OR(Y79>0,X79>0),"IMPUTADO","NADA") -> NADA | AN79: =IF(AND(AM79="IMPUTADO",ISBLANK(M79)),"FALTO","NO") -> NO
A80: 45992 | B80: =IF(AND(VALUE(P80)>=VALUE("06:00"),VALUE(P80)<=VALUE("17:59")),"06 A 18","18 A 06") -> 06 A 18 | C80: =IF(AND(VALUE(P80)>=VALUE("00:00"),VALUE(P80)<=VALUE("01:59")),"00:00 a 02:00",IF(AND(VALUE(P80)>=VALUE("02:00"),VALUE(P80)<=VALUE("03:59")),"02:00 a 04:00",IF(AND(VALUE(P80)>=VALUE("04:00"),VALUE(P80)<=VALUE("05:59")),"04:00 a 06:00",IF(AND(VALUE(P80)>=VALUE("06:00"),VALUE(P80)<=VALUE("07:59")),"06:00 a 08:00",IF(AND(VALUE(P80)>=VALUE("08:00"),VALUE(P80)<=VALUE("09:59")),"08:00 a 10:00",IF(AND(VALUE(P80)>=VALUE("10:00"),VALUE(P80)<=VALUE("11:59")),"10:00 a 12:00",IF(AND(VALUE(P80)>=VALUE("12:00"),VALUE(P80)<=VALUE("13:59")),"12:00 a 14:00",IF(AND(VALUE(P80)>=VALUE("14:00"),VALUE(P80)<=VALUE("15:59")),"14:00 a 16:00",IF(AND(VALUE(P80)>=VALUE("16:00"),VALUE(P80)<=VALUE("17:59")),"16:00 a 18:00",IF(AND(VALUE(P80)>=VALUE("18:00"),VALUE(P80)<=VALUE("19:59")),"18:00 a 20:00",IF(AND(VALUE(P80)>=VALUE("20:00"),VALUE(P80)<=VALUE("21:59")),"20:00 a 22:00",IF(AND(VALUE(P80)>=VALUE("22:00"),VALUE(P80)<=VALUE("23:59")),"22:00 a 00:00","no corresponde")))))))))))) -> 16:00 a 18:00 | D80: MARTINEZ. R | E80: ARREGUI, FERNANDO | F80: 1 | G80: ROMERO, KARINA | H80: 918427 | I80: 46741712 | J80: CHACARITA | K80: COLABORACION | L80: ROBO/HURTO | N80: FLORES 75 | O80: Flores | P80: 0.71875 | Q80: 0.68055556 | R80: 0.61875 | V80: - | W80: SE TOMA CONOCIMIENTO MEDIANTE CARTA SAE DENUNCIANTE REFIERE QUE LE HABRIAN ROTO EL VIDRIO DE SU AUTO Y LE HABRIAN SUSTRAIDO UNA MOCHILA. SU AUTO ES UN PEUGEOT 308 COLOR GRIS OSCURO DOMINIO: TKG097.-CMU INF, SE POSE SE POSEE CAMARA FLORES78 SE VISUALIZA EL VEHICULO CON DOS MASCULINOS EN EL LUGAR.-CMU AMPLIA ARRIBA PERSONAL POLICIAL.-CMU SE REALIZO LINEA DE TIEMPO POR LA CAMARA FLORES38 SIENDO LAS 13:50HS SE VISUALIZO A UN MASCULINO DE ROPAS OSCURAS APOYASE AL VEHICULO. ES TODO LO APORTADO. YA QUE LA CAMARA EL DOMO Y ESTA SE ENCUENTRA EN MODO PATRON, NO SE VISUALIZA EL MOMENTO DEL HECHO ILICITO.-SE TOMO CONOCIMIENTO. SE SOLICITA QUE, EN CASO DE SURGIR O CONTAR CON ALGUN VEHICULO EN FUGA, EN SEGUIMIENTO O PARA CURSAR A MODO DE ALERTA O HALLAZGO AUTOMOTOR, VOLVER A COMPARTIR CON ESTA AGENCIA.-CMU SE RETIFICA SE REALIZO LINEA DE TIEMPO POR LA CAMARA FLORES78 SIENDO LAS 13:50HS SE VISUALIZO A UN MASCULINO DE ROPAS OSCURAS APOYASE AL VEHICULO. ES TODO LO APORTADO. YA QUE LA CAMARA EL DOMO Y ESTA SE ENCUENTRA EN MODO PATRON, NO SE VISUALIZA EL MOMENTO DEL HECHO ILICITO.-SE ENTREVISTO CON EL DAMNIFICADO QUIEN REFIERE QUE AL REGRESAR DIO CON EL CRISTAL DE SU VEHICULO VIOLENTADO Y EL FALTANTE DE SU MOCHILA , SE REALIZO CONSULTA CON LA FIS 55 A/C DOC TRONCOZO SECRET UNICA A/C DEL DOC CANDELA ACT POR ROBO .- | X80: 0 | Y80: 0 | Z80: 0 | AA80: 7C | AB80: U | AC80: CARTA | AF80: CARTA FINALIZADA | AL80: =VLOOKUP(G80,Hoja2!P:Q,2,0) -> 39416059 | AM80: =IF(OR(Y80>0,X80>0),"IMPUTADO","NADA") -> NADA | AN80: =IF(AND(AM80="IMPUTADO",ISBLANK(M80)),"FALTO","NO") -> NO
A81: 45992 | B81: =IF(AND(VALUE(P81)>=VALUE("06:00"),VALUE(P81)<=VALUE("17:59")),"06 A 18","18 A 06") -> 06 A 18 | C81: =IF(AND(VALUE(P81)>=VALUE("00:00"),VALUE(P81)<=VALUE("01:59")),"00:00 a 02:00",IF(AND(VALUE(P81)>=VALUE("02:00"),VALUE(P81)<=VALUE("03:59")),"02:00 a 04:00",IF(AND(VALUE(P81)>=VALUE("04:00"),VALUE(P81)<=VALUE("05:59")),"04:00 a 06:00",IF(AND(VALUE(P81)>=VALUE("06:00"),VALUE(P81)<=VALUE("07:59")),"06:00 a 08:00",IF(AND(VALUE(P81)>=VALUE("08:00"),VALUE(P81)<=VALUE("09:59")),"08:00 a 10:00",IF(AND(VALUE(P81)>=VALUE("10:00"),VALUE(P81)<=VALUE("11:59")),"10:00 a 12:00",IF(AND(VALUE(P81)>=VALUE("12:00"),VALUE(P81)<=VALUE("13:59")),"12:00 a 14:00",IF(AND(VALUE(P81)>=VALUE("14:00"),VALUE(P81)<=VALUE("15:59")),"14:00 a 16:00",IF(AND(VALUE(P81)>=VALUE("16:00"),VALUE(P81)<=VALUE("17:59")),"16:00 a 18:00",IF(AND(VALUE(P81)>=VALUE("18:00"),VALUE(P81)<=VALUE("19:59")),"18:00 a 20:00",IF(AND(VALUE(P81)>=VALUE("20:00"),VALUE(P81)<=VALUE("21:59")),"20:00 a 22:00",IF(AND(VALUE(P81)>=VALUE("22:00"),VALUE(P81)<=VALUE("23:59")),"22:00 a 00:00","no corresponde")))))))))))) -> 14:00 a 16:00 | D81: MARTINEZ. R | E81: MOLINA, JOSE MANUEL | F81: 1 | G81: MACIAS, SANTIAGO | H81: 918253 | I81: 46741812 | J81: CHACARITA | K81: USO INDEBIDO ESPACIO PUBLICO | M81: CONT. ENSUCIAR BIENES | N81: BALVANERA O136 | O81: Balvanera | P81: 0.61597222 | Q81: 0.69236111 | R81: 0.62361111 | S81: - | T81: - | U81: - | V81: - | W81: SE VISUALIZA MEDIANTE CAMARA BALVANERAO136 A MASCULINO REALIZANDO PEGATINAS EN VIA PUBLICA.-CMU INF MASCULINO ROBUSTO, CABELLO CORTO OSCURO, REMERA Y PANTALON OSCURO, MOCHILA GRIS COLOCADA EL MISMO POR PERSON SENTIDO CONTRARIO AL TRANSITO.-CMU INF EL MISMO AL MOMENTO EN ANCHORENA Y PERON SE LO VISUALIZA MEDIANTE CAMARA BALVANERAO106.-CMU AMPLIA EL MISMO CONTINUA POR PERSON SENTIDO CONTRARIO AL TRANSITO LADO PAR.-CMU INF SE VISUALIZA PERSONAL POLICIAL DAR CON MASCULINO EN MENCION.-HT INF SE REALIZA CONSULTA CON UNIDAD DE FLAGRANCIA ESTE AC DEL DR CARDINALLI SECRETARIA BARRETO, DISPONE ACT ART 94. PEGATINAS, MAGISTRADO NO SOLICITA REGISTRO FILMICO Y DECLARACION. SE REALIZO CONSULTA POR DICHOS DE CMU.- | X81: 1 | Y81: 0 | Z81: 0 | AA81: 3A | AB81: U | AC81: MONITOREO | AF81: FINALIZA CON IMPUTADO/S | AL81: =VLOOKUP(G81,Hoja2!P:Q,2,0) -> 44447985 | AM81: =IF(OR(Y81>0,X81>0),"IMPUTADO","NADA") -> IMPUTADO | AN81: =IF(AND(AM81="IMPUTADO",ISBLANK(M81)),"FALTO","NO") -> NO
A82: 45992 | B82: =IF(AND(VALUE(P82)>=VALUE("06:00"),VALUE(P82)<=VALUE("17:59")),"06 A 18","18 A 06") -> 06 A 18 | C82: =IF(AND(VALUE(P82)>=VALUE("00:00"),VALUE(P82)<=VALUE("01:59")),"00:00 a 02:00",IF(AND(VALUE(P82)>=VALUE("02:00"),VALUE(P82)<=VALUE("03:59")),"02:00 a 04:00",IF(AND(VALUE(P82)>=VALUE("04:00"),VALUE(P82)<=VALUE("05:59")),"04:00 a 06:00",IF(AND(VALUE(P82)>=VALUE("06:00"),VALUE(P82)<=VALUE("07:59")),"06:00 a 08:00",IF(AND(VALUE(P82)>=VALUE("08:00"),VALUE(P82)<=VALUE("09:59")),"08:00 a 10:00",IF(AND(VALUE(P82)>=VALUE("10:00"),VALUE(P82)<=VALUE("11:59")),"10:00 a 12:00",IF(AND(VALUE(P82)>=VALUE("12:00"),VALUE(P82)<=VALUE("13:59")),"12:00 a 14:00",IF(AND(VALUE(P82)>=VALUE("14:00"),VALUE(P82)<=VALUE("15:59")),"14:00 a 16:00",IF(AND(VALUE(P82)>=VALUE("16:00"),VALUE(P82)<=VALUE("17:59")),"16:00 a 18:00",IF(AND(VALUE(P82)>=VALUE("18:00"),VALUE(P82)<=VALUE("19:59")),"18:00 a 20:00",IF(AND(VALUE(P82)>=VALUE("20:00"),VALUE(P82)<=VALUE("21:59")),"20:00 a 22:00",IF(AND(VALUE(P82)>=VALUE("22:00"),VALUE(P82)<=VALUE("23:59")),"22:00 a 00:00","no corresponde")))))))))))) -> 16:00 a 18:00 | D82: MARTINEZ. R | E82: PEREZ, RAMON | F82: 1 | G82: LACABA, CAMILA | H82: 918100 | I82: 46742061 | J82: CHACARITA | K82: COLABORACION | L82: IDENT. DE PERSONAS | N82: VILLA URQUIZA O110 | O82: Villa Urquiza | P82: 0.72361111 | Q82: 0.65208333 | R82: 0.64930556 | V82: - | W82: SE TOMA CONOCIMIENTO MEDIANTE CARTA SAE MASCULINO REFIERE QUE HABRIA UN AMSCULINO EN SITUACION DE CALLE MOLESTANDO A LOS CLIENTES EN LA VEREDA EN LA ENTRADA DEL SUEPRMERCADO.-CMU INFORMA QUE POSEE CAMARA VILLA URQUIZAO110, SE VERIFICA.-CMU AMPLIA AL MOMENTO NO SE LOGRA VISUALIZAR LO APORTADO, ASI MISMO SE VISUALIZA UNA PERSONA DE SIMILARES CARACTERISTICAS SIN CALZADO EN LA VIA PUBLICA.-CMU AMPLIA SE VISUALIZA EL PERSONAL POLICIAL DAR CON EL MASCULINO.-CICLISTA R 2423 INFORMA EN EL LUGAR SE RETIRO UN MASCULINO EN SITUACION VULNERABLE EL MISMO IDENTIFICADO SIN NOVEDAD CORRESPONDE Y NO POSEE, SE RETIRA DEL LUGAR AMABLEMENTE.- | X82: 0 | Y82: 0 | Z82: 0 | AA82: 12C | AB82: U | AC82: CARTA | AF82: CARTA FINALIZADA | AL82: =VLOOKUP(G82,Hoja2!P:Q,2,0) -> 39849206 | AM82: =IF(OR(Y82>0,X82>0),"IMPUTADO","NADA") -> NADA | AN82: =IF(AND(AM82="IMPUTADO",ISBLANK(M82)),"FALTO","NO") -> NO
A83: 45992 | B83: =IF(AND(VALUE(P83)>=VALUE("06:00"),VALUE(P83)<=VALUE("17:59")),"06 A 18","18 A 06") -> 06 A 18 | C83: =IF(AND(VALUE(P83)>=VALUE("00:00"),VALUE(P83)<=VALUE("01:59")),"00:00 a 02:00",IF(AND(VALUE(P83)>=VALUE("02:00"),VALUE(P83)<=VALUE("03:59")),"02:00 a 04:00",IF(AND(VALUE(P83)>=VALUE("04:00"),VALUE(P83)<=VALUE("05:59")),"04:00 a 06:00",IF(AND(VALUE(P83)>=VALUE("06:00"),VALUE(P83)<=VALUE("07:59")),"06:00 a 08:00",IF(AND(VALUE(P83)>=VALUE("08:00"),VALUE(P83)<=VALUE("09:59")),"08:00 a 10:00",IF(AND(VALUE(P83)>=VALUE("10:00"),VALUE(P83)<=VALUE("11:59")),"10:00 a 12:00",IF(AND(VALUE(P83)>=VALUE("12:00"),VALUE(P83)<=VALUE("13:59")),"12:00 a 14:00",IF(AND(VALUE(P83)>=VALUE("14:00"),VALUE(P83)<=VALUE("15:59")),"14:00 a 16:00",IF(AND(VALUE(P83)>=VALUE("16:00"),VALUE(P83)<=VALUE("17:59")),"16:00 a 18:00",IF(AND(VALUE(P83)>=VALUE("18:00"),VALUE(P83)<=VALUE("19:59")),"18:00 a 20:00",IF(AND(VALUE(P83)>=VALUE("20:00"),VALUE(P83)<=VALUE("21:59")),"20:00 a 22:00",IF(AND(VALUE(P83)>=VALUE("22:00"),VALUE(P83)<=VALUE("23:59")),"22:00 a 00:00","no corresponde")))))))))))) -> 14:00 a 16:00 | D83: MARTINEZ. R | E83: ALCOBA, DIEGO | F83: 1 | G83: CABRAL, CAROLINA BELEN | H83: 923586 | I83: 46742245 | J83: CHACARITA | K83: COLABORACION | L83: IDENT. DE PERSONAS | N83: MATADEROS 94 | O83: Mataderos | P83: 0.6625 | Q83: 0.67361111 | R83: 0.67222222 | S83: - | T83: - | U83: - | V83: - | W83: SE TOMA CONOCIMIENTO MEDIANTE CARTA QUE HABRIA DOS MASCULINOS MERODEANDO LA ZONA E INTENTA SUSTRAERLE PERTENECIAS A SUS VECINOS. HT ID 2009086 INF NEGATIVO ILICITO EN EL LUGAR , SE IDENTIFICO MASCULINO LOS MISMO CORRESPONDE Y NO POSEEN /// | X83: 0 | Y83: 0 | Z83: 0 | AA83: 10C | AB83: U | AC83: CARTA | AF83: CARTA FINALIZADA | AH83: NO CARGA ORIGEN | AL83: =VLOOKUP(G83,Hoja2!P:Q,2,0) -> 10239 | AM83: =IF(OR(Y83>0,X83>0),"IMPUTADO","NADA") -> NADA | AN83: =IF(AND(AM83="IMPUTADO",ISBLANK(M83)),"FALTO","NO") -> NO
A84: 45992 | B84: =IF(AND(VALUE(P84)>=VALUE("06:00"),VALUE(P84)<=VALUE("17:59")),"06 A 18","18 A 06") -> 06 A 18 | C84: =IF(AND(VALUE(P84)>=VALUE("00:00"),VALUE(P84)<=VALUE("01:59")),"00:00 a 02:00",IF(AND(VALUE(P84)>=VALUE("02:00"),VALUE(P84)<=VALUE("03:59")),"02:00 a 04:00",IF(AND(VALUE(P84)>=VALUE("04:00"),VALUE(P84)<=VALUE("05:59")),"04:00 a 06:00",IF(AND(VALUE(P84)>=VALUE("06:00"),VALUE(P84)<=VALUE("07:59")),"06:00 a 08:00",IF(AND(VALUE(P84)>=VALUE("08:00"),VALUE(P84)<=VALUE("09:59")),"08:00 a 10:00",IF(AND(VALUE(P84)>=VALUE("10:00"),VALUE(P84)<=VALUE("11:59")),"10:00 a 12:00",IF(AND(VALUE(P84)>=VALUE("12:00"),VALUE(P84)<=VALUE("13:59")),"12:00 a 14:00",IF(AND(VALUE(P84)>=VALUE("14:00"),VALUE(P84)<=VALUE("15:59")),"14:00 a 16:00",IF(AND(VALUE(P84)>=VALUE("16:00"),VALUE(P84)<=VALUE("17:59")),"16:00 a 18:00",IF(AND(VALUE(P84)>=VALUE("18:00"),VALUE(P84)<=VALUE("19:59")),"18:00 a 20:00",IF(AND(VALUE(P84)>=VALUE("20:00"),VALUE(P84)<=VALUE("21:59")),"20:00 a 22:00",IF(AND(VALUE(P84)>=VALUE("22:00"),VALUE(P84)<=VALUE("23:59")),"22:00 a 00:00","no corresponde")))))))))))) -> 16:00 a 18:00 | D84: MARTINEZ. R | E84: MARTINEZ, VERONICA | F84: 1 | G84: CANALIS, LOANA ARIANA | H84: 921975 | I84: 46742428 | J84: VILLA LUGANO | K84: COLABORACION | L84: CHOQUE | M84: LESIONES | N84: MATADEROS 13/ ROSO 173 | O84: Mataderos | P84: 0.67847222 | Q84: 0.73125 | R84: 0.67847222 | S84: 0.68333333 | T84: - | U84: - | V84: - | W84: SE TOMA CONOCIMIENTO MEDIANTE CARTA SAE N°46742428 MASCULINO REFIERE QUE UN AUTO QUE HABRÍA ATROPELLADO A UN FEMENINO QUE HABRÍA CRUZADO MAL LA CALLE. 16:17 HS. SE TOMA CÁMARA MATADEROS13 EMPLAZADA EN J B ALBERDI 7274 Y ALTE LASSARRE VISUALIZANDO AL PERSONAL POLICIAL CON PERSONAS EN EL LUGAR. 16:24 HS. ARRIBA SAME. 16:29 HS. SE RETIRA SAME CON TRASLADO. 17:33 HS. QUEDA DE CONSIGNA EL PERSONAL POLICIAL EN LA ESPERA DE VIALES Y ALCOTEST DANDO POR FINALIZADO EL EVENTO. POSTERIORMENTE SE AMPLÍA POR CARTA SAE HTR031 INFORMA ARRIBO SAME INTERNO 419 EMILIO CASTRO A CARGO DEL DR. FRÍAS MATRICULA N°173277 DERIVA AL HOSPITAL SANTOJIANNI CON DIAGNOSTICO POLITRAUMATISMO LA MISMA VENIA CRUZANDO POR ALBERDI Y ES CUANDO ES COLISIONADA POR EL VEHÍCULO. MÓVIL 609A SE REALIZA CONSULTA CON LA UNIDA DE FLAGRANCIA SUR A CARGO DE LA DRA. BACHIADONE SECRETARIA ÚNICA SE LABRAN ACTUACIONES POR LESIONES 94. SE REALIZA CONSULTA CON LA UNIDAD DE FLAGRANCIA SUR A CARGO DE LA DRA. BACHIDONE DISPUSO REFERENTE AL MASCULINO NOTIFICADO 29/30. ESTE EVENTO FUE MONITOREADO POR LOANA CANALIS 45926523. | X84: 0 | Y84: 1 | Z84: 0 | AA84: 9A | AB84: U | AC84: CARTA | AF84: COLABORACION CON IMPUTADO/S | AH84: NO CARGAN IMPUTADOS | AL84: =VLOOKUP(G84,Hoja2!P:Q,2,0) -> 45926523 | AM84: =IF(OR(Y84>0,X84>0),"IMPUTADO","NADA") -> IMPUTADO | AN84: =IF(AND(AM84="IMPUTADO",ISBLANK(M84)),"FALTO","NO") -> NO
A85: 45992 | B85: =IF(AND(VALUE(P85)>=VALUE("06:00"),VALUE(P85)<=VALUE("17:59")),"06 A 18","18 A 06") -> 06 A 18 | C85: =IF(AND(VALUE(P85)>=VALUE("00:00"),VALUE(P85)<=VALUE("01:59")),"00:00 a 02:00",IF(AND(VALUE(P85)>=VALUE("02:00"),VALUE(P85)<=VALUE("03:59")),"02:00 a 04:00",IF(AND(VALUE(P85)>=VALUE("04:00"),VALUE(P85)<=VALUE("05:59")),"04:00 a 06:00",IF(AND(VALUE(P85)>=VALUE("06:00"),VALUE(P85)<=VALUE("07:59")),"06:00 a 08:00",IF(AND(VALUE(P85)>=VALUE("08:00"),VALUE(P85)<=VALUE("09:59")),"08:00 a 10:00",IF(AND(VALUE(P85)>=VALUE("10:00"),VALUE(P85)<=VALUE("11:59")),"10:00 a 12:00",IF(AND(VALUE(P85)>=VALUE("12:00"),VALUE(P85)<=VALUE("13:59")),"12:00 a 14:00",IF(AND(VALUE(P85)>=VALUE("14:00"),VALUE(P85)<=VALUE("15:59")),"14:00 a 16:00",IF(AND(VALUE(P85)>=VALUE("16:00"),VALUE(P85)<=VALUE("17:59")),"16:00 a 18:00",IF(AND(VALUE(P85)>=VALUE("18:00"),VALUE(P85)<=VALUE("19:59")),"18:00 a 20:00",IF(AND(VALUE(P85)>=VALUE("20:00"),VALUE(P85)<=VALUE("21:59")),"20:00 a 22:00",IF(AND(VALUE(P85)>=VALUE("22:00"),VALUE(P85)<=VALUE("23:59")),"22:00 a 00:00","no corresponde")))))))))))) -> 16:00 a 18:00 | D85: MARTINEZ. R | E85: ALCOBA, DIEGO | F85: 1 | G85: VELTRI, PAULA ANDREA | H85: 923590 | I85: 46742450 | J85: CHACARITA | K85: COLABORACION | L85: IDENT. DE PERSONAS | N85: BALVANERA 20 | O85: Balvanera | P85: 0.67708333 | Q85: 0.6875 | R85: 0.6875 | S85: - | T85: - | U85: - | V85: - | W85: SE TOMA CONOCIMIENTO MEDIANTE SISEP BAJO CONSTANCIA N° 46742450 QUE DENUNCIANTE REFIERE QUE ENTRÓ UNA PERSONA AL LOCAL PREGUNTANDO COSAS LA DENUNCIANTE FUE AL BAÑO Y ESCUCHÓ UN GRITO DE SU HIJA. EL MASCULINO AMENAZÓ CON ROBAR EL LOCAL. EL HOMBRE LE DIJO QUE TENÍA UN FIERRO. LA DENUNCIANTE SE LLAMA ROMINA ESTÁ CON LAS PERSIANAS BAJAS. ESTÁN ADENTRO EL HOMBRE ESTARÍA DANDO VUELTAS POR EL LUGAR. VISTE SHORT NEGRO CON GRIS, CAMPERA GRIS ,MOCHILA OSCURA Y UN TATUAJE CHICO EN LA CARA. SIENDO LAS 16:19 HS. SE VERIFICA CÁMARA BALVANERA20 EMPLAZADA EN RIVADAVIA 3098 Y GENERAL URQUIZA VISUALIZANDO UN MASCULINO DE SIMILARES CARACTERÍSTICAS CABELLO SEMI RAPADO, CAMPERA GRIS CON NEGRA ,SHORT NEGRO ,CON VENDA BLANCA EN PIERNA IZQUIERDA, CALZADO GRIS CON NEGRO Y MOCHILA OSCURA. POSTERIORMENTE SE RETIRA POR JEAN JAURES SENTIDO MITRE PERDIÉNDOSE DE LA VISUAL. POR LÍNEA DE TIEMPO NO SE LOGRA VISUALIZAR QUE ESTE MASCULINO INGRESE AL LOCAL MENCIONADO. 16:25 HS. SE VISUALIZA EL ARRIBO DE PERSONAL POLICIAL QUE SE DIRIGE EN MISMA DIRECCIÓN QUE EL MASCULINO. 16:31 HS. PERSONAL POLICIAL SE RETIRA DEL LUGAR NO DANDO CON EL MASCULINO. POR AMPLIACIÓN DE CARTA SAE GHT INFORMA NO SE LOGRA DAR CON MASCULINO DESCRIPTO. PANORAMA EXTERNO NORMAL. | X85: 0 | Y85: 0 | Z85: 0 | AA85: 3A | AB85: U | AC85: CARTA | AF85: CARTA FINALIZADA | AH85: NO CARGA ORIGEN | AL85: =VLOOKUP(G85,Hoja2!P:Q,2,0) -> 31821827 | AM85: =IF(OR(Y85>0,X85>0),"IMPUTADO","NADA") -> NADA | AN85: =IF(AND(AM85="IMPUTADO",ISBLANK(M85)),"FALTO","NO") -> NO
A86: 45992 | B86: =IF(AND(VALUE(P86)>=VALUE("06:00"),VALUE(P86)<=VALUE("17:59")),"06 A 18","18 A 06") -> 06 A 18 | C86: =IF(AND(VALUE(P86)>=VALUE("00:00"),VALUE(P86)<=VALUE("01:59")),"00:00 a 02:00",IF(AND(VALUE(P86)>=VALUE("02:00"),VALUE(P86)<=VALUE("03:59")),"02:00 a 04:00",IF(AND(VALUE(P86)>=VALUE("04:00"),VALUE(P86)<=VALUE("05:59")),"04:00 a 06:00",IF(AND(VALUE(P86)>=VALUE("06:00"),VALUE(P86)<=VALUE("07:59")),"06:00 a 08:00",IF(AND(VALUE(P86)>=VALUE("08:00"),VALUE(P86)<=VALUE("09:59")),"08:00 a 10:00",IF(AND(VALUE(P86)>=VALUE("10:00"),VALUE(P86)<=VALUE("11:59")),"10:00 a 12:00",IF(AND(VALUE(P86)>=VALUE("12:00"),VALUE(P86)<=VALUE("13:59")),"12:00 a 14:00",IF(AND(VALUE(P86)>=VALUE("14:00"),VALUE(P86)<=VALUE("15:59")),"14:00 a 16:00",IF(AND(VALUE(P86)>=VALUE("16:00"),VALUE(P86)<=VALUE("17:59")),"16:00 a 18:00",IF(AND(VALUE(P86)>=VALUE("18:00"),VALUE(P86)<=VALUE("19:59")),"18:00 a 20:00",IF(AND(VALUE(P86)>=VALUE("20:00"),VALUE(P86)<=VALUE("21:59")),"20:00 a 22:00",IF(AND(VALUE(P86)>=VALUE("22:00"),VALUE(P86)<=VALUE("23:59")),"22:00 a 00:00","no corresponde")))))))))))) -> 16:00 a 18:00 | D86: MARTINEZ. R | E86: MEZA, GASTON | F86: 1 | G86: GODOY RODRIGUEZ, LUCIA MARIA | H86: 918419 | I86: 46742481 | J86: CMU 9 DE JULIO | K86: APARENTE COMERCIALIZACION ESTUPEFACIENTES | N86: CONSTITUCION 74 | O86: Constitucion | P86: 0.67916667 | Q86: 0.68888889 | R86: 0.68125 | S86: - | T86: - | U86: - | V86: - | W86: SE VISUALIZA POR CAMARA CONSTITUCION 74 A UN FEMENINO APARENTEMENTE COMERCIALIZANDO ESTUPEFACIENTES . SE DA AVISO A COMANDO. ARRIBA PERSONAL POLICIAL. SE AMPLIA HT INF SE IDENTIFICO A UN FEMENINOS CON LAS DESCRIPCIONES APORTADAS POR MONITOREO,LA MISMAS CORRESPONDEN Y NO POSEE IMPEDIMENTOS,NO POSEE ELEMENTOS CONSTITUTIVOS DE DELITO.- | X86: 0 | Y86: 0 | Z86: 0 | AA86: 1C | AB86: U | AC86: MONITOREO | AF86: CARTA FINALIZADA | AL86: =VLOOKUP(G86,Hoja2!P:Q,2,0) -> 17212 | AM86: =IF(OR(Y86>0,X86>0),"IMPUTADO","NADA") -> NADA | AN86: =IF(AND(AM86="IMPUTADO",ISBLANK(M86)),"FALTO","NO") -> NO
A87: 45992 | B87: =IF(AND(VALUE(P87)>=VALUE("06:00"),VALUE(P87)<=VALUE("17:59")),"06 A 18","18 A 06") -> 06 A 18 | C87: =IF(AND(VALUE(P87)>=VALUE("00:00"),VALUE(P87)<=VALUE("01:59")),"00:00 a 02:00",IF(AND(VALUE(P87)>=VALUE("02:00"),VALUE(P87)<=VALUE("03:59")),"02:00 a 04:00",IF(AND(VALUE(P87)>=VALUE("04:00"),VALUE(P87)<=VALUE("05:59")),"04:00 a 06:00",IF(AND(VALUE(P87)>=VALUE("06:00"),VALUE(P87)<=VALUE("07:59")),"06:00 a 08:00",IF(AND(VALUE(P87)>=VALUE("08:00"),VALUE(P87)<=VALUE("09:59")),"08:00 a 10:00",IF(AND(VALUE(P87)>=VALUE("10:00"),VALUE(P87)<=VALUE("11:59")),"10:00 a 12:00",IF(AND(VALUE(P87)>=VALUE("12:00"),VALUE(P87)<=VALUE("13:59")),"12:00 a 14:00",IF(AND(VALUE(P87)>=VALUE("14:00"),VALUE(P87)<=VALUE("15:59")),"14:00 a 16:00",IF(AND(VALUE(P87)>=VALUE("16:00"),VALUE(P87)<=VALUE("17:59")),"16:00 a 18:00",IF(AND(VALUE(P87)>=VALUE("18:00"),VALUE(P87)<=VALUE("19:59")),"18:00 a 20:00",IF(AND(VALUE(P87)>=VALUE("20:00"),VALUE(P87)<=VALUE("21:59")),"20:00 a 22:00",IF(AND(VALUE(P87)>=VALUE("22:00"),VALUE(P87)<=VALUE("23:59")),"22:00 a 00:00","no corresponde")))))))))))) -> 16:00 a 18:00 | D87: MARTINEZ. R | E87: MOLINA, JOSE MANUEL | F87: 1 | G87: LURASCHI, IGNACIO | H87: 918109 | I87: 46742487 | J87: CHACARITA | K87: IDENTIFICACION DE PERSONAS | M87: CONT. LIMPIA VIDRIOS | N87: PALERMO 12 | O87: Palermo | P87: 0.67847222 | Q87: 0.70486111 | R87: 0.6875 | V87: - | W87: SE VISUALIZA MEDIANTE CAMARA PALERMO 12 A UN MASCULINO OFICIAR DE LIMPIAVIDRIOS EN LA VIA PUBLICA.-CMU AMPLIA EL MASCULINO VISTE GORRA BEIGE, REMERA AZUL, BERMUIDA OSCURA.- CMU AMPLIA SE VISUALIZA PERSONAL POLICIAL DANDO CON LA PERSONA.- MOTO INF SE IDENTIFICA AL MASC DNI 30603585 OSCAR DANIEL SE REALIZA CONS CON FISC GRAL A LA VOZ DEL PRO SECRETARIO BRUNO ACT POR ART 91 SE NOTIFICA DE 239 Y ACT POR ART 31 | X87: 1 | Y87: 0 | Z87: 0 | AA87: 14A | AB87: U | AC87: MONITOREO | AF87: FINALIZA CON IMPUTADO/S | AL87: =VLOOKUP(G87,Hoja2!P:Q,2,0) -> 43988966 | AM87: =IF(OR(Y87>0,X87>0),"IMPUTADO","NADA") -> IMPUTADO | AN87: =IF(AND(AM87="IMPUTADO",ISBLANK(M87)),"FALTO","NO") -> NO
A88: 45992 | B88: =IF(AND(VALUE(P88)>=VALUE("06:00"),VALUE(P88)<=VALUE("17:59")),"06 A 18","18 A 06") -> 06 A 18 | C88: =IF(AND(VALUE(P88)>=VALUE("00:00"),VALUE(P88)<=VALUE("01:59")),"00:00 a 02:00",IF(AND(VALUE(P88)>=VALUE("02:00"),VALUE(P88)<=VALUE("03:59")),"02:00 a 04:00",IF(AND(VALUE(P88)>=VALUE("04:00"),VALUE(P88)<=VALUE("05:59")),"04:00 a 06:00",IF(AND(VALUE(P88)>=VALUE("06:00"),VALUE(P88)<=VALUE("07:59")),"06:00 a 08:00",IF(AND(VALUE(P88)>=VALUE("08:00"),VALUE(P88)<=VALUE("09:59")),"08:00 a 10:00",IF(AND(VALUE(P88)>=VALUE("10:00"),VALUE(P88)<=VALUE("11:59")),"10:00 a 12:00",IF(AND(VALUE(P88)>=VALUE("12:00"),VALUE(P88)<=VALUE("13:59")),"12:00 a 14:00",IF(AND(VALUE(P88)>=VALUE("14:00"),VALUE(P88)<=VALUE("15:59")),"14:00 a 16:00",IF(AND(VALUE(P88)>=VALUE("16:00"),VALUE(P88)<=VALUE("17:59")),"16:00 a 18:00",IF(AND(VALUE(P88)>=VALUE("18:00"),VALUE(P88)<=VALUE("19:59")),"18:00 a 20:00",IF(AND(VALUE(P88)>=VALUE("20:00"),VALUE(P88)<=VALUE("21:59")),"20:00 a 22:00",IF(AND(VALUE(P88)>=VALUE("22:00"),VALUE(P88)<=VALUE("23:59")),"22:00 a 00:00","no corresponde")))))))))))) -> 16:00 a 18:00 | D88: MARTINEZ. R | E88: MEZA, GASTON | F88: 1 | G88: GODOY RODRIGUEZ, LUCIA MARIA | H88: 926224 | I88: 46742641 | J88: CMU 9 DE JULIO | K88: APARENTE COMERCIALIZACION ESTUPEFACIENTES | M88: LEY 23.737 | N88: CONSTITUCION O137 | O88: Constitucion | P88: 0.68263889 | Q88: 0.70208333 | R88: 0.69513889 | V88: - | W88: SE VISUALIZA A UN FEMENINO APARENTEMENTE COMERCIALIZANDO ESTUPEFACIENTES . CAMARA CONSTITUCION O137. ARRIBA PERSONAL POLICIAL DANDON CONE LO FEMENINO. SE AMPLIA MOVIL 601 INF SE REALIZO CONSULTA CON LA UNIDAD DE FLAGRANCIA ESTE AC DR MERCURIALI DISPUSO ACT POR LEY 23737. NOTIFICACION DE LOS ART 29 Y 30 SOLICITA VISTA FILMICA Y DECLACIONA DE CMU | X88: 0 | Y88: 1 | Z88: 0 | AA88: 1C | AB88: U | AC88: MONITOREO | AE88: 1 IMPUTADO | AF88: FINALIZA CON IMPUTADO/S | AL88: =VLOOKUP(G88,Hoja2!P:Q,2,0) -> 17212 | AM88: =IF(OR(Y88>0,X88>0),"IMPUTADO","NADA") -> IMPUTADO | AN88: =IF(AND(AM88="IMPUTADO",ISBLANK(M88)),"FALTO","NO") -> NO
A89: 45992 | B89: =IF(AND(VALUE(P89)>=VALUE("06:00"),VALUE(P89)<=VALUE("17:59")),"06 A 18","18 A 06") -> 06 A 18 | C89: =IF(AND(VALUE(P89)>=VALUE("00:00"),VALUE(P89)<=VALUE("01:59")),"00:00 a 02:00",IF(AND(VALUE(P89)>=VALUE("02:00"),VALUE(P89)<=VALUE("03:59")),"02:00 a 04:00",IF(AND(VALUE(P89)>=VALUE("04:00"),VALUE(P89)<=VALUE("05:59")),"04:00 a 06:00",IF(AND(VALUE(P89)>=VALUE("06:00"),VALUE(P89)<=VALUE("07:59")),"06:00 a 08:00",IF(AND(VALUE(P89)>=VALUE("08:00"),VALUE(P89)<=VALUE("09:59")),"08:00 a 10:00",IF(AND(VALUE(P89)>=VALUE("10:00"),VALUE(P89)<=VALUE("11:59")),"10:00 a 12:00",IF(AND(VALUE(P89)>=VALUE("12:00"),VALUE(P89)<=VALUE("13:59")),"12:00 a 14:00",IF(AND(VALUE(P89)>=VALUE("14:00"),VALUE(P89)<=VALUE("15:59")),"14:00 a 16:00",IF(AND(VALUE(P89)>=VALUE("16:00"),VALUE(P89)<=VALUE("17:59")),"16:00 a 18:00",IF(AND(VALUE(P89)>=VALUE("18:00"),VALUE(P89)<=VALUE("19:59")),"18:00 a 20:00",IF(AND(VALUE(P89)>=VALUE("20:00"),VALUE(P89)<=VALUE("21:59")),"20:00 a 22:00",IF(AND(VALUE(P89)>=VALUE("22:00"),VALUE(P89)<=VALUE("23:59")),"22:00 a 00:00","no corresponde")))))))))))) -> 16:00 a 18:00 | D89: MARTINEZ. R | E89: ARREGUI, FERNANDO | F89: 1 | G89: CANAGLIA CARREIRO, PATRICIA | H89: 918104 | I89: 46742649 | J89: CHACARITA | K89: COLABORACION | L89: CHOQUE | N89: PARQUE CHAS 09 | O89: Parque Chas | P89: 0.69305556 | Q89: 0.72083333 | R89: 0.69305556 | S89: 0.69305556 | T89: - | U89: - | V89: - | W89: SE VISUALIZA MEDIANTE CAMARA PARQUE CHAS 09 A PERSONAL DE SAME CON PERSONAL POLICIAL CON UN VEHICULO PARTICULAR Y COLECTIVO DETENIDOS EN EL LUGAR.- CMU AMPLIA SE VISUALIZA EL RETIRO DE SAME DEL LUGAR.- CMU AMPLIA SE VERIFICO LINEA DE TIEMPO POR EL DOMO NO LOGRANDO VISUALIZAR EL MOMENTO DE LA COLISION YA QUE LA CAMARA SE ENCUENTRA EN PATRON DE MOVIMIENTO Y CON LAS CAMARAS FIJAS NO APUNTAN HACIA EL QTH. | X89: 0 | Y89: 0 | Z89: 0 | AA89: 12C | AB89: U | AC89: MONITOREO | AF89: CARTA FINALIZADA | AL89: =VLOOKUP(G89,Hoja2!P:Q,2,0) -> 28460124 | AM89: =IF(OR(Y89>0,X89>0),"IMPUTADO","NADA") -> NADA | AN89: =IF(AND(AM89="IMPUTADO",ISBLANK(M89)),"FALTO","NO") -> NO
A90: 45992 | B90: =IF(AND(VALUE(P90)>=VALUE("06:00"),VALUE(P90)<=VALUE("17:59")),"06 A 18","18 A 06") -> 06 A 18 | C90: =IF(AND(VALUE(P90)>=VALUE("00:00"),VALUE(P90)<=VALUE("01:59")),"00:00 a 02:00",IF(AND(VALUE(P90)>=VALUE("02:00"),VALUE(P90)<=VALUE("03:59")),"02:00 a 04:00",IF(AND(VALUE(P90)>=VALUE("04:00"),VALUE(P90)<=VALUE("05:59")),"04:00 a 06:00",IF(AND(VALUE(P90)>=VALUE("06:00"),VALUE(P90)<=VALUE("07:59")),"06:00 a 08:00",IF(AND(VALUE(P90)>=VALUE("08:00"),VALUE(P90)<=VALUE("09:59")),"08:00 a 10:00",IF(AND(VALUE(P90)>=VALUE("10:00"),VALUE(P90)<=VALUE("11:59")),"10:00 a 12:00",IF(AND(VALUE(P90)>=VALUE("12:00"),VALUE(P90)<=VALUE("13:59")),"12:00 a 14:00",IF(AND(VALUE(P90)>=VALUE("14:00"),VALUE(P90)<=VALUE("15:59")),"14:00 a 16:00",IF(AND(VALUE(P90)>=VALUE("16:00"),VALUE(P90)<=VALUE("17:59")),"16:00 a 18:00",IF(AND(VALUE(P90)>=VALUE("18:00"),VALUE(P90)<=VALUE("19:59")),"18:00 a 20:00",IF(AND(VALUE(P90)>=VALUE("20:00"),VALUE(P90)<=VALUE("21:59")),"20:00 a 22:00",IF(AND(VALUE(P90)>=VALUE("22:00"),VALUE(P90)<=VALUE("23:59")),"22:00 a 00:00","no corresponde")))))))))))) -> 16:00 a 18:00 | D90: MARTINEZ. R | E90: MEZA, GASTON | F90: 1 | G90: CACERES, ANTONELA | H90: 926228 | I90: 46742651 | J90: CMU 9 DE JULIO | K90: TOTEM | L90: ROBO/HURTO | M90: ROBO/HURTO | N90: SAN TELMO 18 CAM 02_ | O90: San Telmo | P90: 0.7 | Q90: 0.70208333 | R90: 0.69861111 | V90: - | W90: SE TOMA CONOCIMIENTO MEDIANTE CARTA SAE LLAMANTE REFIERE QUE LE HABRIAN ROBADO EL MOTOVEHICULO HONDA FALCON 400 2012 COLOR GRIS CON CALCOMANIA DOMINIO 999IRE - SE AMPLIA LINEA DE TIEMPO POR CAMARA SAN TELMO 18 CAM 02_ SIENDO LAS 16:17 HS SE VISUALIZA EL PASO DE UN MASCULINO DE BUZO RALLADO VERDE Y NEGRO BERMUDA CELESTE ACARRIANDO UN MOTOVEHICULO POR JUAN DE GARAY DOBLANDO EN CHACABUCO | X90: 0 | Y90: 1 | Z90: 0 | AA90: 1F | AB90: U | AC90: CARTA | AF90: COLABORACION CON IMPUTADO/S | AL90: =VLOOKUP(G90,Hoja2!P:Q,2,0) -> 34999122 | AM90: =IF(OR(Y90>0,X90>0),"IMPUTADO","NADA") -> IMPUTADO | AN90: =IF(AND(AM90="IMPUTADO",ISBLANK(M90)),"FALTO","NO") -> NO
A91: 45992 | B91: =IF(AND(VALUE(P91)>=VALUE("06:00"),VALUE(P91)<=VALUE("17:59")),"06 A 18","18 A 06") -> 06 A 18 | C91: =IF(AND(VALUE(P91)>=VALUE("00:00"),VALUE(P91)<=VALUE("01:59")),"00:00 a 02:00",IF(AND(VALUE(P91)>=VALUE("02:00"),VALUE(P91)<=VALUE("03:59")),"02:00 a 04:00",IF(AND(VALUE(P91)>=VALUE("04:00"),VALUE(P91)<=VALUE("05:59")),"04:00 a 06:00",IF(AND(VALUE(P91)>=VALUE("06:00"),VALUE(P91)<=VALUE("07:59")),"06:00 a 08:00",IF(AND(VALUE(P91)>=VALUE("08:00"),VALUE(P91)<=VALUE("09:59")),"08:00 a 10:00",IF(AND(VALUE(P91)>=VALUE("10:00"),VALUE(P91)<=VALUE("11:59")),"10:00 a 12:00",IF(AND(VALUE(P91)>=VALUE("12:00"),VALUE(P91)<=VALUE("13:59")),"12:00 a 14:00",IF(AND(VALUE(P91)>=VALUE("14:00"),VALUE(P91)<=VALUE("15:59")),"14:00 a 16:00",IF(AND(VALUE(P91)>=VALUE("16:00"),VALUE(P91)<=VALUE("17:59")),"16:00 a 18:00",IF(AND(VALUE(P91)>=VALUE("18:00"),VALUE(P91)<=VALUE("19:59")),"18:00 a 20:00",IF(AND(VALUE(P91)>=VALUE("20:00"),VALUE(P91)<=VALUE("21:59")),"20:00 a 22:00",IF(AND(VALUE(P91)>=VALUE("22:00"),VALUE(P91)<=VALUE("23:59")),"22:00 a 00:00","no corresponde")))))))))))) -> 16:00 a 18:00 | D91: MARTINEZ. R | E91: MARTINEZ, VERONICA | F91: 1 | G91: NARANJO, JENNIFER | H91: 922096 | I91: 46742797 | J91: VILLA LUGANO | K91: COLABORACION | L91: CHOQUE | M91: LESIONES | N91: V. SOLDATI 21 CAM 01 | O91: Villa Soldati | P91: 0.70694444 | Q91: 0.75 | R91: 0.70694444 | S91: 0.71527778 | T91: - | U91: - | V91: - | W91: SE TOMA CONOCIMIENTO MEDIANTE FRECUENCIA HT PERSONAL POLICIAL SOLICITANDO AMBULANCIA DE SAME EN AVENIDA FERNANDEZ DE LA CRUZ Y AVENIDA VARELA POR UN CHOQUE EN EL LUGAR. 16:58HS. AL TOMAR LA CÁMARA VILLA SOLDATI 21 CAM 01 EMPLAZADA EN FERNANDEZ DE LA CRUZ 2400 Y RIVERA INDARTE SE VISUALIZA COLECTIVO Y CAMION EN EL LUGAR COMO ASÍ TAMBIÉN PERSONAL POLICIAL. SE DA AVISO A COMANDO MEDIANTE CARTA SAE N.º 46742797 BRINDADO APOYO ÓPTICO. SE REALIZÓ LINEA DE TIEMPO DE CAMARA VILLA SOLDATI 21 CAM 01 EMPLAZADA EN FERNANDEZ DE LA CRUZ 2400 Y RIVERA INDARTE SIENDO LAS 16:53HS. SE VISUALIZA A UN CAMIÓN EL CUAL COMIENZA SU MARCHA EN LA VERERA EN DIRECCION A FERNANDEZ DE LA CRUZ DOBLANDO EN ESTE SENTIDO A PERITO MORENO CUANDO UN COLECTIVO DE COLOR VERDE QUE TRANSITABA POR FERNANDEZ DE LA CRUZ SENTIDO A PERITO MORENO ES COLISIONADO EN EL LADO IZQUIERDO POR EL CAMIÓN MENCIONADO. 17:10HS. ARRIBA AMBULANCIA DE SAME. SE RETIRA AMBULANCIA DE SAME CON TRASLADO. 18:00HS. SE RETIRA MÓVIL POLICIAL DANDO POR FINALIZADO ESTE EVENTO. SE TOMA CONOCIMIENTO MEDIANTE AMPLIACIÓN DE CARTA SAE CONSULTA CON UNIDAD DE FLAGRANCIA OESTE A CARGO DOCTOR BERRIGUI CRISTIAN SECRETARIA UNICA A CARGO DOCTORA PALUMBO ACTUACIONES LESIONES 94 SE SOLCITA VIALES. EVENTO MONITOREADO POR NARNJO JENNIFER DNI 37542097 | X91: 0 | Y91: 1 | Z91: 0 | AA91: 7A | AB91: U | AC91: CARTA | AF91: COLABORACION CON IMPUTADO/S | AH91: NO CARGA IMPUTADOS | AL91: =VLOOKUP(G91,Hoja2!P:Q,2,0) -> 37542097 | AM91: =IF(OR(Y91>0,X91>0),"IMPUTADO","NADA") -> IMPUTADO | AN91: =IF(AND(AM91="IMPUTADO",ISBLANK(M91)),"FALTO","NO") -> NO
